Workbook
Name budget: 'Budget Dashboard'!$L1
Name budget_range: 'Budget Dashboard'!$Q1
Name budget_rank: 'Budget Dashboard'!$R1
Name cc_budget: Calculations!$K1
Name cc_delta: Calculations!$L1
Name cc_in_focus: Calculations!$G1
Name cc_month_number: Calculations!$F1
Name cc_show_remaining_budget: Calculations!$I1
Name cc_show_type: Calculations!$H1
Name cc_tracked: Calculations!$J1
Name cc_type: Calculations!$E1
Name comb_rank: 'Budget Dashboard'!$S1
Name comb_rank_norm: 'Budget Dashboard'!$U1
Name comb_rank_norm_run_range: 'Budget Dashboard'!$V1
Name comb_rank_range: 'Budget Dashboard'!$T1
Name comb_rank_unique: 'Budget Dashboard'!$W1
Name curren_date: TODAY()
Name expenses_header_row: ROW(Expenses[[#Headers],[ Expenses]])
Name expenses_max_row: MAX(ROW(Expenses[]))
Name expenses_min_row: MIN(ROW(Expenses[]))
Name expenses_total_row: ROW('Budget Planning'!$C$41)
Name header_row_id: 'Budget Dashboard'!$D1
Name Income_header_row: ROW(Income[[#Headers],[Income]])
Name income_max_row: MAX(ROW(Income[]))
Name income_min_row: MIN(ROW(Income[]))
Name income_total_row: ROW('Budget Planning'!$C$24)
Name is_cat: 'Budget Dashboard'!$F1
Name is_empty: 'Budget Dashboard'!$H1
Name is_header: 'Budget Dashboard'!$E1
Name is_total: 'Budget Dashboard'!$G1
Name item: 'Budget Dashboard'!$J1
Name item: 'Budget Dashboard'!$J1
Name out_budget: 'Budget Dashboard'!$AA1
Name out_percentage_completed: 'Budget Dashboard'!$AB1
Name out_tracked: 'Budget Dashboard'!$Z1
Name row_id: 'Budget Dashboard'!$C1
Name savings_header_row: ROW(Savings[[#Headers],[ Savings]])
Name savings_max_row: MAX(ROW(Savings[]))
Name savings_min_row: MIN(ROW(Savings[]))
Name savings_rate_calculation_type: Settings!$E$20
Name savings_total_row: ROW('Budget Planning'!$C$58)
Name selected_period: Calculations!$E$20
Name selected_period_display: Calculations!$E$21
Name selected_year: Calculations!$E$19
Name sort_max_row: 'Budget Dashboard'!$N1
Name sort_min_row: 'Budget Dashboard'!$M1
Name starting_year: Settings!$E$8
Name tracked: 'Budget Dashboard'!$K1
Name tracked_range: 'Budget Dashboard'!$O1
Name tracked_rank: 'Budget Dashboard'!$P1
Name type: 'Budget Dashboard'!$I1
Name type: 'Budget Dashboard'!$I$13

Sheet Settings
A1: Settings
C6: General
D8: Starting Year: | E8: 2026 | G8: Set the starting year (YYYY) once at the beginning and do not change it again
C17: Budget Tracking & Dashboard
D19: KPI Calculation in Dashboard | G19: Choose how you want the savings rate (SR) to be calculated in the dashboard KPI tiles:
D20: Savings Rate as % of Income: | E20: % allocated to Savings | G20: 1) Active Option (% allocated to Savings): SR = Savings / Income
G21: 2) Passive Option (% not allocated to Expenses): SR= (Income - Expenses) / Income

Sheet Budget Planning
A1: Budget Planning
C5: Define the starting year in the settings → | E5: =starting_year -> 2026 | S5: =E5+1 -> 2027 | AG5: =S5+1 -> 2028 | AU5: =AG5+1 -> 2029 | BI5: =AU5+1 -> 2030 | BW5: =BI5+1 -> 2031 | CK5: =BW5+1 -> 2032 | CY5: =CK5+1 -> 2033 | DM5: =CY5+1 -> 2034 | EA5: =DM5+1 -> 2035 | EO5: =EA5+1 -> 2036
E6: =IF(E7=0,"Jan✓","Jan") -> Jan | F6: =IF(F7=0,"Feb✓","Feb") -> Feb✓ | G6: =IF(G7=0,"Mar✓","Mar") -> Mar✓ | H6: =IF(H7=0,"Apr✓","Apr") -> Apr✓ | I6: =IF(I7=0,"May✓","May") -> May✓ | J6: =IF(J7=0,"Jun✓","Jun") -> Jun✓ | K6: =IF(K7=0,"Jul✓","Jul") -> Jul✓ | L6: =IF(L7=0,"Aug✓","Aug") -> Aug✓ | M6: =IF(M7=0,"Sep✓","Sep") -> Sep✓ | N6: =IF(N7=0,"Oct✓","Oct") -> Oct✓ | O6: =IF(O7=0,"Nov✓","Nov") -> Nov✓ | P6: =IF(P7=0,"Dec✓","Dec") -> Dec✓ | Q6: =IF(Q7=0,"Total✓","Total") -> Total | S6: =IF(S7=0,"Jan✓","Jan") -> Jan✓ | T6: =IF(T7=0,"Feb✓","Feb") -> Feb✓ | U6: =IF(U7=0,"Mar✓","Mar") -> Mar✓ | V6: =IF(V7=0,"Apr✓","Apr") -> Apr✓ | W6: =IF(W7=0,"May✓","May") -> May✓ | X6: =IF(X7=0,"Jun✓","Jun") -> Jun✓ | Y6: =IF(Y7=0,"Jul✓","Jul") -> Jul✓ | Z6: =IF(Z7=0,"Aug✓","Aug") -> Aug✓ | AA6: =IF(AA7=0,"Sep✓","Sep") -> Sep✓ | AB6: =IF(AB7=0,"Oct✓","Oct") -> Oct✓ | AC6: =IF(AC7=0,"Nov✓","Nov") -> Nov✓ | AD6: =IF(AD7=0,"Dec✓","Dec") -> Dec✓ | AE6: =IF(AE7=0,"Total✓","Total") -> Total✓ | AG6: =IF(AG7=0,"Jan✓","Jan") -> Jan✓ | AH6: =IF(AH7=0,"Feb✓","Feb") -> Feb✓ | AI6: =IF(AI7=0,"Mar✓","Mar") -> Mar✓ | AJ6: =IF(AJ7=0,"Apr✓","Apr") -> Apr✓ | AK6: =IF(AK7=0,"May✓","May") -> May✓ | AL6: =IF(AL7=0,"Jun✓","Jun") -> Jun✓ | AM6: =IF(AM7=0,"Jul✓","Jul") -> Jul✓ | AN6: =IF(AN7=0,"Aug✓","Aug") -> Aug✓ | AO6: =IF(AO7=0,"Sep✓","Sep") -> Sep✓ | AP6: =IF(AP7=0,"Oct✓","Oct") -> Oct✓ | AQ6: =IF(AQ7=0,"Nov✓","Nov") -> Nov✓ | AR6: =IF(AR7=0,"Dec✓","Dec") -> Dec✓ | AS6: =IF(AS7=0,"Total✓","Total") -> Total✓ | AU6: =IF(AU7=0,"Jan✓","Jan") -> Jan✓ | AV6: =IF(AV7=0,"Feb✓","Feb") -> Feb✓ | AW6: =IF(AW7=0,"Mar✓","Mar") -> Mar✓ | AX6: =IF(AX7=0,"Apr✓","Apr") -> Apr✓ | AY6: =IF(AY7=0,"May✓","May") -> May✓ | AZ6: =IF(AZ7=0,"Jun✓","Jun") -> Jun✓ | BA6: =IF(BA7=0,"Jul✓","Jul") -> Jul✓ | BB6: =IF(BB7=0,"Aug✓","Aug") -> Aug✓ | BC6: =IF(BC7=0,"Sep✓","Sep") -> Sep✓ | BD6: =IF(BD7=0,"Oct✓","Oct") -> Oct✓ | BE6: =IF(BE7=0,"Nov✓","Nov") -> Nov✓ | BF6: =IF(BF7=0,"Dec✓","Dec") -> Dec✓ | BG6: =IF(BG7=0,"Total✓","Total") -> Total✓ | BI6: =IF(BI7=0,"Jan✓","Jan") -> Jan✓ | BJ6: =IF(BJ7=0,"Feb✓","Feb") -> Feb✓ | BK6: =IF(BK7=0,"Mar✓","Mar") -> Mar✓ | BL6: =IF(BL7=0,"Apr✓","Apr") -> Apr✓ | BM6: =IF(BM7=0,"May✓","May") -> May✓ | BN6: =IF(BN7=0,"Jun✓","Jun") -> Jun✓ | BO6: =IF(BO7=0,"Jul✓","Jul") -> Jul✓ | BP6: =IF(BP7=0,"Aug✓","Aug") -> Aug✓ | BQ6: =IF(BQ7=0,"Sep✓","Sep") -> Sep✓ | BR6: =IF(BR7=0,"Oct✓","Oct") -> Oct✓ | BS6: =IF(BS7=0,"Nov✓","Nov") -> Nov✓ | BT6: =IF(BT7=0,"Dec✓","Dec") -> Dec✓ | BU6: =IF(BU7=0,"Total✓","Total") -> Total✓ | BW6: =IF(BW7=0,"Jan✓","Jan") -> Jan✓ | BX6: =IF(BX7=0,"Feb✓","Feb") -> Feb✓ | BY6: =IF(BY7=0,"Mar✓","Mar") -> Mar✓ | BZ6: =IF(BZ7=0,"Apr✓","Apr") -> Apr✓ | CA6: =IF(CA7=0,"May✓","May") -> May✓ | CB6: =IF(CB7=0,"Jun✓","Jun") -> Jun✓ | CC6: =IF(CC7=0,"Jul✓","Jul") -> Jul✓ | CD6: =IF(CD7=0,"Aug✓","Aug") -> Aug✓ | CE6: =IF(CE7=0,"Sep✓","Sep") -> Sep✓ | CF6: =IF(CF7=0,"Oct✓","Oct") -> Oct✓ | CG6: =IF(CG7=0,"Nov✓","Nov") -> Nov✓ | CH6: =IF(CH7=0,"Dec✓","Dec") -> Dec✓ | CI6: =IF(CI7=0,"Total✓","Total") -> Total✓ | CK6: =IF(CK7=0,"Jan✓","Jan") -> Jan✓ | CL6: =IF(CL7=0,"Feb✓","Feb") -> Feb✓ | CM6: =IF(CM7=0,"Mar✓","Mar") -> Mar✓ | CN6: =IF(CN7=0,"Apr✓","Apr") -> Apr✓ | CO6: =IF(CO7=0,"May✓","May") -> May✓ | CP6: =IF(CP7=0,"Jun✓","Jun") -> Jun✓ | CQ6: =IF(CQ7=0,"Jul✓","Jul") -> Jul✓ | CR6: =IF(CR7=0,"Aug✓","Aug") -> Aug✓ | CS6: =IF(CS7=0,"Sep✓","Sep") -> Sep✓ | CT6: =IF(CT7=0,"Oct✓","Oct") -> Oct✓ | CU6: =IF(CU7=0,"Nov✓","Nov") -> Nov✓ | CV6: =IF(CV7=0,"Dec✓","Dec") -> Dec✓ | CW6: =IF(CW7=0,"Total✓","Total") -> Total✓ | CY6: =IF(CY7=0,"Jan✓","Jan") -> Jan✓ | CZ6: =IF(CZ7=0,"Feb✓","Feb") -> Feb✓ | DA6: =IF(DA7=0,"Mar✓","Mar") -> Mar✓ | DB6: =IF(DB7=0,"Apr✓","Apr") -> Apr✓ | DC6: =IF(DC7=0,"May✓","May") -> May✓ | DD6: =IF(DD7=0,"Jun✓","Jun") -> Jun✓ | DE6: =IF(DE7=0,"Jul✓","Jul") -> Jul✓ | DF6: =IF(DF7=0,"Aug✓","Aug") -> Aug✓ | DG6: =IF(DG7=0,"Sep✓","Sep") -> Sep✓ | DH6: =IF(DH7=0,"Oct✓","Oct") -> Oct✓ | DI6: =IF(DI7=0,"Nov✓","Nov") -> Nov✓ | DJ6: =IF(DJ7=0,"Dec✓","Dec") -> Dec✓ | DK6: =IF(DK7=0,"Total✓","Total") -> Total✓ | DM6: =IF(DM7=0,"Jan✓","Jan") -> Jan✓ | DN6: =IF(DN7=0,"Feb✓","Feb") -> Feb✓ | DO6: =IF(DO7=0,"Mar✓","Mar") -> Mar✓ | DP6: =IF(DP7=0,"Apr✓","Apr") -> Apr✓ | DQ6: =IF(DQ7=0,"May✓","May") -> May✓ | DR6: =IF(DR7=0,"Jun✓","Jun") -> Jun✓ | DS6: =IF(DS7=0,"Jul✓","Jul") -> Jul✓ | DT6: =IF(DT7=0,"Aug✓","Aug") -> Aug✓ | DU6: =IF(DU7=0,"Sep✓","Sep") -> Sep✓ | DV6: =IF(DV7=0,"Oct✓","Oct") -> Oct✓ | DW6: =IF(DW7=0,"Nov✓","Nov") -> Nov✓ | DX6: =IF(DX7=0,"Dec✓","Dec") -> Dec✓ | DY6: =IF(DY7=0,"Total✓","Total") -> Total✓ | EA6: =IF(EA7=0,"Jan✓","Jan") -> Jan✓ | EB6: =IF(EB7=0,"Feb✓","Feb") -> Feb✓ | EC6: =IF(EC7=0,"Mar✓","Mar") -> Mar✓ | ED6: =IF(ED7=0,"Apr✓","Apr") -> Apr✓ | EE6: =IF(EE7=0,"May✓","May") -> May✓ | EF6: =IF(EF7=0,"Jun✓","Jun") -> Jun✓ | EG6: =IF(EG7=0,"Jul✓","Jul") -> Jul✓ | EH6: =IF(EH7=0,"Aug✓","Aug") -> Aug✓ | EI6: =IF(EI7=0,"Sep✓","Sep") -> Sep✓ | EJ6: =IF(EJ7=0,"Oct✓","Oct") -> Oct✓ | EK6: =IF(EK7=0,"Nov✓","Nov") -> Nov✓ | EL6: =IF(EL7=0,"Dec✓","Dec") -> Dec✓ | EM6: =IF(EM7=0,"Total✓","Total") -> Total✓ | EO6: =IF(EO7=0,"Jan✓","Jan") -> Jan✓ | EP6: =IF(EP7=0,"Feb✓","Feb") -> Feb✓ | EQ6: =IF(EQ7=0,"Mar✓","Mar") -> Mar✓ | ER6: =IF(ER7=0,"Apr✓","Apr") -> Apr✓ | ES6: =IF(ES7=0,"May✓","May") -> May✓ | ET6: =IF(ET7=0,"Jun✓","Jun") -> Jun✓ | EU6: =IF(EU7=0,"Jul✓","Jul") -> Jul✓ | EV6: =IF(EV7=0,"Aug✓","Aug") -> Aug✓ | EW6: =IF(EW7=0,"Sep✓","Sep") -> Sep✓ | EX6: =IF(EX7=0,"Oct✓","Oct") -> Oct✓ | EY6: =IF(EY7=0,"Nov✓","Nov") -> Nov✓ | EZ6: =IF(EZ7=0,"Dec✓","Dec") -> Dec✓ | FA6: =IF(FA7=0,"Total✓","Total") -> Total✓
C7: To be Allocated: | E7: =E24-(E41+E58) -> -4978 | F7: =F24-(F41+F58) -> 0 | G7: =G24-(G41+G58) -> 0 | H7: =H24-(H41+H58) -> 0 | I7: =I24-(I41+I58) -> 0 | J7: =J24-(J41+J58) -> 0 | K7: =K24-(K41+K58) -> 0 | L7: =L24-(L41+L58) -> 0 | ... Q7: =Q24-(Q41+Q58) -> -4978 | S7: =S24-(S41+S58) -> 0 | T7: =T24-(T41+T58) -> 0 | U7: =U24-(U41+U58) -> 0 | V7: =V24-(V41+V58) -> 0 | W7: =W24-(W41+W58) -> 0 | X7: =X24-(X41+X58) -> 0 | Y7: =Y24-(Y41+Y58) -> 0 | Z7: =Z24-(Z41+Z58) -> 0 | ... AE7: =AE24-(AE41+AE58) -> 0 | AG7: =AG24-(AG41+AG58) -> 0 | AH7: =AH24-(AH41+AH58) -> 0 | AI7: =AI24-(AI41+AI58) -> 0 | AJ7: =AJ24-(AJ41+AJ58) -> 0 | AK7: =AK24-(AK41+AK58) -> 0 | AL7: =AL24-(AL41+AL58) -> 0 | AM7: =AM24-(AM41+AM58) -> 0 | AN7: =AN24-(AN41+AN58) -> 0 | ... AS7: =AS24-(AS41+AS58) -> 0 | AU7: =AU24-(AU41+AU58) -> 0 | AV7: =AV24-(AV41+AV58) -> 0 | AW7: =AW24-(AW41+AW58) -> 0 | AX7: =AX24-(AX41+AX58) -> 0 | AY7: =AY24-(AY41+AY58) -> 0 | AZ7: =AZ24-(AZ41+AZ58) -> 0 | BA7: =BA24-(BA41+BA58) -> 0 | BB7: =BB24-(BB41+BB58) -> 0 | ... BG7: =BG24-(BG41+BG58) -> 0 | BI7: =BI24-(BI41+BI58) -> 0 | BJ7: =BJ24-(BJ41+BJ58) -> 0 | BK7: =BK24-(BK41+BK58) -> 0 | BL7: =BL24-(BL41+BL58) -> 0 | BM7: =BM24-(BM41+BM58) -> 0 | BN7: =BN24-(BN41+BN58) -> 0 | BO7: =BO24-(BO41+BO58) -> 0 | BP7: =BP24-(BP41+BP58) -> 0 | ... BU7: =BU24-(BU41+BU58) -> 0 | BW7: =BW24-(BW41+BW58) -> 0 | BX7: =BX24-(BX41+BX58) -> 0 | BY7: =BY24-(BY41+BY58) -> 0 | BZ7: =BZ24-(BZ41+BZ58) -> 0 | CA7: =CA24-(CA41+CA58) -> 0 | CB7: =CB24-(CB41+CB58) -> 0 | CC7: =CC24-(CC41+CC58) -> 0 | CD7: =CD24-(CD41+CD58) -> 0 | ... CI7: =CI24-(CI41+CI58) -> 0 | CK7: =CK24-(CK41+CK58) -> 0 | CL7: =CL24-(CL41+CL58) -> 0 | CM7: =CM24-(CM41+CM58) -> 0 | CN7: =CN24-(CN41+CN58) -> 0 | CO7: =CO24-(CO41+CO58) -> 0 | CP7: =CP24-(CP41+CP58) -> 0 | CQ7: =CQ24-(CQ41+CQ58) -> 0 | CR7: =CR24-(CR41+CR58) -> 0 | ... CW7: =CW24-(CW41+CW58) -> 0 | CY7: =CY24-(CY41+CY58) -> 0 | CZ7: =CZ24-(CZ41+CZ58) -> 0 | DA7: =DA24-(DA41+DA58) -> 0 | DB7: =DB24-(DB41+DB58) -> 0 | DC7: =DC24-(DC41+DC58) -> 0 | DD7: =DD24-(DD41+DD58) -> 0 | DE7: =DE24-(DE41+DE58) -> 0 | DF7: =DF24-(DF41+DF58) -> 0 | ... DK7: =DK24-(DK41+DK58) -> 0 | DM7: =DM24-(DM41+DM58) -> 0 | DN7: =DN24-(DN41+DN58) -> 0 | DO7: =DO24-(DO41+DO58) -> 0 | DP7: =DP24-(DP41+DP58) -> 0 | DQ7: =DQ24-(DQ41+DQ58) -> 0 | DR7: =DR24-(DR41+DR58) -> 0 | DS7: =DS24-(DS41+DS58) -> 0 | DT7: =DT24-(DT41+DT58) -> 0 | ... DY7: =DY24-(DY41+DY58) -> 0 | EA7: =EA24-(EA41+EA58) -> 0 | EB7: =EB24-(EB41+EB58) -> 0 | EC7: =EC24-(EC41+EC58) -> 0 | ED7: =ED24-(ED41+ED58) -> 0 | EE7: =EE24-(EE41+EE58) -> 0 | EF7: =EF24-(EF41+EF58) -> 0 | EG7: =EG24-(EG41+EG58) -> 0 | EH7: =EH24-(EH41+EH58) -> 0 | ... EM7: =EM24-(EM41+EM58) -> 0 | EO7: =EO24-(EO41+EO58) -> 0 | EP7: =EP24-(EP41+EP58) -> 0 | EQ7: =EQ24-(EQ41+EQ58) -> 0 | ER7: =ER24-(ER41+ER58) -> 0 | ES7: =ES24-(ES41+ES58) -> 0 | ET7: =ET24-(ET41+ET58) -> 0 | EU7: =EU24-(EU41+EU58) -> 0 | EV7: =EV24-(EV41+EV58) -> 0 | ... FA7: =FA24-(FA41+FA58) -> 0
C9: Income | E9: =DATE(E$5,1,1) -> 46023 | F9: =DATE(E$5,2,1) -> 46054 | G9: =DATE(E$5,3,1) -> 46082 | H9: =DATE(E$5,4,1) -> 46113 | I9: =DATE(E$5,5,1) -> 46143 | J9: =DATE(E$5,6,1) -> 46174 | K9: =DATE(E$5,7,1) -> 46204 | L9: =DATE(E$5,8,1) -> 46235 | M9: =DATE(E$5,9,1) -> 46266 | N9: =DATE(E$5,10,1) -> 46296 | O9: =DATE(E$5,11,1) -> 46327 | P9: =DATE(E$5,12,1) -> 46357 | Q9: =E$5 -> 2026 | S9: =DATE(S$5,1,1) -> 46388 | T9: =DATE(S$5,2,1) -> 46419 | U9: =DATE(S$5,3,1) -> 46447 | V9: =DATE(S$5,4,1) -> 46478 | W9: =DATE(S$5,5,1) -> 46508 | X9: =DATE(S$5,6,1) -> 46539 | Y9: =DATE(S$5,7,1) -> 46569 | Z9: =DATE(S$5,8,1) -> 46600 | AA9: =DATE(S$5,9,1) -> 46631 | AB9: =DATE(S$5,10,1) -> 46661 | AC9: =DATE(S$5,11,1) -> 46692 | AD9: =DATE(S$5,12,1) -> 46722 | AE9: =S$5 -> 2027 | AG9: =DATE(AG$5,1,1) -> 46753 | AH9: =DATE(AG$5,2,1) -> 46784 | AI9: =DATE(AG$5,3,1) -> 46813 | AJ9: =DATE(AG$5,4,1) -> 46844 | AK9: =DATE(AG$5,5,1) -> 46874 | AL9: =DATE(AG$5,6,1) -> 46905 | AM9: =DATE(AG$5,7,1) -> 46935 | AN9: =DATE(AG$5,8,1) -> 46966 | AO9: =DATE(AG$5,9,1) -> 46997 | AP9: =DATE(AG$5,10,1) -> 47027 | AQ9: =DATE(AG$5,11,1) -> 47058 | AR9: =DATE(AG$5,12,1) -> 47088 | AS9: =AG$5 -> 2028 | AU9: =DATE(AU$5,1,1) -> 47119 | AV9: =DATE(AU$5,2,1) -> 47150 | AW9: =DATE(AU$5,3,1) -> 47178 | AX9: =DATE(AU$5,4,1) -> 47209 | AY9: =DATE(AU$5,5,1) -> 47239 | AZ9: =DATE(AU$5,6,1) -> 47270 | BA9: =DATE(AU$5,7,1) -> 47300 | BB9: =DATE(AU$5,8,1) -> 47331 | BC9: =DATE(AU$5,9,1) -> 47362 | BD9: =DATE(AU$5,10,1) -> 47392 | BE9: =DATE(AU$5,11,1) -> 47423 | BF9: =DATE(AU$5,12,1) -> 47453 | BG9: =AU$5 -> 2029 | BI9: =DATE(BI$5,1,1) -> 47484 | BJ9: =DATE(BI$5,2,1) -> 47515 | BK9: =DATE(BI$5,3,1) -> 47543 | BL9: =DATE(BI$5,4,1) -> 47574 | BM9: =DATE(BI$5,5,1) -> 47604 | BN9: =DATE(BI$5,6,1) -> 47635 | BO9: =DATE(BI$5,7,1) -> 47665 | BP9: =DATE(BI$5,8,1) -> 47696 | BQ9: =DATE(BI$5,9,1) -> 47727 | BR9: =DATE(BI$5,10,1) -> 47757 | BS9: =DATE(BI$5,11,1) -> 47788 | BT9: =DATE(BI$5,12,1) -> 47818 | BU9: =BI$5 -> 2030 | BW9: =DATE(BW$5,1,1) -> 47849 | BX9: =DATE(BW$5,2,1) -> 47880 | BY9: =DATE(BW$5,3,1) -> 47908 | BZ9: =DATE(BW$5,4,1) -> 47939 | CA9: =DATE(BW$5,5,1) -> 47969 | CB9: =DATE(BW$5,6,1) -> 48000 | CC9: =DATE(BW$5,7,1) -> 48030 | CD9: =DATE(BW$5,8,1) -> 48061 | CE9: =DATE(BW$5,9,1) -> 48092 | CF9: =DATE(BW$5,10,1) -> 48122 | CG9: =DATE(BW$5,11,1) -> 48153 | CH9: =DATE(BW$5,12,1) -> 48183 | CI9: =BW$5 -> 2031 | CK9: =DATE(CK$5,1,1) -> 48214 | CL9: =DATE(CK$5,2,1) -> 48245 | CM9: =DATE(CK$5,3,1) -> 48274 | CN9: =DATE(CK$5,4,1) -> 48305 | CO9: =DATE(CK$5,5,1) -> 48335 | CP9: =DATE(CK$5,6,1) -> 48366 | CQ9: =DATE(CK$5,7,1) -> 48396 | CR9: =DATE(CK$5,8,1) -> 48427 | CS9: =DATE(CK$5,9,1) -> 48458 | CT9: =DATE(CK$5,10,1) -> 48488 | CU9: =DATE(CK$5,11,1) -> 48519 | CV9: =DATE(CK$5,12,1) -> 48549 | CW9: =CK$5 -> 2032 | CY9: =DATE(CY$5,1,1) -> 48580 | CZ9: =DATE(CY$5,2,1) -> 48611 | DA9: =DATE(CY$5,3,1) -> 48639 | DB9: =DATE(CY$5,4,1) -> 48670 | DC9: =DATE(CY$5,5,1) -> 48700 | DD9: =DATE(CY$5,6,1) -> 48731 | DE9: =DATE(CY$5,7,1) -> 48761 | DF9: =DATE(CY$5,8,1) -> 48792 | DG9: =DATE(CY$5,9,1) -> 48823 | DH9: =DATE(CY$5,10,1) -> 48853 | DI9: =DATE(CY$5,11,1) -> 48884 | DJ9: =DATE(CY$5,12,1) -> 48914 | DK9: =CY$5 -> 2033 | DM9: =DATE(DM$5,1,1) -> 48945 | DN9: =DATE(DM$5,2,1) -> 48976 | DO9: =DATE(DM$5,3,1) -> 49004 | DP9: =DATE(DM$5,4,1) -> 49035 | DQ9: =DATE(DM$5,5,1) -> 49065 | DR9: =DATE(DM$5,6,1) -> 49096 | DS9: =DATE(DM$5,7,1) -> 49126 | DT9: =DATE(DM$5,8,1) -> 49157 | DU9: =DATE(DM$5,9,1) -> 49188 | DV9: =DATE(DM$5,10,1) -> 49218 | DW9: =DATE(DM$5,11,1) -> 49249 | DX9: =DATE(DM$5,12,1) -> 49279 | DY9: =DM$5 -> 2034 | EA9: =DATE(EA$5,1,1) -> 49310 | EB9: =DATE(EA$5,2,1) -> 49341 | EC9: =DATE(EA$5,3,1) -> 49369 | ED9: =DATE(EA$5,4,1) -> 49400 | EE9: =DATE(EA$5,5,1) -> 49430 | EF9: =DATE(EA$5,6,1) -> 49461 | EG9: =DATE(EA$5,7,1) -> 49491 | EH9: =DATE(EA$5,8,1) -> 49522 | EI9: =DATE(EA$5,9,1) -> 49553 | EJ9: =DATE(EA$5,10,1) -> 49583 | EK9: =DATE(EA$5,11,1) -> 49614 | EL9: =DATE(EA$5,12,1) -> 49644 | EM9: =EA$5 -> 2035 | EO9: =DATE(EO$5,1,1) -> 49675 | EP9: =DATE(EO$5,2,1) -> 49706 | EQ9: =DATE(EO$5,3,1) -> 49735 | ER9: =DATE(EO$5,4,1) -> 49766 | ES9: =DATE(EO$5,5,1) -> 49796 | ET9: =DATE(EO$5,6,1) -> 49827 | EU9: =DATE(EO$5,7,1) -> 49857 | EV9: =DATE(EO$5,8,1) -> 49888 | EW9: =DATE(EO$5,9,1) -> 49919 | EX9: =DATE(EO$5,10,1) -> 49949 | EY9: =DATE(EO$5,11,1) -> 49980 | EZ9: =DATE(EO$5,12,1) -> 50010 | FA9: =EO$5 -> 2036
C10: Salary (Net) | E10: 25000 | F10: 80562 | G10: 80562 | H10: 80562 | I10: 80562 | J10: 80562 | K10: 80562 | L10: 80562 | M10: 80562 | N10: 80562 | O10: 80562 | P10: 80562 | Q10: =SUM(E10:P10) -> 911182 | AE10: =SUM(S10:AD10) -> 0 | AS10: =SUM(AG10:AR10) -> 0 | BG10: =SUM(AU10:BF10) -> 0 | BU10: =SUM(BI10:BT10) -> 0 | CI10: =SUM(BW10:CH10) -> 0 | CW10: =SUM(CK10:CV10) -> 0 | DK10: =SUM(CY10:DJ10) -> 0 | DY10: =SUM(DM10:DX10) -> 0 | EM10: =SUM(EA10:EL10) -> 0 | FA10: =SUM(EO10:EZ10) -> 0
C11: Side Hustle (Net) | E11: 950 | F11: 5672 | G11: 11084 | H11: 13467 | I11: 17631 | J11: 21021 | K11: 27087 | L11: 33084 | M11: 39765 | N11: 41098 | O11: 43897 | P11: 44567 | Q11: =SUM(E11:P11) -> 299323 | AE11: =SUM(S11:AD11) -> 0 | AS11: =SUM(AG11:AR11) -> 0 | BG11: =SUM(AU11:BF11) -> 0 | BU11: =SUM(BI11:BT11) -> 0 | CI11: =SUM(BW11:CH11) -> 0 | CW11: =SUM(CK11:CV11) -> 0 | DK11: =SUM(CY11:DJ11) -> 0 | DY11: =SUM(DM11:DX11) -> 0 | EM11: =SUM(EA11:EL11) -> 0 | FA11: =SUM(EO11:EZ11) -> 0
C12: Dividends (Net) | E12: 190 | F12: 120 | G12: 210 | H12: 70 | I12: 260 | J12: 220 | K12: 30 | L12: 70 | M12: 350 | N12: 290 | O12: 70 | P12: 50 | Q12: =SUM(E12:P12) -> 1930 | AE12: =SUM(S12:AD12) -> 0 | AS12: =SUM(AG12:AR12) -> 0 | BG12: =SUM(AU12:BF12) -> 0 | BU12: =SUM(BI12:BT12) -> 0 | CI12: =SUM(BW12:CH12) -> 0 | CW12: =SUM(CK12:CV12) -> 0 | DK12: =SUM(CY12:DJ12) -> 0 | DY12: =SUM(DM12:DX12) -> 0 | EM12: =SUM(EA12:EL12) -> 0 | FA12: =SUM(EO12:EZ12) -> 0
C13: Freelance (Net) | E13: 800 | F13: 2250 | G13: 7700 | H13: 8100 | I13: 9300 | J13: 9900 | K13: 10057 | L13: 11097 | M13: 12156 | N13: 13345 | O13: 13980 | P13: 14763 | Q13: =SUM(E13:P13) -> 113448 | AE13: =SUM(S13:AD13) -> 0 | AS13: =SUM(AG13:AR13) -> 0 | BG13: =SUM(AU13:BF13) -> 0 | BU13: =SUM(BI13:BT13) -> 0 | CI13: =SUM(BW13:CH13) -> 0 | CW13: =SUM(CK13:CV13) -> 0 | DK13: =SUM(CY13:DJ13) -> 0 | DY13: =SUM(DM13:DX13) -> 0 | EM13: =SUM(EA13:EL13) -> 0 | FA13: =SUM(EO13:EZ13) -> 0
C14: Other Income | Q14: =SUM(E14:P14) -> 0 | AE14: =SUM(S14:AD14) -> 0 | AS14: =SUM(AG14:AR14) -> 0 | BG14: =SUM(AU14:BF14) -> 0 | BU14: =SUM(BI14:BT14) -> 0 | CI14: =SUM(BW14:CH14) -> 0 | CW14: =SUM(CK14:CV14) -> 0 | DK14: =SUM(CY14:DJ14) -> 0 | DY14: =SUM(DM14:DX14) -> 0 | EM14: =SUM(EA14:EL14) -> 0 | FA14: =SUM(EO14:EZ14) -> 0
C15: Enter Income Category | Q15: =SUM(E15:P15) -> 0 | AE15: =SUM(S15:AD15) -> 0 | AS15: =SUM(AG15:AR15) -> 0 | BG15: =SUM(AU15:BF15) -> 0 | BU15: =SUM(BI15:BT15) -> 0 | CI15: =SUM(BW15:CH15) -> 0 | CW15: =SUM(CK15:CV15) -> 0 | DK15: =SUM(CY15:DJ15) -> 0 | DY15: =SUM(DM15:DX15) -> 0 | EM15: =SUM(EA15:EL15) -> 0 | FA15: =SUM(EO15:EZ15) -> 0
C16: Enter Income Category | Q16: =SUM(E16:P16) -> 0 | AE16: =SUM(S16:AD16) -> 0 | AS16: =SUM(AG16:AR16) -> 0 | BG16: =SUM(AU16:BF16) -> 0 | BU16: =SUM(BI16:BT16) -> 0 | CI16: =SUM(BW16:CH16) -> 0 | CW16: =SUM(CK16:CV16) -> 0 | DK16: =SUM(CY16:DJ16) -> 0 | DY16: =SUM(DM16:DX16) -> 0 | EM16: =SUM(EA16:EL16) -> 0 | FA16: =SUM(EO16:EZ16) -> 0
C17: Enter Income Category | Q17: =SUM(E17:P17) -> 0 | AE17: =SUM(S17:AD17) -> 0 | AS17: =SUM(AG17:AR17) -> 0 | BG17: =SUM(AU17:BF17) -> 0 | BU17: =SUM(BI17:BT17) -> 0 | CI17: =SUM(BW17:CH17) -> 0 | CW17: =SUM(CK17:CV17) -> 0 | DK17: =SUM(CY17:DJ17) -> 0 | DY17: =SUM(DM17:DX17) -> 0 | EM17: =SUM(EA17:EL17) -> 0 | FA17: =SUM(EO17:EZ17) -> 0
C18: Enter Income Category | Q18: =SUM(E18:P18) -> 0 | AE18: =SUM(S18:AD18) -> 0 | AS18: =SUM(AG18:AR18) -> 0 | BG18: =SUM(AU18:BF18) -> 0 | BU18: =SUM(BI18:BT18) -> 0 | CI18: =SUM(BW18:CH18) -> 0 | CW18: =SUM(CK18:CV18) -> 0 | DK18: =SUM(CY18:DJ18) -> 0 | DY18: =SUM(DM18:DX18) -> 0 | EM18: =SUM(EA18:EL18) -> 0 | FA18: =SUM(EO18:EZ18) -> 0
C19: Enter Income Category | Q19: =SUM(E19:P19) -> 0 | AE19: =SUM(S19:AD19) -> 0 | AS19: =SUM(AG19:AR19) -> 0 | BG19: =SUM(AU19:BF19) -> 0 | BU19: =SUM(BI19:BT19) -> 0 | CI19: =SUM(BW19:CH19) -> 0 | CW19: =SUM(CK19:CV19) -> 0 | DK19: =SUM(CY19:DJ19) -> 0 | DY19: =SUM(DM19:DX19) -> 0 | EM19: =SUM(EA19:EL19) -> 0 | FA19: =SUM(EO19:EZ19) -> 0
C20: Enter Income Category | Q20: =SUM(E20:P20) -> 0 | AE20: =SUM(S20:AD20) -> 0 | AS20: =SUM(AG20:AR20) -> 0 | BG20: =SUM(AU20:BF20) -> 0 | BU20: =SUM(BI20:BT20) -> 0 | CI20: =SUM(BW20:CH20) -> 0 | CW20: =SUM(CK20:CV20) -> 0 | DK20: =SUM(CY20:DJ20) -> 0 | DY20: =SUM(DM20:DX20) -> 0 | EM20: =SUM(EA20:EL20) -> 0 | FA20: =SUM(EO20:EZ20) -> 0
C21: Enter Income Category | Q21: =SUM(E21:P21) -> 0 | AE21: =SUM(S21:AD21) -> 0 | AS21: =SUM(AG21:AR21) -> 0 | BG21: =SUM(AU21:BF21) -> 0 | BU21: =SUM(BI21:BT21) -> 0 | CI21: =SUM(BW21:CH21) -> 0 | CW21: =SUM(CK21:CV21) -> 0 | DK21: =SUM(CY21:DJ21) -> 0 | DY21: =SUM(DM21:DX21) -> 0 | EM21: =SUM(EA21:EL21) -> 0 | FA21: =SUM(EO21:EZ21) -> 0
C22: Enter Income Category | Q22: =SUM(E22:P22) -> 0 | AE22: =SUM(S22:AD22) -> 0 | AS22: =SUM(AG22:AR22) -> 0 | BG22: =SUM(AU22:BF22) -> 0 | BU22: =SUM(BI22:BT22) -> 0 | CI22: =SUM(BW22:CH22) -> 0 | CW22: =SUM(CK22:CV22) -> 0 | DK22: =SUM(CY22:DJ22) -> 0 | DY22: =SUM(DM22:DX22) -> 0 | EM22: =SUM(EA22:EL22) -> 0 | FA22: =SUM(EO22:EZ22) -> 0
C23: Other Income | Q23: =SUM(E23:P23) -> 0 | AE23: =SUM(S23:AD23) -> 0 | AS23: =SUM(AG23:AR23) -> 0 | BG23: =SUM(AU23:BF23) -> 0 | BU23: =SUM(BI23:BT23) -> 0 | CI23: =SUM(BW23:CH23) -> 0 | CW23: =SUM(CK23:CV23) -> 0 | DK23: =SUM(CY23:DJ23) -> 0 | DY23: =SUM(DM23:DX23) -> 0 | EM23: =SUM(EA23:EL23) -> 0 | FA23: =SUM(EO23:EZ23) -> 0
C24: Total | E24: {=SUM(INDIRECT(ADDRESS(income_min_row,COLUMN()) &":"& ADDRESS(income_max_row,COLUMN())))} -> 26940 | F24: {=SUM(INDIRECT(ADDRESS(income_min_row,COLUMN()) &":"& ADDRESS(income_max_row,COLUMN())))} -> 88604 | G24: {=SUM(INDIRECT(ADDRESS(income_min_row,COLUMN()) &":"& ADDRESS(income_max_row,COLUMN())))} -> 99556 | H24: {=SUM(INDIRECT(ADDRESS(income_min_row,COLUMN()) &":"& ADDRESS(income_max_row,COLUMN())))} -> 102199 | I24: {=SUM(INDIRECT(ADDRESS(income_min_row,COLUMN()) &":"& ADDRESS(income_max_row,COLUMN())))} -> 107753 | J24: {=SUM(INDIRECT(ADDRESS(income_min_row,COLUMN()) &":"& ADDRESS(income_max_row,COLUMN())))} -> 111703 | K24: {=SUM(INDIRECT(ADDRESS(income_min_row,COLUMN()) &":"& ADDRESS(income_max_row,COLUMN())))} -> 117736 | L24: {=SUM(INDIRECT(ADDRESS(income_min_row,COLUMN()) &":"& ADDRESS(income_max_row,COLUMN())))} -> 124813 | ... Q24: {=SUM(INDIRECT(ADDRESS(income_min_row,COLUMN()) &":"& ADDRESS(income_max_row,COLUMN())))} -> 1325883 | S24: {=SUM(INDIRECT(ADDRESS(income_min_row,COLUMN()) &":"& ADDRESS(income_max_row,COLUMN())))} -> 0 | T24: {=SUM(INDIRECT(ADDRESS(income_min_row,COLUMN()) &":"& ADDRESS(income_max_row,COLUMN())))} -> 0 | U24: {=SUM(INDIRECT(ADDRESS(income_min_row,COLUMN()) &":"& ADDRESS(income_max_row,COLUMN())))} -> 0 | V24: {=SUM(INDIRECT(ADDRESS(income_min_row,COLUMN()) &":"& ADDRESS(income_max_row,COLUMN())))} -> 0 | W24: {=SUM(INDIRECT(ADDRESS(income_min_row,COLUMN()) &":"& ADDRESS(income_max_row,COLUMN())))} -> 0 | X24: {=SUM(INDIRECT(ADDRESS(income_min_row,COLUMN()) &":"& ADDRESS(income_max_row,COLUMN())))} -> 0 | Y24: {=SUM(INDIRECT(ADDRESS(income_min_row,COLUMN()) &":"& ADDRESS(income_max_row,COLUMN())))} -> 0 | Z24: {=SUM(INDIRECT(ADDRESS(income_min_row,COLUMN()) &":"& ADDRESS(income_max_row,COLUMN())))} -> 0 | ... AE24: {=SUM(INDIRECT(ADDRESS(income_min_row,COLUMN()) &":"& ADDRESS(income_max_row,COLUMN())))} -> 0 | AG24: {=SUM(INDIRECT(ADDRESS(income_min_row,COLUMN()) &":"& ADDRESS(income_max_row,COLUMN())))} -> 0 | AH24: {=SUM(INDIRECT(ADDRESS(income_min_row,COLUMN()) &":"& ADDRESS(income_max_row,COLUMN())))} -> 0 | AI24: {=SUM(INDIRECT(ADDRESS(income_min_row,COLUMN()) &":"& ADDRESS(income_max_row,COLUMN())))} -> 0 | AJ24: {=SUM(INDIRECT(ADDRESS(income_min_row,COLUMN()) &":"& ADDRESS(income_max_row,COLUMN())))} -> 0 | AK24: {=SUM(INDIRECT(ADDRESS(income_min_row,COLUMN()) &":"& ADDRESS(income_max_row,COLUMN())))} -> 0 | AL24: {=SUM(INDIRECT(ADDRESS(income_min_row,COLUMN()) &":"& ADDRESS(income_max_row,COLUMN())))} -> 0 | AM24: {=SUM(INDIRECT(ADDRESS(income_min_row,COLUMN()) &":"& ADDRESS(income_max_row,COLUMN())))} -> 0 | AN24: {=SUM(INDIRECT(ADDRESS(income_min_row,COLUMN()) &":"& ADDRESS(income_max_row,COLUMN())))} -> 0 | ... AS24: {=SUM(INDIRECT(ADDRESS(income_min_row,COLUMN()) &":"& ADDRESS(income_max_row,COLUMN())))} -> 0 | AU24: {=SUM(INDIRECT(ADDRESS(income_min_row,COLUMN()) &":"& ADDRESS(income_max_row,COLUMN())))} -> 0 | AV24: {=SUM(INDIRECT(ADDRESS(income_min_row,COLUMN()) &":"& ADDRESS(income_max_row,COLUMN())))} -> 0 | AW24: {=SUM(INDIRECT(ADDRESS(income_min_row,COLUMN()) &":"& ADDRESS(income_max_row,COLUMN())))} -> 0 | AX24: {=SUM(INDIRECT(ADDRESS(income_min_row,COLUMN()) &":"& ADDRESS(income_max_row,COLUMN())))} -> 0 | AY24: {=SUM(INDIRECT(ADDRESS(income_min_row,COLUMN()) &":"& ADDRESS(income_max_row,COLUMN())))} -> 0 | AZ24: {=SUM(INDIRECT(ADDRESS(income_min_row,COLUMN()) &":"& ADDRESS(income_max_row,COLUMN())))} -> 0 | BA24: {=SUM(INDIRECT(ADDRESS(income_min_row,COLUMN()) &":"& ADDRESS(income_max_row,COLUMN())))} -> 0 | BB24: {=SUM(INDIRECT(ADDRESS(income_min_row,COLUMN()) &":"& ADDRESS(income_max_row,COLUMN())))} -> 0 | ... BG24: {=SUM(INDIRECT(ADDRESS(income_min_row,COLUMN()) &":"& ADDRESS(income_max_row,COLUMN())))} -> 0 | BI24: {=SUM(INDIRECT(ADDRESS(income_min_row,COLUMN()) &":"& ADDRESS(income_max_row,COLUMN())))} -> 0 | BJ24: {=SUM(INDIRECT(ADDRESS(income_min_row,COLUMN()) &":"& ADDRESS(income_max_row,COLUMN())))} -> 0 | BK24: {=SUM(INDIRECT(ADDRESS(income_min_row,COLUMN()) &":"& ADDRESS(income_max_row,COLUMN())))} -> 0 | BL24: {=SUM(INDIRECT(ADDRESS(income_min_row,COLUMN()) &":"& ADDRESS(income_max_row,COLUMN())))} -> 0 | BM24: {=SUM(INDIRECT(ADDRESS(income_min_row,COLUMN()) &":"& ADDRESS(income_max_row,COLUMN())))} -> 0 | BN24: {=SUM(INDIRECT(ADDRESS(income_min_row,COLUMN()) &":"& ADDRESS(income_max_row,COLUMN())))} -> 0 | BO24: {=SUM(INDIRECT(ADDRESS(income_min_row,COLUMN()) &":"& ADDRESS(income_max_row,COLUMN())))} -> 0 | BP24: {=SUM(INDIRECT(ADDRESS(income_min_row,COLUMN()) &":"& ADDRESS(income_max_row,COLUMN())))} -> 0 | ... BU24: {=SUM(INDIRECT(ADDRESS(income_min_row,COLUMN()) &":"& ADDRESS(income_max_row,COLUMN())))} -> 0 | BW24: {=SUM(INDIRECT(ADDRESS(income_min_row,COLUMN()) &":"& ADDRESS(income_max_row,COLUMN())))} -> 0 | BX24: {=SUM(INDIRECT(ADDRESS(income_min_row,COLUMN()) &":"& ADDRESS(income_max_row,COLUMN())))} -> 0 | BY24: {=SUM(INDIRECT(ADDRESS(income_min_row,COLUMN()) &":"& ADDRESS(income_max_row,COLUMN())))} -> 0 | BZ24: {=SUM(INDIRECT(ADDRESS(income_min_row,COLUMN()) &":"& ADDRESS(income_max_row,COLUMN())))} -> 0 | CA24: {=SUM(INDIRECT(ADDRESS(income_min_row,COLUMN()) &":"& ADDRESS(income_max_row,COLUMN())))} -> 0 | CB24: {=SUM(INDIRECT(ADDRESS(income_min_row,COLUMN()) &":"& ADDRESS(income_max_row,COLUMN())))} -> 0 | CC24: {=SUM(INDIRECT(ADDRESS(income_min_row,COLUMN()) &":"& ADDRESS(income_max_row,COLUMN())))} -> 0 | CD24: {=SUM(INDIRECT(ADDRESS(income_min_row,COLUMN()) &":"& ADDRESS(income_max_row,COLUMN())))} -> 0 | ... CI24: {=SUM(INDIRECT(ADDRESS(income_min_row,COLUMN()) &":"& ADDRESS(income_max_row,COLUMN())))} -> 0 | CK24: {=SUM(INDIRECT(ADDRESS(income_min_row,COLUMN()) &":"& ADDRESS(income_max_row,COLUMN())))} -> 0 | CL24: {=SUM(INDIRECT(ADDRESS(income_min_row,COLUMN()) &":"& ADDRESS(income_max_row,COLUMN())))} -> 0 | CM24: {=SUM(INDIRECT(ADDRESS(income_min_row,COLUMN()) &":"& ADDRESS(income_max_row,COLUMN())))} -> 0 | CN24: {=SUM(INDIRECT(ADDRESS(income_min_row,COLUMN()) &":"& ADDRESS(income_max_row,COLUMN())))} -> 0 | CO24: {=SUM(INDIRECT(ADDRESS(income_min_row,COLUMN()) &":"& ADDRESS(income_max_row,COLUMN())))} -> 0 | CP24: {=SUM(INDIRECT(ADDRESS(income_min_row,COLUMN()) &":"& ADDRESS(income_max_row,COLUMN())))} -> 0 | CQ24: {=SUM(INDIRECT(ADDRESS(income_min_row,COLUMN()) &":"& ADDRESS(income_max_row,COLUMN())))} -> 0 | CR24: {=SUM(INDIRECT(ADDRESS(income_min_row,COLUMN()) &":"& ADDRESS(income_max_row,COLUMN())))} -> 0 | ... CW24: {=SUM(INDIRECT(ADDRESS(income_min_row,COLUMN()) &":"& ADDRESS(income_max_row,COLUMN())))} -> 0 | CY24: {=SUM(INDIRECT(ADDRESS(income_min_row,COLUMN()) &":"& ADDRESS(income_max_row,COLUMN())))} -> 0 | CZ24: {=SUM(INDIRECT(ADDRESS(income_min_row,COLUMN()) &":"& ADDRESS(income_max_row,COLUMN())))} -> 0 | DA24: {=SUM(INDIRECT(ADDRESS(income_min_row,COLUMN()) &":"& ADDRESS(income_max_row,COLUMN())))} -> 0 | DB24: {=SUM(INDIRECT(ADDRESS(income_min_row,COLUMN()) &":"& ADDRESS(income_max_row,COLUMN())))} -> 0 | DC24: {=SUM(INDIRECT(ADDRESS(income_min_row,COLUMN()) &":"& ADDRESS(income_max_row,COLUMN())))} -> 0 | DD24: {=SUM(INDIRECT(ADDRESS(income_min_row,COLUMN()) &":"& ADDRESS(income_max_row,COLUMN())))} -> 0 | DE24: {=SUM(INDIRECT(ADDRESS(income_min_row,COLUMN()) &":"& ADDRESS(income_max_row,COLUMN())))} -> 0 | DF24: {=SUM(INDIRECT(ADDRESS(income_min_row,COLUMN()) &":"& ADDRESS(income_max_row,COLUMN())))} -> 0 | ... DK24: {=SUM(INDIRECT(ADDRESS(income_min_row,COLUMN()) &":"& ADDRESS(income_max_row,COLUMN())))} -> 0 | DM24: {=SUM(INDIRECT(ADDRESS(income_min_row,COLUMN()) &":"& ADDRESS(income_max_row,COLUMN())))} -> 0 | DN24: {=SUM(INDIRECT(ADDRESS(income_min_row,COLUMN()) &":"& ADDRESS(income_max_row,COLUMN())))} -> 0 | DO24: {=SUM(INDIRECT(ADDRESS(income_min_row,COLUMN()) &":"& ADDRESS(income_max_row,COLUMN())))} -> 0 | DP24: {=SUM(INDIRECT(ADDRESS(income_min_row,COLUMN()) &":"& ADDRESS(income_max_row,COLUMN())))} -> 0 | DQ24: {=SUM(INDIRECT(ADDRESS(income_min_row,COLUMN()) &":"& ADDRESS(income_max_row,COLUMN())))} -> 0 | DR24: {=SUM(INDIRECT(ADDRESS(income_min_row,COLUMN()) &":"& ADDRESS(income_max_row,COLUMN())))} -> 0 | DS24: {=SUM(INDIRECT(ADDRESS(income_min_row,COLUMN()) &":"& ADDRESS(income_max_row,COLUMN())))} -> 0 | DT24: {=SUM(INDIRECT(ADDRESS(income_min_row,COLUMN()) &":"& ADDRESS(income_max_row,COLUMN())))} -> 0 | ... DY24: {=SUM(INDIRECT(ADDRESS(income_min_row,COLUMN()) &":"& ADDRESS(income_max_row,COLUMN())))} -> 0 | EA24: {=SUM(INDIRECT(ADDRESS(income_min_row,COLUMN()) &":"& ADDRESS(income_max_row,COLUMN())))} -> 0 | EB24: {=SUM(INDIRECT(ADDRESS(income_min_row,COLUMN()) &":"& ADDRESS(income_max_row,COLUMN())))} -> 0 | EC24: {=SUM(INDIRECT(ADDRESS(income_min_row,COLUMN()) &":"& ADDRESS(income_max_row,COLUMN())))} -> 0 | ED24: {=SUM(INDIRECT(ADDRESS(income_min_row,COLUMN()) &":"& ADDRESS(income_max_row,COLUMN())))} -> 0 | EE24: {=SUM(INDIRECT(ADDRESS(income_min_row,COLUMN()) &":"& ADDRESS(income_max_row,COLUMN())))} -> 0 | EF24: {=SUM(INDIRECT(ADDRESS(income_min_row,COLUMN()) &":"& ADDRESS(income_max_row,COLUMN())))} -> 0 | EG24: {=SUM(INDIRECT(ADDRESS(income_min_row,COLUMN()) &":"& ADDRESS(income_max_row,COLUMN())))} -> 0 | EH24: {=SUM(INDIRECT(ADDRESS(income_min_row,COLUMN()) &":"& ADDRESS(income_max_row,COLUMN())))} -> 0 | ... EM24: {=SUM(INDIRECT(ADDRESS(income_min_row,COLUMN()) &":"& ADDRESS(income_max_row,COLUMN())))} -> 0 | EO24: {=SUM(INDIRECT(ADDRESS(income_min_row,COLUMN()) &":"& ADDRESS(income_max_row,COLUMN())))} -> 0 | EP24: {=SUM(INDIRECT(ADDRESS(income_min_row,COLUMN()) &":"& ADDRESS(income_max_row,COLUMN())))} -> 0 | EQ24: {=SUM(INDIRECT(ADDRESS(income_min_row,COLUMN()) &":"& ADDRESS(income_max_row,COLUMN())))} -> 0 | ER24: {=SUM(INDIRECT(ADDRESS(income_min_row,COLUMN()) &":"& ADDRESS(income_max_row,COLUMN())))} -> 0 | ES24: {=SUM(INDIRECT(ADDRESS(income_min_row,COLUMN()) &":"& ADDRESS(income_max_row,COLUMN())))} -> 0 | ET24: {=SUM(INDIRECT(ADDRESS(income_min_row,COLUMN()) &":"& ADDRESS(income_max_row,COLUMN())))} -> 0 | EU24: {=SUM(INDIRECT(ADDRESS(income_min_row,COLUMN()) &":"& ADDRESS(income_max_row,COLUMN())))} -> 0 | EV24: {=SUM(INDIRECT(ADDRESS(income_min_row,COLUMN()) &":"& ADDRESS(income_max_row,COLUMN())))} -> 0 | ... FA24: {=SUM(INDIRECT(ADDRESS(income_min_row,COLUMN()) &":"& ADDRESS(income_max_row,COLUMN())))} -> 0
C26: Expenses | E26: =DATE(E$5,1,1) -> 46023 | F26: =DATE(E$5,2,1) -> 46054 | G26: =DATE(E$5,3,1) -> 46082 | H26: =DATE(E$5,4,1) -> 46113 | I26: =DATE(E$5,5,1) -> 46143 | J26: =DATE(E$5,6,1) -> 46174 | K26: =DATE(E$5,7,1) -> 46204 | L26: =DATE(E$5,8,1) -> 46235 | M26: =DATE(E$5,9,1) -> 46266 | N26: =DATE(E$5,10,1) -> 46296 | O26: =DATE(E$5,11,1) -> 46327 | P26: =DATE(E$5,12,1) -> 46357 | Q26: =E$5 -> 2026 | S26: =DATE(S$5,1,1) -> 46388 | T26: =DATE(S$5,2,1) -> 46419 | U26: =DATE(S$5,3,1) -> 46447 | V26: =DATE(S$5,4,1) -> 46478 | W26: =DATE(S$5,5,1) -> 46508 | X26: =DATE(S$5,6,1) -> 46539 | Y26: =DATE(S$5,7,1) -> 46569 | Z26: =DATE(S$5,8,1) -> 46600 | AA26: =DATE(S$5,9,1) -> 46631 | AB26: =DATE(S$5,10,1) -> 46661 | AC26: =DATE(S$5,11,1) -> 46692 | AD26: =DATE(S$5,12,1) -> 46722 | AE26: =S$5 -> 2027 | AG26: =DATE(AG$5,1,1) -> 46753 | AH26: =DATE(AG$5,2,1) -> 46784 | AI26: =DATE(AG$5,3,1) -> 46813 | AJ26: =DATE(AG$5,4,1) -> 46844 | AK26: =DATE(AG$5,5,1) -> 46874 | AL26: =DATE(AG$5,6,1) -> 46905 | AM26: =DATE(AG$5,7,1) -> 46935 | AN26: =DATE(AG$5,8,1) -> 46966 | AO26: =DATE(AG$5,9,1) -> 46997 | AP26: =DATE(AG$5,10,1) -> 47027 | AQ26: =DATE(AG$5,11,1) -> 47058 | AR26: =DATE(AG$5,12,1) -> 47088 | AS26: =AG$5 -> 2028 | AU26: =DATE(AU$5,1,1) -> 47119 | AV26: =DATE(AU$5,2,1) -> 47150 | AW26: =DATE(AU$5,3,1) -> 47178 | AX26: =DATE(AU$5,4,1) -> 47209 | AY26: =DATE(AU$5,5,1) -> 47239 | AZ26: =DATE(AU$5,6,1) -> 47270 | BA26: =DATE(AU$5,7,1) -> 47300 | BB26: =DATE(AU$5,8,1) -> 47331 | BC26: =DATE(AU$5,9,1) -> 47362 | BD26: =DATE(AU$5,10,1) -> 47392 | BE26: =DATE(AU$5,11,1) -> 47423 | BF26: =DATE(AU$5,12,1) -> 47453 | BG26: =AU$5 -> 2029 | BI26: =DATE(BI$5,1,1) -> 47484 | BJ26: =DATE(BI$5,2,1) -> 47515 | BK26: =DATE(BI$5,3,1) -> 47543 | BL26: =DATE(BI$5,4,1) -> 47574 | BM26: =DATE(BI$5,5,1) -> 47604 | BN26: =DATE(BI$5,6,1) -> 47635 | BO26: =DATE(BI$5,7,1) -> 47665 | BP26: =DATE(BI$5,8,1) -> 47696 | BQ26: =DATE(BI$5,9,1) -> 47727 | BR26: =DATE(BI$5,10,1) -> 47757 | BS26: =DATE(BI$5,11,1) -> 47788 | BT26: =DATE(BI$5,12,1) -> 47818 | BU26: =BI$5 -> 2030 | BW26: =DATE(BW$5,1,1) -> 47849 | BX26: =DATE(BW$5,2,1) -> 47880 | BY26: =DATE(BW$5,3,1) -> 47908 | BZ26: =DATE(BW$5,4,1) -> 47939 | CA26: =DATE(BW$5,5,1) -> 47969 | CB26: =DATE(BW$5,6,1) -> 48000 | CC26: =DATE(BW$5,7,1) -> 48030 | CD26: =DATE(BW$5,8,1) -> 48061 | CE26: =DATE(BW$5,9,1) -> 48092 | CF26: =DATE(BW$5,10,1) -> 48122 | CG26: =DATE(BW$5,11,1) -> 48153 | CH26: =DATE(BW$5,12,1) -> 48183 | CI26: =BW$5 -> 2031 | CK26: =DATE(CK$5,1,1) -> 48214 | CL26: =DATE(CK$5,2,1) -> 48245 | CM26: =DATE(CK$5,3,1) -> 48274 | CN26: =DATE(CK$5,4,1) -> 48305 | CO26: =DATE(CK$5,5,1) -> 48335 | CP26: =DATE(CK$5,6,1) -> 48366 | CQ26: =DATE(CK$5,7,1) -> 48396 | CR26: =DATE(CK$5,8,1) -> 48427 | CS26: =DATE(CK$5,9,1) -> 48458 | CT26: =DATE(CK$5,10,1) -> 48488 | CU26: =DATE(CK$5,11,1) -> 48519 | CV26: =DATE(CK$5,12,1) -> 48549 | CW26: =CK$5 -> 2032 | CY26: =DATE(CY$5,1,1) -> 48580 | CZ26: =DATE(CY$5,2,1) -> 48611 | DA26: =DATE(CY$5,3,1) -> 48639 | DB26: =DATE(CY$5,4,1) -> 48670 | DC26: =DATE(CY$5,5,1) -> 48700 | DD26: =DATE(CY$5,6,1) -> 48731 | DE26: =DATE(CY$5,7,1) -> 48761 | DF26: =DATE(CY$5,8,1) -> 48792 | DG26: =DATE(CY$5,9,1) -> 48823 | DH26: =DATE(CY$5,10,1) -> 48853 | DI26: =DATE(CY$5,11,1) -> 48884 | DJ26: =DATE(CY$5,12,1) -> 48914 | DK26: =CY$5 -> 2033 | DM26: =DATE(DM$5,1,1) -> 48945 | DN26: =DATE(DM$5,2,1) -> 48976 | DO26: =DATE(DM$5,3,1) -> 49004 | DP26: =DATE(DM$5,4,1) -> 49035 | DQ26: =DATE(DM$5,5,1) -> 49065 | DR26: =DATE(DM$5,6,1) -> 49096 | DS26: =DATE(DM$5,7,1) -> 49126 | DT26: =DATE(DM$5,8,1) -> 49157 | DU26: =DATE(DM$5,9,1) -> 49188 | DV26: =DATE(DM$5,10,1) -> 49218 | DW26: =DATE(DM$5,11,1) -> 49249 | DX26: =DATE(DM$5,12,1) -> 49279 | DY26: =DM$5 -> 2034 | EA26: =DATE(EA$5,1,1) -> 49310 | EB26: =DATE(EA$5,2,1) -> 49341 | EC26: =DATE(EA$5,3,1) -> 49369 | ED26: =DATE(EA$5,4,1) -> 49400 | EE26: =DATE(EA$5,5,1) -> 49430 | EF26: =DATE(EA$5,6,1) -> 49461 | EG26: =DATE(EA$5,7,1) -> 49491 | EH26: =DATE(EA$5,8,1) -> 49522 | EI26: =DATE(EA$5,9,1) -> 49553 | EJ26: =DATE(EA$5,10,1) -> 49583 | EK26: =DATE(EA$5,11,1) -> 49614 | EL26: =DATE(EA$5,12,1) -> 49644 | EM26: =EA$5 -> 2035 | EO26: =DATE(EO$5,1,1) -> 49675 | EP26: =DATE(EO$5,2,1) -> 49706 | EQ26: =DATE(EO$5,3,1) -> 49735 | ER26: =DATE(EO$5,4,1) -> 49766 | ES26: =DATE(EO$5,5,1) -> 49796 | ET26: =DATE(EO$5,6,1) -> 49827 | EU26: =DATE(EO$5,7,1) -> 49857 | EV26: =DATE(EO$5,8,1) -> 49888 | EW26: =DATE(EO$5,9,1) -> 49919 | EX26: =DATE(EO$5,10,1) -> 49949 | EY26: =DATE(EO$5,11,1) -> 49980 | EZ26: =DATE(EO$5,12,1) -> 50010 | FA26: =EO$5 -> 2036
C27: Rent | E27: 8500 | F27: 8500 | G27: 8500 | H27: 22000 | I27: 22000 | J27: 22000 | K27: 22000 | L27: 22000 | M27: 22000 | N27: 22000 | O27: 22000 | P27: 22000 | Q27: =SUM(E27:P27) -> 223500 | AE27: =SUM(S27:AD27) -> 0 | AS27: =SUM(AG27:AR27) -> 0 | BG27: =SUM(AU27:BF27) -> 0 | BU27: =SUM(BI27:BT27) -> 0 | CI27: =SUM(BW27:CH27) -> 0 | CW27: =SUM(CK27:CV27) -> 0 | DK27: =SUM(CY27:DJ27) -> 0 | DY27: =SUM(DM27:DX27) -> 0 | EM27: =SUM(EA27:EL27) -> 0 | FA27: =SUM(EO27:EZ27) -> 0
C28: Fuel | E28: 1500 | F28: 1500 | G28: 1500 | H28: 3500 | I28: 3500 | J28: 3500 | K28: 3500 | L28: 3500 | M28: 3500 | N28: 3500 | O28: 3500 | P28: 3500 | Q28: =SUM(E28:P28) -> 36000 | AE28: =SUM(S28:AD28) -> 0 | AS28: =SUM(AG28:AR28) -> 0 | BG28: =SUM(AU28:BF28) -> 0 | BU28: =SUM(BI28:BT28) -> 0 | CI28: =SUM(BW28:CH28) -> 0 | CW28: =SUM(CK28:CV28) -> 0 | DK28: =SUM(CY28:DJ28) -> 0 | DY28: =SUM(DM28:DX28) -> 0 | EM28: =SUM(EA28:EL28) -> 0 | FA28: =SUM(EO28:EZ28) -> 0
C29: Groceries | E29: 15568 | F29: 15568 | G29: 15568 | H29: 15568 | I29: 15568 | J29: 15568 | K29: 15568 | L29: 15568 | M29: 15568 | N29: 15568 | O29: 15568 | P29: 15568 | Q29: =SUM(E29:P29) -> 186816 | AE29: =SUM(S29:AD29) -> 0 | AS29: =SUM(AG29:AR29) -> 0 | BG29: =SUM(AU29:BF29) -> 0 | BU29: =SUM(BI29:BT29) -> 0 | CI29: =SUM(BW29:CH29) -> 0 | CW29: =SUM(CK29:CV29) -> 0 | DK29: =SUM(CY29:DJ29) -> 0 | DY29: =SUM(DM29:DX29) -> 0 | EM29: =SUM(EA29:EL29) -> 0 | FA29: =SUM(EO29:EZ29) -> 0
C30: MISC | E30: 1000 | F30: 1000 | G30: 1000 | H30: 1000 | I30: 1000 | J30: 1000 | K30: 1000 | L30: 1000 | M30: 1000 | N30: 1000 | O30: 1000 | P30: 1000 | Q30: =SUM(E30:P30) -> 12000 | AE30: =SUM(S30:AD30) -> 0 | AS30: =SUM(AG30:AR30) -> 0 | BG30: =SUM(AU30:BF30) -> 0 | BU30: =SUM(BI30:BT30) -> 0 | CI30: =SUM(BW30:CH30) -> 0 | CW30: =SUM(CK30:CV30) -> 0 | DK30: =SUM(CY30:DJ30) -> 0 | DY30: =SUM(DM30:DX30) -> 0 | EM30: =SUM(EA30:EL30) -> 0 | FA30: =SUM(EO30:EZ30) -> 0
C31: Insurances | E31: 1050 | F31: 1050 | G31: 1050 | H31: 1050 | I31: 1050 | J31: 1050 | K31: 1050 | L31: 1050 | M31: 1050 | N31: 1050 | O31: 1050 | P31: 1050 | Q31: =SUM(E31:P31) -> 12600 | AE31: =SUM(S31:AD31) -> 0 | AS31: =SUM(AG31:AR31) -> 0 | BG31: =SUM(AU31:BF31) -> 0 | BU31: =SUM(BI31:BT31) -> 0 | CI31: =SUM(BW31:CH31) -> 0 | CW31: =SUM(CK31:CV31) -> 0 | DK31: =SUM(CY31:DJ31) -> 0 | DY31: =SUM(DM31:DX31) -> 0 | EM31: =SUM(EA31:EL31) -> 0 | FA31: =SUM(EO31:EZ31) -> 0
C32: Clothing | E32: 0 | F32: 0 | G32: 0 | H32: 0 | I32: 3500 | J32: 0 | K32: 0 | L32: 0 | M32: 5500 | N32: 0 | O32: 0 | P32: 7000 | Q32: =SUM(E32:P32) -> 16000 | AE32: =SUM(S32:AD32) -> 0 | AS32: =SUM(AG32:AR32) -> 0 | BG32: =SUM(AU32:BF32) -> 0 | BU32: =SUM(BI32:BT32) -> 0 | CI32: =SUM(BW32:CH32) -> 0 | CW32: =SUM(CK32:CV32) -> 0 | DK32: =SUM(CY32:DJ32) -> 0 | DY32: =SUM(DM32:DX32) -> 0 | EM32: =SUM(EA32:EL32) -> 0 | FA32: =SUM(EO32:EZ32) -> 0
C33: Wellness&Medicine | E33: 500 | F33: 500 | G33: 500 | H33: 500 | I33: 500 | J33: 500 | K33: 500 | L33: 500 | M33: 500 | N33: 500 | O33: 500 | P33: 500 | Q33: =SUM(E33:P33) -> 6000 | AE33: =SUM(S33:AD33) -> 0 | AS33: =SUM(AG33:AR33) -> 0 | BG33: =SUM(AU33:BF33) -> 0 | BU33: =SUM(BI33:BT33) -> 0 | CI33: =SUM(BW33:CH33) -> 0 | CW33: =SUM(CK33:CV33) -> 0 | DK33: =SUM(CY33:DJ33) -> 0 | DY33: =SUM(DM33:DX33) -> 0 | EM33: =SUM(EA33:EL33) -> 0 | FA33: =SUM(EO33:EZ33) -> 0
C34: Media | E34: 300 | F34: 300 | G34: 300 | H34: 300 | I34: 300 | J34: 300 | K34: 300 | L34: 300 | M34: 300 | N34: 300 | O34: 300 | P34: 300 | Q34: =SUM(E34:P34) -> 3600 | AE34: =SUM(S34:AD34) -> 0 | AS34: =SUM(AG34:AR34) -> 0 | BG34: =SUM(AU34:BF34) -> 0 | BU34: =SUM(BI34:BT34) -> 0 | CI34: =SUM(BW34:CH34) -> 0 | CW34: =SUM(CK34:CV34) -> 0 | DK34: =SUM(CY34:DJ34) -> 0 | DY34: =SUM(DM34:DX34) -> 0 | EM34: =SUM(EA34:EL34) -> 0 | FA34: =SUM(EO34:EZ34) -> 0
C35: Fun & Vacation | E35: 500 | F35: 1500 | G35: 1000 | H35: 2500 | I35: 3000 | J35: 5000 | K35: 5500 | L35: 3000 | M35: 4000 | N35: 2500 | O35: 2000 | P35: 3800 | Q35: =SUM(E35:P35) -> 34300 | AE35: =SUM(S35:AD35) -> 0 | AS35: =SUM(AG35:AR35) -> 0 | BG35: =SUM(AU35:BF35) -> 0 | BU35: =SUM(BI35:BT35) -> 0 | CI35: =SUM(BW35:CH35) -> 0 | CW35: =SUM(CK35:CV35) -> 0 | DK35: =SUM(CY35:DJ35) -> 0 | DY35: =SUM(DM35:DX35) -> 0 | EM35: =SUM(EA35:EL35) -> 0 | FA35: =SUM(EO35:EZ35) -> 0
C36: Enter Expenses Category | Q36: =SUM(E36:P36) -> 0 | AE36: =SUM(S36:AD36) -> 0 | AS36: =SUM(AG36:AR36) -> 0 | BG36: =SUM(AU36:BF36) -> 0 | BU36: =SUM(BI36:BT36) -> 0 | CI36: =SUM(BW36:CH36) -> 0 | CW36: =SUM(CK36:CV36) -> 0 | DK36: =SUM(CY36:DJ36) -> 0 | DY36: =SUM(DM36:DX36) -> 0 | EM36: =SUM(EA36:EL36) -> 0 | FA36: =SUM(EO36:EZ36) -> 0
C37: Enter Expenses Category | Q37: =SUM(E37:P37) -> 0 | AE37: =SUM(S37:AD37) -> 0 | AS37: =SUM(AG37:AR37) -> 0 | BG37: =SUM(AU37:BF37) -> 0 | BU37: =SUM(BI37:BT37) -> 0 | CI37: =SUM(BW37:CH37) -> 0 | CW37: =SUM(CK37:CV37) -> 0 | DK37: =SUM(CY37:DJ37) -> 0 | DY37: =SUM(DM37:DX37) -> 0 | EM37: =SUM(EA37:EL37) -> 0 | FA37: =SUM(EO37:EZ37) -> 0
C38: Enter Expenses Category | Q38: =SUM(E38:P38) -> 0 | AE38: =SUM(S38:AD38) -> 0 | AS38: =SUM(AG38:AR38) -> 0 | BG38: =SUM(AU38:BF38) -> 0 | BU38: =SUM(BI38:BT38) -> 0 | CI38: =SUM(BW38:CH38) -> 0 | CW38: =SUM(CK38:CV38) -> 0 | DK38: =SUM(CY38:DJ38) -> 0 | DY38: =SUM(DM38:DX38) -> 0 | EM38: =SUM(EA38:EL38) -> 0 | FA38: =SUM(EO38:EZ38) -> 0
C39: Enter Expenses Category | Q39: =SUM(E39:P39) -> 0 | AE39: =SUM(S39:AD39) -> 0 | AS39: =SUM(AG39:AR39) -> 0 | BG39: =SUM(AU39:BF39) -> 0 | BU39: =SUM(BI39:BT39) -> 0 | CI39: =SUM(BW39:CH39) -> 0 | CW39: =SUM(CK39:CV39) -> 0 | DK39: =SUM(CY39:DJ39) -> 0 | DY39: =SUM(DM39:DX39) -> 0 | EM39: =SUM(EA39:EL39) -> 0 | FA39: =SUM(EO39:EZ39) -> 0
C40: Enter Expenses Category | Q40: =SUM(E40:P40) -> 0 | AE40: =SUM(S40:AD40) -> 0 | AS40: =SUM(AG40:AR40) -> 0 | BG40: =SUM(AU40:BF40) -> 0 | BU40: =SUM(BI40:BT40) -> 0 | CI40: =SUM(BW40:CH40) -> 0 | CW40: =SUM(CK40:CV40) -> 0 | DK40: =SUM(CY40:DJ40) -> 0 | DY40: =SUM(DM40:DX40) -> 0 | EM40: =SUM(EA40:EL40) -> 0 | FA40: =SUM(EO40:EZ40) -> 0
C41: Total | E41: {=SUM(INDIRECT(ADDRESS(expenses_min_row,COLUMN()) &":"& ADDRESS(expenses_max_row,COLUMN())))} -> 28918 | F41: {=SUM(INDIRECT(ADDRESS(expenses_min_row,COLUMN()) &":"& ADDRESS(expenses_max_row,COLUMN())))} -> 29918 | G41: {=SUM(INDIRECT(ADDRESS(expenses_min_row,COLUMN()) &":"& ADDRESS(expenses_max_row,COLUMN())))} -> 29418 | H41: {=SUM(INDIRECT(ADDRESS(expenses_min_row,COLUMN()) &":"& ADDRESS(expenses_max_row,COLUMN())))} -> 46418 | I41: {=SUM(INDIRECT(ADDRESS(expenses_min_row,COLUMN()) &":"& ADDRESS(expenses_max_row,COLUMN())))} -> 50418 | J41: {=SUM(INDIRECT(ADDRESS(expenses_min_row,COLUMN()) &":"& ADDRESS(expenses_max_row,COLUMN())))} -> 48918 | K41: {=SUM(INDIRECT(ADDRESS(expenses_min_row,COLUMN()) &":"& ADDRESS(expenses_max_row,COLUMN())))} -> 49418 | L41: {=SUM(INDIRECT(ADDRESS(expenses_min_row,COLUMN()) &":"& ADDRESS(expenses_max_row,COLUMN())))} -> 46918 | ... Q41: {=SUM(INDIRECT(ADDRESS(expenses_min_row,COLUMN()) &":"& ADDRESS(expenses_max_row,COLUMN())))} -> 530816 | S41: {=SUM(INDIRECT(ADDRESS(expenses_min_row,COLUMN()) &":"& ADDRESS(expenses_max_row,COLUMN())))} -> 0 | T41: {=SUM(INDIRECT(ADDRESS(expenses_min_row,COLUMN()) &":"& ADDRESS(expenses_max_row,COLUMN())))} -> 0 | U41: {=SUM(INDIRECT(ADDRESS(expenses_min_row,COLUMN()) &":"& ADDRESS(expenses_max_row,COLUMN())))} -> 0 | V41: {=SUM(INDIRECT(ADDRESS(expenses_min_row,COLUMN()) &":"& ADDRESS(expenses_max_row,COLUMN())))} -> 0 | W41: {=SUM(INDIRECT(ADDRESS(expenses_min_row,COLUMN()) &":"& ADDRESS(expenses_max_row,COLUMN())))} -> 0 | X41: {=SUM(INDIRECT(ADDRESS(expenses_min_row,COLUMN()) &":"& ADDRESS(expenses_max_row,COLUMN())))} -> 0 | Y41: {=SUM(INDIRECT(ADDRESS(expenses_min_row,COLUMN()) &":"& ADDRESS(expenses_max_row,COLUMN())))} -> 0 | Z41: {=SUM(INDIRECT(ADDRESS(expenses_min_row,COLUMN()) &":"& ADDRESS(expenses_max_row,COLUMN())))} -> 0 | ... AE41: {=SUM(INDIRECT(ADDRESS(expenses_min_row,COLUMN()) &":"& ADDRESS(expenses_max_row,COLUMN())))} -> 0 | AG41: {=SUM(INDIRECT(ADDRESS(expenses_min_row,COLUMN()) &":"& ADDRESS(expenses_max_row,COLUMN())))} -> 0 | AH41: {=SUM(INDIRECT(ADDRESS(expenses_min_row,COLUMN()) &":"& ADDRESS(expenses_max_row,COLUMN())))} -> 0 | AI41: {=SUM(INDIRECT(ADDRESS(expenses_min_row,COLUMN()) &":"& ADDRESS(expenses_max_row,COLUMN())))} -> 0 | AJ41: {=SUM(INDIRECT(ADDRESS(expenses_min_row,COLUMN()) &":"& ADDRESS(expenses_max_row,COLUMN())))} -> 0 | AK41: {=SUM(INDIRECT(ADDRESS(expenses_min_row,COLUMN()) &":"& ADDRESS(expenses_max_row,COLUMN())))} -> 0 | AL41: {=SUM(INDIRECT(ADDRESS(expenses_min_row,COLUMN()) &":"& ADDRESS(expenses_max_row,COLUMN())))} -> 0 | AM41: {=SUM(INDIRECT(ADDRESS(expenses_min_row,COLUMN()) &":"& ADDRESS(expenses_max_row,COLUMN())))} -> 0 | AN41: {=SUM(INDIRECT(ADDRESS(expenses_min_row,COLUMN()) &":"& ADDRESS(expenses_max_row,COLUMN())))} -> 0 | ... AS41: {=SUM(INDIRECT(ADDRESS(expenses_min_row,COLUMN()) &":"& ADDRESS(expenses_max_row,COLUMN())))} -> 0 | AU41: {=SUM(INDIRECT(ADDRESS(expenses_min_row,COLUMN()) &":"& ADDRESS(expenses_max_row,COLUMN())))} -> 0 | AV41: {=SUM(INDIRECT(ADDRESS(expenses_min_row,COLUMN()) &":"& ADDRESS(expenses_max_row,COLUMN())))} -> 0 | AW41: {=SUM(INDIRECT(ADDRESS(expenses_min_row,COLUMN()) &":"& ADDRESS(expenses_max_row,COLUMN())))} -> 0 | AX41: {=SUM(INDIRECT(ADDRESS(expenses_min_row,COLUMN()) &":"& ADDRESS(expenses_max_row,COLUMN())))} -> 0 | AY41: {=SUM(INDIRECT(ADDRESS(expenses_min_row,COLUMN()) &":"& ADDRESS(expenses_max_row,COLUMN())))} -> 0 | AZ41: {=SUM(INDIRECT(ADDRESS(expenses_min_row,COLUMN()) &":"& ADDRESS(expenses_max_row,COLUMN())))} -> 0 | BA41: {=SUM(INDIRECT(ADDRESS(expenses_min_row,COLUMN()) &":"& ADDRESS(expenses_max_row,COLUMN())))} -> 0 | BB41: {=SUM(INDIRECT(ADDRESS(expenses_min_row,COLUMN()) &":"& ADDRESS(expenses_max_row,COLUMN())))} -> 0 | ... BG41: {=SUM(INDIRECT(ADDRESS(expenses_min_row,COLUMN()) &":"& ADDRESS(expenses_max_row,COLUMN())))} -> 0 | BI41: {=SUM(INDIRECT(ADDRESS(expenses_min_row,COLUMN()) &":"& ADDRESS(expenses_max_row,COLUMN())))} -> 0 | BJ41: {=SUM(INDIRECT(ADDRESS(expenses_min_row,COLUMN()) &":"& ADDRESS(expenses_max_row,COLUMN())))} -> 0 | BK41: {=SUM(INDIRECT(ADDRESS(expenses_min_row,COLUMN()) &":"& ADDRESS(expenses_max_row,COLUMN())))} -> 0 | BL41: {=SUM(INDIRECT(ADDRESS(expenses_min_row,COLUMN()) &":"& ADDRESS(expenses_max_row,COLUMN())))} -> 0 | BM41: {=SUM(INDIRECT(ADDRESS(expenses_min_row,COLUMN()) &":"& ADDRESS(expenses_max_row,COLUMN())))} -> 0 | BN41: {=SUM(INDIRECT(ADDRESS(expenses_min_row,COLUMN()) &":"& ADDRESS(expenses_max_row,COLUMN())))} -> 0 | BO41: {=SUM(INDIRECT(ADDRESS(expenses_min_row,COLUMN()) &":"& ADDRESS(expenses_max_row,COLUMN())))} -> 0 | BP41: {=SUM(INDIRECT(ADDRESS(expenses_min_row,COLUMN()) &":"& ADDRESS(expenses_max_row,COLUMN())))} -> 0 | ... BU41: {=SUM(INDIRECT(ADDRESS(expenses_min_row,COLUMN()) &":"& ADDRESS(expenses_max_row,COLUMN())))} -> 0 | BW41: {=SUM(INDIRECT(ADDRESS(expenses_min_row,COLUMN()) &":"& ADDRESS(expenses_max_row,COLUMN())))} -> 0 | BX41: {=SUM(INDIRECT(ADDRESS(expenses_min_row,COLUMN()) &":"& ADDRESS(expenses_max_row,COLUMN())))} -> 0 | BY41: {=SUM(INDIRECT(ADDRESS(expenses_min_row,COLUMN()) &":"& ADDRESS(expenses_max_row,COLUMN())))} -> 0 | BZ41: {=SUM(INDIRECT(ADDRESS(expenses_min_row,COLUMN()) &":"& ADDRESS(expenses_max_row,COLUMN())))} -> 0 | CA41: {=SUM(INDIRECT(ADDRESS(expenses_min_row,COLUMN()) &":"& ADDRESS(expenses_max_row,COLUMN())))} -> 0 | CB41: {=SUM(INDIRECT(ADDRESS(expenses_min_row,COLUMN()) &":"& ADDRESS(expenses_max_row,COLUMN())))} -> 0 | CC41: {=SUM(INDIRECT(ADDRESS(expenses_min_row,COLUMN()) &":"& ADDRESS(expenses_max_row,COLUMN())))} -> 0 | CD41: {=SUM(INDIRECT(ADDRESS(expenses_min_row,COLUMN()) &":"& ADDRESS(expenses_max_row,COLUMN())))} -> 0 | ... CI41: {=SUM(INDIRECT(ADDRESS(expenses_min_row,COLUMN()) &":"& ADDRESS(expenses_max_row,COLUMN())))} -> 0 | CK41: {=SUM(INDIRECT(ADDRESS(expenses_min_row,COLUMN()) &":"& ADDRESS(expenses_max_row,COLUMN())))} -> 0 | CL41: {=SUM(INDIRECT(ADDRESS(expenses_min_row,COLUMN()) &":"& ADDRESS(expenses_max_row,COLUMN())))} -> 0 | CM41: {=SUM(INDIRECT(ADDRESS(expenses_min_row,COLUMN()) &":"& ADDRESS(expenses_max_row,COLUMN())))} -> 0 | CN41: {=SUM(INDIRECT(ADDRESS(expenses_min_row,COLUMN()) &":"& ADDRESS(expenses_max_row,COLUMN())))} -> 0 | CO41: {=SUM(INDIRECT(ADDRESS(expenses_min_row,COLUMN()) &":"& ADDRESS(expenses_max_row,COLUMN())))} -> 0 | CP41: {=SUM(INDIRECT(ADDRESS(expenses_min_row,COLUMN()) &":"& ADDRESS(expenses_max_row,COLUMN())))} -> 0 | CQ41: {=SUM(INDIRECT(ADDRESS(expenses_min_row,COLUMN()) &":"& ADDRESS(expenses_max_row,COLUMN())))} -> 0 | CR41: {=SUM(INDIRECT(ADDRESS(expenses_min_row,COLUMN()) &":"& ADDRESS(expenses_max_row,COLUMN())))} -> 0 | ... CW41: {=SUM(INDIRECT(ADDRESS(expenses_min_row,COLUMN()) &":"& ADDRESS(expenses_max_row,COLUMN())))} -> 0 | CY41: {=SUM(INDIRECT(ADDRESS(expenses_min_row,COLUMN()) &":"& ADDRESS(expenses_max_row,COLUMN())))} -> 0 | CZ41: {=SUM(INDIRECT(ADDRESS(expenses_min_row,COLUMN()) &":"& ADDRESS(expenses_max_row,COLUMN())))} -> 0 | DA41: {=SUM(INDIRECT(ADDRESS(expenses_min_row,COLUMN()) &":"& ADDRESS(expenses_max_row,COLUMN())))} -> 0 | DB41: {=SUM(INDIRECT(ADDRESS(expenses_min_row,COLUMN()) &":"& ADDRESS(expenses_max_row,COLUMN())))} -> 0 | DC41: {=SUM(INDIRECT(ADDRESS(expenses_min_row,COLUMN()) &":"& ADDRESS(expenses_max_row,COLUMN())))} -> 0 | DD41: {=SUM(INDIRECT(ADDRESS(expenses_min_row,COLUMN()) &":"& ADDRESS(expenses_max_row,COLUMN())))} -> 0 | DE41: {=SUM(INDIRECT(ADDRESS(expenses_min_row,COLUMN()) &":"& ADDRESS(expenses_max_row,COLUMN())))} -> 0 | DF41: {=SUM(INDIRECT(ADDRESS(expenses_min_row,COLUMN()) &":"& ADDRESS(expenses_max_row,COLUMN())))} -> 0 | ... DK41: {=SUM(INDIRECT(ADDRESS(expenses_min_row,COLUMN()) &":"& ADDRESS(expenses_max_row,COLUMN())))} -> 0 | DM41: {=SUM(INDIRECT(ADDRESS(expenses_min_row,COLUMN()) &":"& ADDRESS(expenses_max_row,COLUMN())))} -> 0 | DN41: {=SUM(INDIRECT(ADDRESS(expenses_min_row,COLUMN()) &":"& ADDRESS(expenses_max_row,COLUMN())))} -> 0 | DO41: {=SUM(INDIRECT(ADDRESS(expenses_min_row,COLUMN()) &":"& ADDRESS(expenses_max_row,COLUMN())))} -> 0 | DP41: {=SUM(INDIRECT(ADDRESS(expenses_min_row,COLUMN()) &":"& ADDRESS(expenses_max_row,COLUMN())))} -> 0 | DQ41: {=SUM(INDIRECT(ADDRESS(expenses_min_row,COLUMN()) &":"& ADDRESS(expenses_max_row,COLUMN())))} -> 0 | DR41: {=SUM(INDIRECT(ADDRESS(expenses_min_row,COLUMN()) &":"& ADDRESS(expenses_max_row,COLUMN())))} -> 0 | DS41: {=SUM(INDIRECT(ADDRESS(expenses_min_row,COLUMN()) &":"& ADDRESS(expenses_max_row,COLUMN())))} -> 0 | DT41: {=SUM(INDIRECT(ADDRESS(expenses_min_row,COLUMN()) &":"& ADDRESS(expenses_max_row,COLUMN())))} -> 0 | ... DY41: {=SUM(INDIRECT(ADDRESS(expenses_min_row,COLUMN()) &":"& ADDRESS(expenses_max_row,COLUMN())))} -> 0 | EA41: {=SUM(INDIRECT(ADDRESS(expenses_min_row,COLUMN()) &":"& ADDRESS(expenses_max_row,COLUMN())))} -> 0 | EB41: {=SUM(INDIRECT(ADDRESS(expenses_min_row,COLUMN()) &":"& ADDRESS(expenses_max_row,COLUMN())))} -> 0 | EC41: {=SUM(INDIRECT(ADDRESS(expenses_min_row,COLUMN()) &":"& ADDRESS(expenses_max_row,COLUMN())))} -> 0 | ED41: {=SUM(INDIRECT(ADDRESS(expenses_min_row,COLUMN()) &":"& ADDRESS(expenses_max_row,COLUMN())))} -> 0 | EE41: {=SUM(INDIRECT(ADDRESS(expenses_min_row,COLUMN()) &":"& ADDRESS(expenses_max_row,COLUMN())))} -> 0 | EF41: {=SUM(INDIRECT(ADDRESS(expenses_min_row,COLUMN()) &":"& ADDRESS(expenses_max_row,COLUMN())))} -> 0 | EG41: {=SUM(INDIRECT(ADDRESS(expenses_min_row,COLUMN()) &":"& ADDRESS(expenses_max_row,COLUMN())))} -> 0 | EH41: {=SUM(INDIRECT(ADDRESS(expenses_min_row,COLUMN()) &":"& ADDRESS(expenses_max_row,COLUMN())))} -> 0 | ... EM41: {=SUM(INDIRECT(ADDRESS(expenses_min_row,COLUMN()) &":"& ADDRESS(expenses_max_row,COLUMN())))} -> 0 | EO41: {=SUM(INDIRECT(ADDRESS(expenses_min_row,COLUMN()) &":"& ADDRESS(expenses_max_row,COLUMN())))} -> 0 | EP41: {=SUM(INDIRECT(ADDRESS(expenses_min_row,COLUMN()) &":"& ADDRESS(expenses_max_row,COLUMN())))} -> 0 | EQ41: {=SUM(INDIRECT(ADDRESS(expenses_min_row,COLUMN()) &":"& ADDRESS(expenses_max_row,COLUMN())))} -> 0 | ER41: {=SUM(INDIRECT(ADDRESS(expenses_min_row,COLUMN()) &":"& ADDRESS(expenses_max_row,COLUMN())))} -> 0 | ES41: {=SUM(INDIRECT(ADDRESS(expenses_min_row,COLUMN()) &":"& ADDRESS(expenses_max_row,COLUMN())))} -> 0 | ET41: {=SUM(INDIRECT(ADDRESS(expenses_min_row,COLUMN()) &":"& ADDRESS(expenses_max_row,COLUMN())))} -> 0 | EU41: {=SUM(INDIRECT(ADDRESS(expenses_min_row,COLUMN()) &":"& ADDRESS(expenses_max_row,COLUMN())))} -> 0 | EV41: {=SUM(INDIRECT(ADDRESS(expenses_min_row,COLUMN()) &":"& ADDRESS(expenses_max_row,COLUMN())))} -> 0 | ... FA41: {=SUM(INDIRECT(ADDRESS(expenses_min_row,COLUMN()) &":"& ADDRESS(expenses_max_row,COLUMN())))} -> 0
C43: Savings | E43: =DATE(E$5,1,1) -> 46023 | F43: =DATE(E$5,2,1) -> 46054 | G43: =DATE(E$5,3,1) -> 46082 | H43: =DATE(E$5,4,1) -> 46113 | I43: =DATE(E$5,5,1) -> 46143 | J43: =DATE(E$5,6,1) -> 46174 | K43: =DATE(E$5,7,1) -> 46204 | L43: =DATE(E$5,8,1) -> 46235 | M43: =DATE(E$5,9,1) -> 46266 | N43: =DATE(E$5,10,1) -> 46296 | O43: =DATE(E$5,11,1) -> 46327 | P43: =DATE(E$5,12,1) -> 46357 | Q43: =E$5 -> 2026 | S43: =DATE(S$5,1,1) -> 46388 | T43: =DATE(S$5,2,1) -> 46419 | U43: =DATE(S$5,3,1) -> 46447 | V43: =DATE(S$5,4,1) -> 46478 | W43: =DATE(S$5,5,1) -> 46508 | X43: =DATE(S$5,6,1) -> 46539 | Y43: =DATE(S$5,7,1) -> 46569 | Z43: =DATE(S$5,8,1) -> 46600 | AA43: =DATE(S$5,9,1) -> 46631 | AB43: =DATE(S$5,10,1) -> 46661 | AC43: =DATE(S$5,11,1) -> 46692 | AD43: =DATE(S$5,12,1) -> 46722 | AE43: =S$5 -> 2027 | AG43: =DATE(AG$5,1,1) -> 46753 | AH43: =DATE(AG$5,2,1) -> 46784 | AI43: =DATE(AG$5,3,1) -> 46813 | AJ43: =DATE(AG$5,4,1) -> 46844 | AK43: =DATE(AG$5,5,1) -> 46874 | AL43: =DATE(AG$5,6,1) -> 46905 | AM43: =DATE(AG$5,7,1) -> 46935 | AN43: =DATE(AG$5,8,1) -> 46966 | AO43: =DATE(AG$5,9,1) -> 46997 | AP43: =DATE(AG$5,10,1) -> 47027 | AQ43: =DATE(AG$5,11,1) -> 47058 | AR43: =DATE(AG$5,12,1) -> 47088 | AS43: =AG$5 -> 2028 | AU43: =DATE(AU$5,1,1) -> 47119 | AV43: =DATE(AU$5,2,1) -> 47150 | AW43: =DATE(AU$5,3,1) -> 47178 | AX43: =DATE(AU$5,4,1) -> 47209 | AY43: =DATE(AU$5,5,1) -> 47239 | AZ43: =DATE(AU$5,6,1) -> 47270 | BA43: =DATE(AU$5,7,1) -> 47300 | BB43: =DATE(AU$5,8,1) -> 47331 | BC43: =DATE(AU$5,9,1) -> 47362 | BD43: =DATE(AU$5,10,1) -> 47392 | BE43: =DATE(AU$5,11,1) -> 47423 | BF43: =DATE(AU$5,12,1) -> 47453 | BG43: =AU$5 -> 2029 | BI43: =DATE(BI$5,1,1) -> 47484 | BJ43: =DATE(BI$5,2,1) -> 47515 | BK43: =DATE(BI$5,3,1) -> 47543 | BL43: =DATE(BI$5,4,1) -> 47574 | BM43: =DATE(BI$5,5,1) -> 47604 | BN43: =DATE(BI$5,6,1) -> 47635 | BO43: =DATE(BI$5,7,1) -> 47665 | BP43: =DATE(BI$5,8,1) -> 47696 | BQ43: =DATE(BI$5,9,1) -> 47727 | BR43: =DATE(BI$5,10,1) -> 47757 | BS43: =DATE(BI$5,11,1) -> 47788 | BT43: =DATE(BI$5,12,1) -> 47818 | BU43: =BI$5 -> 2030 | BW43: =DATE(BW$5,1,1) -> 47849 | BX43: =DATE(BW$5,2,1) -> 47880 | BY43: =DATE(BW$5,3,1) -> 47908 | BZ43: =DATE(BW$5,4,1) -> 47939 | CA43: =DATE(BW$5,5,1) -> 47969 | CB43: =DATE(BW$5,6,1) -> 48000 | CC43: =DATE(BW$5,7,1) -> 48030 | CD43: =DATE(BW$5,8,1) -> 48061 | CE43: =DATE(BW$5,9,1) -> 48092 | CF43: =DATE(BW$5,10,1) -> 48122 | CG43: =DATE(BW$5,11,1) -> 48153 | CH43: =DATE(BW$5,12,1) -> 48183 | CI43: =BW$5 -> 2031 | CK43: =DATE(CK$5,1,1) -> 48214 | CL43: =DATE(CK$5,2,1) -> 48245 | CM43: =DATE(CK$5,3,1) -> 48274 | CN43: =DATE(CK$5,4,1) -> 48305 | CO43: =DATE(CK$5,5,1) -> 48335 | CP43: =DATE(CK$5,6,1) -> 48366 | CQ43: =DATE(CK$5,7,1) -> 48396 | CR43: =DATE(CK$5,8,1) -> 48427 | CS43: =DATE(CK$5,9,1) -> 48458 | CT43: =DATE(CK$5,10,1) -> 48488 | CU43: =DATE(CK$5,11,1) -> 48519 | CV43: =DATE(CK$5,12,1) -> 48549 | CW43: =CK$5 -> 2032 | CY43: =DATE(CY$5,1,1) -> 48580 | CZ43: =DATE(CY$5,2,1) -> 48611 | DA43: =DATE(CY$5,3,1) -> 48639 | DB43: =DATE(CY$5,4,1) -> 48670 | DC43: =DATE(CY$5,5,1) -> 48700 | DD43: =DATE(CY$5,6,1) -> 48731 | DE43: =DATE(CY$5,7,1) -> 48761 | DF43: =DATE(CY$5,8,1) -> 48792 | DG43: =DATE(CY$5,9,1) -> 48823 | DH43: =DATE(CY$5,10,1) -> 48853 | DI43: =DATE(CY$5,11,1) -> 48884 | DJ43: =DATE(CY$5,12,1) -> 48914 | DK43: =CY$5 -> 2033 | DM43: =DATE(DM$5,1,1) -> 48945 | DN43: =DATE(DM$5,2,1) -> 48976 | DO43: =DATE(DM$5,3,1) -> 49004 | DP43: =DATE(DM$5,4,1) -> 49035 | DQ43: =DATE(DM$5,5,1) -> 49065 | DR43: =DATE(DM$5,6,1) -> 49096 | DS43: =DATE(DM$5,7,1) -> 49126 | DT43: =DATE(DM$5,8,1) -> 49157 | DU43: =DATE(DM$5,9,1) -> 49188 | DV43: =DATE(DM$5,10,1) -> 49218 | DW43: =DATE(DM$5,11,1) -> 49249 | DX43: =DATE(DM$5,12,1) -> 49279 | DY43: =DM$5 -> 2034 | EA43: =DATE(EA$5,1,1) -> 49310 | EB43: =DATE(EA$5,2,1) -> 49341 | EC43: =DATE(EA$5,3,1) -> 49369 | ED43: =DATE(EA$5,4,1) -> 49400 | EE43: =DATE(EA$5,5,1) -> 49430 | EF43: =DATE(EA$5,6,1) -> 49461 | EG43: =DATE(EA$5,7,1) -> 49491 | EH43: =DATE(EA$5,8,1) -> 49522 | EI43: =DATE(EA$5,9,1) -> 49553 | EJ43: =DATE(EA$5,10,1) -> 49583 | EK43: =DATE(EA$5,11,1) -> 49614 | EL43: =DATE(EA$5,12,1) -> 49644 | EM43: =EA$5 -> 2035 | EO43: =DATE(EO$5,1,1) -> 49675 | EP43: =DATE(EO$5,2,1) -> 49706 | EQ43: =DATE(EO$5,3,1) -> 49735 | ER43: =DATE(EO$5,4,1) -> 49766 | ES43: =DATE(EO$5,5,1) -> 49796 | ET43: =DATE(EO$5,6,1) -> 49827 | EU43: =DATE(EO$5,7,1) -> 49857 | EV43: =DATE(EO$5,8,1) -> 49888 | EW43: =DATE(EO$5,9,1) -> 49919 | EX43: =DATE(EO$5,10,1) -> 49949 | EY43: =DATE(EO$5,11,1) -> 49980 | EZ43: =DATE(EO$5,12,1) -> 50010 | FA43: =EO$5 -> 2036
C44: Emergency Fund | F44: 25000 | G44: 25000 | H44: 25000 | I44: 25000 | J44: 25000 | K44: 25000 | L44: 25000 | M44: 25000 | N44: 25000 | O44: 25000 | P44: 25000 | Q44: =SUM(E44:P44) -> 275000 | AE44: =SUM(S44:AD44) -> 0 | AS44: =SUM(AG44:AR44) -> 0 | BG44: =SUM(AU44:BF44) -> 0 | BU44: =SUM(BI44:BT44) -> 0 | CI44: =SUM(BW44:CH44) -> 0 | CW44: =SUM(CK44:CV44) -> 0 | DK44: =SUM(CY44:DJ44) -> 0 | DY44: =SUM(DM44:DX44) -> 0 | EM44: =SUM(EA44:EL44) -> 0 | FA44: =SUM(EO44:EZ44) -> 0
C45: SIP | E45: 3000 | F45: 10000 | G45: 10000 | H45: 10000 | I45: 10000 | J45: 10000 | K45: 10000 | L45: 10000 | M45: 10000 | N45: 10000 | O45: 10000 | P45: 10000 | Q45: =SUM(E45:P45) -> 113000 | AE45: =SUM(S45:AD45) -> 0 | AS45: =SUM(AG45:AR45) -> 0 | BG45: =SUM(AU45:BF45) -> 0 | BU45: =SUM(BI45:BT45) -> 0 | CI45: =SUM(BW45:CH45) -> 0 | CW45: =SUM(CK45:CV45) -> 0 | DK45: =SUM(CY45:DJ45) -> 0 | DY45: =SUM(DM45:DX45) -> 0 | EM45: =SUM(EA45:EL45) -> 0 | FA45: =SUM(EO45:EZ45) -> 0
C46: Stock Portfolio | F46: 8686 | G46: 10000 | H46: 7500 | I46: 2000 | J46: 5000 | L46: 3000 | M46: 4000 | N46: 20000 | O46: 35000 | P46: 25000 | Q46: =SUM(E46:P46) -> 120186 | AE46: =SUM(S46:AD46) -> 0 | AS46: =SUM(AG46:AR46) -> 0 | BG46: =SUM(AU46:BF46) -> 0 | BU46: =SUM(BI46:BT46) -> 0 | CI46: =SUM(BW46:CH46) -> 0 | CW46: =SUM(CK46:CV46) -> 0 | DK46: =SUM(CY46:DJ46) -> 0 | DY46: =SUM(DM46:DX46) -> 0 | EM46: =SUM(EA46:EL46) -> 0 | FA46: =SUM(EO46:EZ46) -> 0
C47: Crpto | F47: 2500 | G47: 7638 | H47: 3281 | I47: 335 | J47: 2785 | K47: 818 | L47: 2395 | M47: 2415 | N47: 3877 | O47: 5091 | P47: 10224 | Q47: =SUM(E47:P47) -> 41359 | AE47: =SUM(S47:AD47) -> 0 | AS47: =SUM(AG47:AR47) -> 0 | BG47: =SUM(AU47:BF47) -> 0 | BU47: =SUM(BI47:BT47) -> 0 | CI47: =SUM(BW47:CH47) -> 0 | CW47: =SUM(CK47:CV47) -> 0 | DK47: =SUM(CY47:DJ47) -> 0 | DY47: =SUM(DM47:DX47) -> 0 | EM47: =SUM(EA47:EL47) -> 0 | FA47: =SUM(EO47:EZ47) -> 0
C48: Skill Development | F48: 0 | G48: 5000 | H48: 0 | I48: 0 | J48: 0 | K48: 0 | M48: 8000 | N48: 10000 | O48: 10000 | P48: 0 | Q48: =SUM(E48:P48) -> 33000 | AE48: =SUM(S48:AD48) -> 0 | AS48: =SUM(AG48:AR48) -> 0 | BG48: =SUM(AU48:BF48) -> 0 | BU48: =SUM(BI48:BT48) -> 0 | CI48: =SUM(BW48:CH48) -> 0 | CW48: =SUM(CK48:CV48) -> 0 | DK48: =SUM(CY48:DJ48) -> 0 | DY48: =SUM(DM48:DX48) -> 0 | EM48: =SUM(EA48:EL48) -> 0 | FA48: =SUM(EO48:EZ48) -> 0
C49: Coorg Trip Fund | F49: 5000 | G49: 5000 | H49: 2500 | I49: 0 | J49: 0 | K49: 0 | L49: 0 | M49: 0 | N49: 0 | O49: 0 | P49: 0 | Q49: =SUM(E49:P49) -> 12500 | AE49: =SUM(S49:AD49) -> 0 | AS49: =SUM(AG49:AR49) -> 0 | BG49: =SUM(AU49:BF49) -> 0 | BU49: =SUM(BI49:BT49) -> 0 | CI49: =SUM(BW49:CH49) -> 0 | CW49: =SUM(CK49:CV49) -> 0 | DK49: =SUM(CY49:DJ49) -> 0 | DY49: =SUM(DM49:DX49) -> 0 | EM49: =SUM(EA49:EL49) -> 0 | FA49: =SUM(EO49:EZ49) -> 0
C50: Mcleodganj Trip Fund | F50: 2500 | G50: 2500 | H50: 2500 | I50: 10000 | J50: 10000 | K50: 22500 | L50: 0 | M50: 0 | N50: 0 | O50: 0 | P50: 0 | Q50: =SUM(E50:P50) -> 50000 | AE50: =SUM(S50:AD50) -> 0 | AS50: =SUM(AG50:AR50) -> 0 | BG50: =SUM(AU50:BF50) -> 0 | BU50: =SUM(BI50:BT50) -> 0 | CI50: =SUM(BW50:CH50) -> 0 | CW50: =SUM(CK50:CV50) -> 0 | DK50: =SUM(CY50:DJ50) -> 0 | DY50: =SUM(DM50:DX50) -> 0 | EM50: =SUM(EA50:EL50) -> 0 | FA50: =SUM(EO50:EZ50) -> 0
C51: Sri Lanka Trip Fund | F51: 2500 | G51: 2500 | H51: 2500 | I51: 5000 | J51: 5000 | K51: 5000 | L51: 32500 | M51: 10000 | N51: 0 | O51: 0 | P51: 0 | Q51: =SUM(E51:P51) -> 65000 | AE51: =SUM(S51:AD51) -> 0 | AS51: =SUM(AG51:AR51) -> 0 | BG51: =SUM(AU51:BF51) -> 0 | BU51: =SUM(BI51:BT51) -> 0 | CI51: =SUM(BW51:CH51) -> 0 | CW51: =SUM(CK51:CV51) -> 0 | DK51: =SUM(CY51:DJ51) -> 0 | DY51: =SUM(DM51:DX51) -> 0 | EM51: =SUM(EA51:EL51) -> 0 | FA51: =SUM(EO51:EZ51) -> 0
C52: Vietnam Trip Fund | F52: 2500 | G52: 2500 | H52: 2500 | I52: 5000 | J52: 5000 | K52: 5000 | L52: 5000 | M52: 20000 | N52: 20000 | O52: 7500 | P52: 15000 | Q52: =SUM(E52:P52) -> 90000 | AE52: =SUM(S52:AD52) -> 0 | AS52: =SUM(AG52:AR52) -> 0 | BG52: =SUM(AU52:BF52) -> 0 | BU52: =SUM(BI52:BT52) -> 0 | CI52: =SUM(BW52:CH52) -> 0 | CW52: =SUM(CK52:CV52) -> 0 | DK52: =SUM(CY52:DJ52) -> 0 | DY52: =SUM(DM52:DX52) -> 0 | EM52: =SUM(EA52:EL52) -> 0 | FA52: =SUM(EO52:EZ52) -> 0
C53: Enter Savings Category | Q53: =SUM(E53:P53) -> 0 | AE53: =SUM(S53:AD53) -> 0 | AS53: =SUM(AG53:AR53) -> 0 | BG53: =SUM(AU53:BF53) -> 0 | BU53: =SUM(BI53:BT53) -> 0 | CI53: =SUM(BW53:CH53) -> 0 | CW53: =SUM(CK53:CV53) -> 0 | DK53: =SUM(CY53:DJ53) -> 0 | DY53: =SUM(DM53:DX53) -> 0 | EM53: =SUM(EA53:EL53) -> 0 | FA53: =SUM(EO53:EZ53) -> 0
C54: Enter Savings Category | Q54: =SUM(E54:P54) -> 0 | AE54: =SUM(S54:AD54) -> 0 | AS54: =SUM(AG54:AR54) -> 0 | BG54: =SUM(AU54:BF54) -> 0 | BU54: =SUM(BI54:BT54) -> 0 | CI54: =SUM(BW54:CH54) -> 0 | CW54: =SUM(CK54:CV54) -> 0 | DK54: =SUM(CY54:DJ54) -> 0 | DY54: =SUM(DM54:DX54) -> 0 | EM54: =SUM(EA54:EL54) -> 0 | FA54: =SUM(EO54:EZ54) -> 0
C55: Enter Savings Category | Q55: =SUM(E55:P55) -> 0 | AE55: =SUM(S55:AD55) -> 0 | AS55: =SUM(AG55:AR55) -> 0 | BG55: =SUM(AU55:BF55) -> 0 | BU55: =SUM(BI55:BT55) -> 0 | CI55: =SUM(BW55:CH55) -> 0 | CW55: =SUM(CK55:CV55) -> 0 | DK55: =SUM(CY55:DJ55) -> 0 | DY55: =SUM(DM55:DX55) -> 0 | EM55: =SUM(EA55:EL55) -> 0 | FA55: =SUM(EO55:EZ55) -> 0
C56: Enter Savings Category | Q56: =SUM(E56:P56) -> 0 | AE56: =SUM(S56:AD56) -> 0 | AS56: =SUM(AG56:AR56) -> 0 | BG56: =SUM(AU56:BF56) -> 0 | BU56: =SUM(BI56:BT56) -> 0 | CI56: =SUM(BW56:CH56) -> 0 | CW56: =SUM(CK56:CV56) -> 0 | DK56: =SUM(CY56:DJ56) -> 0 | DY56: =SUM(DM56:DX56) -> 0 | EM56: =SUM(EA56:EL56) -> 0 | FA56: =SUM(EO56:EZ56) -> 0
C57: Enter Savings Category | Q57: =SUM(E57:P57) -> 0 | AE57: =SUM(S57:AD57) -> 0 | AS57: =SUM(AG57:AR57) -> 0 | BG57: =SUM(AU57:BF57) -> 0 | BU57: =SUM(BI57:BT57) -> 0 | CI57: =SUM(BW57:CH57) -> 0 | CW57: =SUM(CK57:CV57) -> 0 | DK57: =SUM(CY57:DJ57) -> 0 | DY57: =SUM(DM57:DX57) -> 0 | EM57: =SUM(EA57:EL57) -> 0 | FA57: =SUM(EO57:EZ57) -> 0
C58: Total | E58: {=SUM(INDIRECT(ADDRESS(savings_min_row,COLUMN()) &":"& ADDRESS(savings_max_row,COLUMN())))} -> 3000 | F58: {=SUM(INDIRECT(ADDRESS(savings_min_row,COLUMN()) &":"& ADDRESS(savings_max_row,COLUMN())))} -> 58686 | G58: {=SUM(INDIRECT(ADDRESS(savings_min_row,COLUMN()) &":"& ADDRESS(savings_max_row,COLUMN())))} -> 70138 | H58: {=SUM(INDIRECT(ADDRESS(savings_min_row,COLUMN()) &":"& ADDRESS(savings_max_row,COLUMN())))} -> 55781 | I58: {=SUM(INDIRECT(ADDRESS(savings_min_row,COLUMN()) &":"& ADDRESS(savings_max_row,COLUMN())))} -> 57335 | J58: {=SUM(INDIRECT(ADDRESS(savings_min_row,COLUMN()) &":"& ADDRESS(savings_max_row,COLUMN())))} -> 62785 | K58: {=SUM(INDIRECT(ADDRESS(savings_min_row,COLUMN()) &":"& ADDRESS(savings_max_row,COLUMN())))} -> 68318 | L58: {=SUM(INDIRECT(ADDRESS(savings_min_row,COLUMN()) &":"& ADDRESS(savings_max_row,COLUMN())))} -> 77895 | ... Q58: {=SUM(INDIRECT(ADDRESS(savings_min_row,COLUMN()) &":"& ADDRESS(savings_max_row,COLUMN())))} -> 800045 | S58: {=SUM(INDIRECT(ADDRESS(savings_min_row,COLUMN()) &":"& ADDRESS(savings_max_row,COLUMN())))} -> 0 | T58: {=SUM(INDIRECT(ADDRESS(savings_min_row,COLUMN()) &":"& ADDRESS(savings_max_row,COLUMN())))} -> 0 | U58: {=SUM(INDIRECT(ADDRESS(savings_min_row,COLUMN()) &":"& ADDRESS(savings_max_row,COLUMN())))} -> 0 | V58: {=SUM(INDIRECT(ADDRESS(savings_min_row,COLUMN()) &":"& ADDRESS(savings_max_row,COLUMN())))} -> 0 | W58: {=SUM(INDIRECT(ADDRESS(savings_min_row,COLUMN()) &":"& ADDRESS(savings_max_row,COLUMN())))} -> 0 | X58: {=SUM(INDIRECT(ADDRESS(savings_min_row,COLUMN()) &":"& ADDRESS(savings_max_row,COLUMN())))} -> 0 | Y58: {=SUM(INDIRECT(ADDRESS(savings_min_row,COLUMN()) &":"& ADDRESS(savings_max_row,COLUMN())))} -> 0 | Z58: {=SUM(INDIRECT(ADDRESS(savings_min_row,COLUMN()) &":"& ADDRESS(savings_max_row,COLUMN())))} -> 0 | ... AE58: {=SUM(INDIRECT(ADDRESS(savings_min_row,COLUMN()) &":"& ADDRESS(savings_max_row,COLUMN())))} -> 0 | AG58: {=SUM(INDIRECT(ADDRESS(savings_min_row,COLUMN()) &":"& ADDRESS(savings_max_row,COLUMN())))} -> 0 | AH58: {=SUM(INDIRECT(ADDRESS(savings_min_row,COLUMN()) &":"& ADDRESS(savings_max_row,COLUMN())))} -> 0 | AI58: {=SUM(INDIRECT(ADDRESS(savings_min_row,COLUMN()) &":"& ADDRESS(savings_max_row,COLUMN())))} -> 0 | AJ58: {=SUM(INDIRECT(ADDRESS(savings_min_row,COLUMN()) &":"& ADDRESS(savings_max_row,COLUMN())))} -> 0 | AK58: {=SUM(INDIRECT(ADDRESS(savings_min_row,COLUMN()) &":"& ADDRESS(savings_max_row,COLUMN())))} -> 0 | AL58: {=SUM(INDIRECT(ADDRESS(savings_min_row,COLUMN()) &":"& ADDRESS(savings_max_row,COLUMN())))} -> 0 | AM58: {=SUM(INDIRECT(ADDRESS(savings_min_row,COLUMN()) &":"& ADDRESS(savings_max_row,COLUMN())))} -> 0 | AN58: {=SUM(INDIRECT(ADDRESS(savings_min_row,COLUMN()) &":"& ADDRESS(savings_max_row,COLUMN())))} -> 0 | ... AS58: {=SUM(INDIRECT(ADDRESS(savings_min_row,COLUMN()) &":"& ADDRESS(savings_max_row,COLUMN())))} -> 0 | AU58: {=SUM(INDIRECT(ADDRESS(savings_min_row,COLUMN()) &":"& ADDRESS(savings_max_row,COLUMN())))} -> 0 | AV58: {=SUM(INDIRECT(ADDRESS(savings_min_row,COLUMN()) &":"& ADDRESS(savings_max_row,COLUMN())))} -> 0 | AW58: {=SUM(INDIRECT(ADDRESS(savings_min_row,COLUMN()) &":"& ADDRESS(savings_max_row,COLUMN())))} -> 0 | AX58: {=SUM(INDIRECT(ADDRESS(savings_min_row,COLUMN()) &":"& ADDRESS(savings_max_row,COLUMN())))} -> 0 | AY58: {=SUM(INDIRECT(ADDRESS(savings_min_row,COLUMN()) &":"& ADDRESS(savings_max_row,COLUMN())))} -> 0 | AZ58: {=SUM(INDIRECT(ADDRESS(savings_min_row,COLUMN()) &":"& ADDRESS(savings_max_row,COLUMN())))} -> 0 | BA58: {=SUM(INDIRECT(ADDRESS(savings_min_row,COLUMN()) &":"& ADDRESS(savings_max_row,COLUMN())))} -> 0 | BB58: {=SUM(INDIRECT(ADDRESS(savings_min_row,COLUMN()) &":"& ADDRESS(savings_max_row,COLUMN())))} -> 0 | ... BG58: {=SUM(INDIRECT(ADDRESS(savings_min_row,COLUMN()) &":"& ADDRESS(savings_max_row,COLUMN())))} -> 0 | BI58: {=SUM(INDIRECT(ADDRESS(savings_min_row,COLUMN()) &":"& ADDRESS(savings_max_row,COLUMN())))} -> 0 | BJ58: {=SUM(INDIRECT(ADDRESS(savings_min_row,COLUMN()) &":"& ADDRESS(savings_max_row,COLUMN())))} -> 0 | BK58: {=SUM(INDIRECT(ADDRESS(savings_min_row,COLUMN()) &":"& ADDRESS(savings_max_row,COLUMN())))} -> 0 | BL58: {=SUM(INDIRECT(ADDRESS(savings_min_row,COLUMN()) &":"& ADDRESS(savings_max_row,COLUMN())))} -> 0 | BM58: {=SUM(INDIRECT(ADDRESS(savings_min_row,COLUMN()) &":"& ADDRESS(savings_max_row,COLUMN())))} -> 0 | BN58: {=SUM(INDIRECT(ADDRESS(savings_min_row,COLUMN()) &":"& ADDRESS(savings_max_row,COLUMN())))} -> 0 | BO58: {=SUM(INDIRECT(ADDRESS(savings_min_row,COLUMN()) &":"& ADDRESS(savings_max_row,COLUMN())))} -> 0 | BP58: {=SUM(INDIRECT(ADDRESS(savings_min_row,COLUMN()) &":"& ADDRESS(savings_max_row,COLUMN())))} -> 0 | ... BU58: {=SUM(INDIRECT(ADDRESS(savings_min_row,COLUMN()) &":"& ADDRESS(savings_max_row,COLUMN())))} -> 0 | BW58: {=SUM(INDIRECT(ADDRESS(savings_min_row,COLUMN()) &":"& ADDRESS(savings_max_row,COLUMN())))} -> 0 | BX58: {=SUM(INDIRECT(ADDRESS(savings_min_row,COLUMN()) &":"& ADDRESS(savings_max_row,COLUMN())))} -> 0 | BY58: {=SUM(INDIRECT(ADDRESS(savings_min_row,COLUMN()) &":"& ADDRESS(savings_max_row,COLUMN())))} -> 0 | BZ58: {=SUM(INDIRECT(ADDRESS(savings_min_row,COLUMN()) &":"& ADDRESS(savings_max_row,COLUMN())))} -> 0 | CA58: {=SUM(INDIRECT(ADDRESS(savings_min_row,COLUMN()) &":"& ADDRESS(savings_max_row,COLUMN())))} -> 0 | CB58: {=SUM(INDIRECT(ADDRESS(savings_min_row,COLUMN()) &":"& ADDRESS(savings_max_row,COLUMN())))} -> 0 | CC58: {=SUM(INDIRECT(ADDRESS(savings_min_row,COLUMN()) &":"& ADDRESS(savings_max_row,COLUMN())))} -> 0 | CD58: {=SUM(INDIRECT(ADDRESS(savings_min_row,COLUMN()) &":"& ADDRESS(savings_max_row,COLUMN())))} -> 0 | ... CI58: {=SUM(INDIRECT(ADDRESS(savings_min_row,COLUMN()) &":"& ADDRESS(savings_max_row,COLUMN())))} -> 0 | CK58: {=SUM(INDIRECT(ADDRESS(savings_min_row,COLUMN()) &":"& ADDRESS(savings_max_row,COLUMN())))} -> 0 | CL58: {=SUM(INDIRECT(ADDRESS(savings_min_row,COLUMN()) &":"& ADDRESS(savings_max_row,COLUMN())))} -> 0 | CM58: {=SUM(INDIRECT(ADDRESS(savings_min_row,COLUMN()) &":"& ADDRESS(savings_max_row,COLUMN())))} -> 0 | CN58: {=SUM(INDIRECT(ADDRESS(savings_min_row,COLUMN()) &":"& ADDRESS(savings_max_row,COLUMN())))} -> 0 | CO58: {=SUM(INDIRECT(ADDRESS(savings_min_row,COLUMN()) &":"& ADDRESS(savings_max_row,COLUMN())))} -> 0 | CP58: {=SUM(INDIRECT(ADDRESS(savings_min_row,COLUMN()) &":"& ADDRESS(savings_max_row,COLUMN())))} -> 0 | CQ58: {=SUM(INDIRECT(ADDRESS(savings_min_row,COLUMN()) &":"& ADDRESS(savings_max_row,COLUMN())))} -> 0 | CR58: {=SUM(INDIRECT(ADDRESS(savings_min_row,COLUMN()) &":"& ADDRESS(savings_max_row,COLUMN())))} -> 0 | ... CW58: {=SUM(INDIRECT(ADDRESS(savings_min_row,COLUMN()) &":"& ADDRESS(savings_max_row,COLUMN())))} -> 0 | CY58: {=SUM(INDIRECT(ADDRESS(savings_min_row,COLUMN()) &":"& ADDRESS(savings_max_row,COLUMN())))} -> 0 | CZ58: {=SUM(INDIRECT(ADDRESS(savings_min_row,COLUMN()) &":"& ADDRESS(savings_max_row,COLUMN())))} -> 0 | DA58: {=SUM(INDIRECT(ADDRESS(savings_min_row,COLUMN()) &":"& ADDRESS(savings_max_row,COLUMN())))} -> 0 | DB58: {=SUM(INDIRECT(ADDRESS(savings_min_row,COLUMN()) &":"& ADDRESS(savings_max_row,COLUMN())))} -> 0 | DC58: {=SUM(INDIRECT(ADDRESS(savings_min_row,COLUMN()) &":"& ADDRESS(savings_max_row,COLUMN())))} -> 0 | DD58: {=SUM(INDIRECT(ADDRESS(savings_min_row,COLUMN()) &":"& ADDRESS(savings_max_row,COLUMN())))} -> 0 | DE58: {=SUM(INDIRECT(ADDRESS(savings_min_row,COLUMN()) &":"& ADDRESS(savings_max_row,COLUMN())))} -> 0 | DF58: {=SUM(INDIRECT(ADDRESS(savings_min_row,COLUMN()) &":"& ADDRESS(savings_max_row,COLUMN())))} -> 0 | ... DK58: {=SUM(INDIRECT(ADDRESS(savings_min_row,COLUMN()) &":"& ADDRESS(savings_max_row,COLUMN())))} -> 0 | DM58: {=SUM(INDIRECT(ADDRESS(savings_min_row,COLUMN()) &":"& ADDRESS(savings_max_row,COLUMN())))} -> 0 | DN58: {=SUM(INDIRECT(ADDRESS(savings_min_row,COLUMN()) &":"& ADDRESS(savings_max_row,COLUMN())))} -> 0 | DO58: {=SUM(INDIRECT(ADDRESS(savings_min_row,COLUMN()) &":"& ADDRESS(savings_max_row,COLUMN())))} -> 0 | DP58: {=SUM(INDIRECT(ADDRESS(savings_min_row,COLUMN()) &":"& ADDRESS(savings_max_row,COLUMN())))} -> 0 | DQ58: {=SUM(INDIRECT(ADDRESS(savings_min_row,COLUMN()) &":"& ADDRESS(savings_max_row,COLUMN())))} -> 0 | DR58: {=SUM(INDIRECT(ADDRESS(savings_min_row,COLUMN()) &":"& ADDRESS(savings_max_row,COLUMN())))} -> 0 | DS58: {=SUM(INDIRECT(ADDRESS(savings_min_row,COLUMN()) &":"& ADDRESS(savings_max_row,COLUMN())))} -> 0 | DT58: {=SUM(INDIRECT(ADDRESS(savings_min_row,COLUMN()) &":"& ADDRESS(savings_max_row,COLUMN())))} -> 0 | ... DY58: {=SUM(INDIRECT(ADDRESS(savings_min_row,COLUMN()) &":"& ADDRESS(savings_max_row,COLUMN())))} -> 0 | EA58: {=SUM(INDIRECT(ADDRESS(savings_min_row,COLUMN()) &":"& ADDRESS(savings_max_row,COLUMN())))} -> 0 | EB58: {=SUM(INDIRECT(ADDRESS(savings_min_row,COLUMN()) &":"& ADDRESS(savings_max_row,COLUMN())))} -> 0 | EC58: {=SUM(INDIRECT(ADDRESS(savings_min_row,COLUMN()) &":"& ADDRESS(savings_max_row,COLUMN())))} -> 0 | ED58: {=SUM(INDIRECT(ADDRESS(savings_min_row,COLUMN()) &":"& ADDRESS(savings_max_row,COLUMN())))} -> 0 | EE58: {=SUM(INDIRECT(ADDRESS(savings_min_row,COLUMN()) &":"& ADDRESS(savings_max_row,COLUMN())))} -> 0 | EF58: {=SUM(INDIRECT(ADDRESS(savings_min_row,COLUMN()) &":"& ADDRESS(savings_max_row,COLUMN())))} -> 0 | EG58: {=SUM(INDIRECT(ADDRESS(savings_min_row,COLUMN()) &":"& ADDRESS(savings_max_row,COLUMN())))} -> 0 | EH58: {=SUM(INDIRECT(ADDRESS(savings_min_row,COLUMN()) &":"& ADDRESS(savings_max_row,COLUMN())))} -> 0 | ... EM58: {=SUM(INDIRECT(ADDRESS(savings_min_row,COLUMN()) &":"& ADDRESS(savings_max_row,COLUMN())))} -> 0 | EO58: {=SUM(INDIRECT(ADDRESS(savings_min_row,COLUMN()) &":"& ADDRESS(savings_max_row,COLUMN())))} -> 0 | EP58: {=SUM(INDIRECT(ADDRESS(savings_min_row,COLUMN()) &":"& ADDRESS(savings_max_row,COLUMN())))} -> 0 | EQ58: {=SUM(INDIRECT(ADDRESS(savings_min_row,COLUMN()) &":"& ADDRESS(savings_max_row,COLUMN())))} -> 0 | ER58: {=SUM(INDIRECT(ADDRESS(savings_min_row,COLUMN()) &":"& ADDRESS(savings_max_row,COLUMN())))} -> 0 | ES58: {=SUM(INDIRECT(ADDRESS(savings_min_row,COLUMN()) &":"& ADDRESS(savings_max_row,COLUMN())))} -> 0 | ET58: {=SUM(INDIRECT(ADDRESS(savings_min_row,COLUMN()) &":"& ADDRESS(savings_max_row,COLUMN())))} -> 0 | EU58: {=SUM(INDIRECT(ADDRESS(savings_min_row,COLUMN()) &":"& ADDRESS(savings_max_row,COLUMN())))} -> 0 | EV58: {=SUM(INDIRECT(ADDRESS(savings_min_row,COLUMN()) &":"& ADDRESS(savings_max_row,COLUMN())))} -> 0 | ... FA58: {=SUM(INDIRECT(ADDRESS(savings_min_row,COLUMN()) &":"& ADDRESS(savings_max_row,COLUMN())))} -> 0

Sheet Budget Tracking
A1: Budget Tracking
C11: Date | D11: Type | E11: Categories | F11: Amount | G11: Details | H11: Balance
C12: 46025 | D12: Income | E12: Salary (Net) | F12: 25000 | G12: Net Salary received | H12: {=SUMPRODUCT(Tracking[Amount],--(Tracking[Date]<=Tracking[[#This Row],[Date]]),(Tracking[Type]<>"Income")*(-1)+(Tracking[Type]="Income"))} -> 25000
C13: 46026 | D13: Savings | E13: SIP | F13: 3000 | H13: {=SUMPRODUCT(Tracking[Amount],--(Tracking[Date]<=Tracking[[#This Row],[Date]]),(Tracking[Type]<>"Income")*(-1)+(Tracking[Type]="Income"))} -> 22000
C14: 46027 | D14: Expenses | E14: Groceries | F14: 2450 | H14: {=SUMPRODUCT(Tracking[Amount],--(Tracking[Date]<=Tracking[[#This Row],[Date]]),(Tracking[Type]<>"Income")*(-1)+(Tracking[Type]="Income"))} -> 19550
C15: 46029 | D15: Expenses | E15: Insurances | F15: 1050 | H15: {=SUMPRODUCT(Tracking[Amount],--(Tracking[Date]<=Tracking[[#This Row],[Date]]),(Tracking[Type]<>"Income")*(-1)+(Tracking[Type]="Income"))} -> 18500
C16: 46030 | D16: Income | E16: Dividends (Net) | F16: 475 | H16: {=SUMPRODUCT(Tracking[Amount],--(Tracking[Date]<=Tracking[[#This Row],[Date]]),(Tracking[Type]<>"Income")*(-1)+(Tracking[Type]="Income"))} -> 18975
C17: 46031 | D17: Income | E17: Side Hustle (Net) | F17: 8766 | H17: {=SUMPRODUCT(Tracking[Amount],--(Tracking[Date]<=Tracking[[#This Row],[Date]]),(Tracking[Type]<>"Income")*(-1)+(Tracking[Type]="Income"))} -> 27741
C18: 46032 | D18: Income | E18: Freelance (Net) | F18: 922 | H18: {=SUMPRODUCT(Tracking[Amount],--(Tracking[Date]<=Tracking[[#This Row],[Date]]),(Tracking[Type]<>"Income")*(-1)+(Tracking[Type]="Income"))} -> 28663
C19: 46033 | D19: Expenses | E19: MISC | F19: 722 | H19: {=SUMPRODUCT(Tracking[Amount],--(Tracking[Date]<=Tracking[[#This Row],[Date]]),(Tracking[Type]<>"Income")*(-1)+(Tracking[Type]="Income"))} -> 27941
C20: 46034 | D20: Expenses | E20: Clothing | F20: 1023 | H20: {=SUMPRODUCT(Tracking[Amount],--(Tracking[Date]<=Tracking[[#This Row],[Date]]),(Tracking[Type]<>"Income")*(-1)+(Tracking[Type]="Income"))} -> 26918
C21: 46035 | D21: Expenses | E21: Rent | F21: 8500 | H21: {=SUMPRODUCT(Tracking[Amount],--(Tracking[Date]<=Tracking[[#This Row],[Date]]),(Tracking[Type]<>"Income")*(-1)+(Tracking[Type]="Income"))} -> 18418
C22: 46036 | D22: Expenses | E22: Groceries | F22: 12244 | H22: {=SUMPRODUCT(Tracking[Amount],--(Tracking[Date]<=Tracking[[#This Row],[Date]]),(Tracking[Type]<>"Income")*(-1)+(Tracking[Type]="Income"))} -> 6174
C23: 46044 | D23: Expenses | E23: Fuel | F23: 3000 | H23: {=SUMPRODUCT(Tracking[Amount],--(Tracking[Date]<=Tracking[[#This Row],[Date]]),(Tracking[Type]<>"Income")*(-1)+(Tracking[Type]="Income"))} -> 3174
C24: 46055 | D24: Income | E24: Salary (Net) | F24: 30000 | H24: {=SUMPRODUCT(Tracking[Amount],--(Tracking[Date]<=Tracking[[#This Row],[Date]]),(Tracking[Type]<>"Income")*(-1)+(Tracking[Type]="Income"))} -> 33174
... C48: 46093 | D48: Savings | E48: Mcleodganj Trip Fund | F48: 20000 | H48: {=SUMPRODUCT(Tracking[Amount],--(Tracking[Date]<=Tracking[[#This Row],[Date]]),(Tracking[Type]<>"Income")*(-1)+(Tracking[Type]="Income"))} -> 114723

Sheet Budget Dashboard
A1: Budget Dashboard
AQ5: Year
AN6: Select the year to view ➜ | AQ6: Current Year
AQ8: Period
AN9: Select the period to view ➜ | AQ9: Total Year
Y11: ="Breakdown-"& IF( selected_period="Total Year", selected_year & "(Total Year)",selected_period_display & " " & selected_year) -> Breakdown-2026(Total Year) | AF11: ="Summary-"& IF( selected_period="Total Year", selected_year & "(Total Year)",selected_period_display & " " & selected_year) -> Summary-2026(Total Year)
C12: row_id | D12: header_row_id | E12: is_header | F12: is_cat | G12: is_total | H12: is_empty | I12: type | J12: item | K12: tracked | L12: budget | M12: sort_min_row | N12: sort_max_row | O12: tracked_range | P12: tracked_rank | Q12: budget_range | R12: budget_rank | S12: comb_rank | T12: comb_rank_range | U12: comb_rank_norm | V12: comb_rank_norm_run_range | W12: comb_rank_unique | X12: sorted_row_id[Lookup]
C13: {=Income_header_row} -> 9 | D13: =IF(is_header,row_id,IF(NOT(is_empty),D12,-1)) -> 9 | E13: {=1*OR(row_id=Income_header_row, row_id=expenses_header_row, row_id=savings_header_row)} -> 1 | F13: =1*NOT(OR(is_header, is_total, is_empty)) -> 0 | G13: {=1*OR(row_id=income_total_row, row_id=expenses_total_row, row_id=savings_total_row)} -> 0 | H13: =1*OR(row_id="/1", row_id="/2", row_id=-1) -> 0 | I13: {=IFERROR(INDEX('Budget Planning'!$C:$C,header_row_id),"")} -> Income | J13: {=IFERROR(INDEX('Budget Planning'!$C:$C,row_id),"")} -> Income | K13: {=IF(OR(is_header,is_empty),"",IF(is_total,IF(selected_period="Total Year",SUMPRODUCT(Tracking[Amount],--(TRIM(Tracking[Type])=TRIM(type)),--(Tracking[Date]>=DATE(selected_year,1,1)),--(Tracking[Date]<DATE(selected_year+1,1,1))),SUMPRODUCT(Tracking[Amount],--(TRIM(Tracking[Type])=TRIM(type)),--(Tracking[Date]>=DATE(selected_year,1,1)),--(Tracking[Date]<DATE(selected_year+1,1,1)),--(MONTH(Tracking[Date])=selected_period))),IF(selected_period="Total Year",SUMPRODUCT(Tracking[Amount],--(TRIM(Tracking[Type])=TRIM(type)),--(TRIM(Tracking[Categories])=TRIM(item)),--(Tracking[Date]>=DATE(selected_year,1,1)),--(Tracking[Date]<DATE(selected_year+1,1,1))),SUMPRODUCT(Tracking[Amount],--(TRIM(Tracking[Type])=TRIM(type)),--(TRIM(Tracking[Categories])=TRIM(item)),--(Tracking[Date]>=DATE(selected_year,1,1)),--(Tracking[Date]<DATE(selected_year+1,1,1)),--(MONTH(Tracking[Date])=selected_period)))))} | L13: {=IF(OR(is_header,is_empty),"",INDEX('Budget Planning'!$E:$FA,row_id,MATCH(IF(selected_period="Total Year",selected_year,DATE(selected_year,selected_period,1)),'Budget Planning'!$E$9:$FA$9,0)))} | M13: {=IF(is_cat,IF(header_row_id=Income_header_row, MATCH(income_min_row,$C:$C,0),IF(header_row_id=expenses_header_row, MATCH(expenses_min_row,$C:$C,0),IF(header_row_id=savings_header_row, MATCH(savings_min_row,$C:$C,0),""))),"")} | N13: {=IF(is_cat,IF(header_row_id=Income_header_row, MATCH(income_max_row,$C:$C,0),IF(header_row_id=expenses_header_row, MATCH(expenses_max_row,$C:$C,0),IF(header_row_id=savings_header_row, MATCH(savings_max_row,$C:$C,0),""))),"")} | O13: =IF(is_cat,ADDRESS(sort_min_row,COLUMN(tracked))&":"&ADDRESS(sort_max_row,COLUMN(tracked)),"") | P13: =IF(is_cat,RANK(tracked,INDIRECT(tracked_range),0),"") | Q13: =IF(is_cat,ADDRESS(sort_min_row,COLUMN(budget))&":"&ADDRESS(sort_max_row,COLUMN(budget)),"") | R13: =IF(is_cat,RANK(budget,INDIRECT(budget_range),0),"") | S13: =IF(is_cat,_xlfn.NUMBERVALUE(tracked_rank & budget_rank),"") | T13: =IF(is_cat,ADDRESS(sort_min_row,COLUMN(comb_rank))&":"&ADDRESS(sort_max_row,COLUMN(comb_rank)),"") | U13: =IF(is_cat, RANK(comb_rank, INDIRECT(comb_rank_range),1),"") | V13: =IF(is_cat,ADDRESS(sort_min_row,COLUMN(comb_rank_norm))&":"&ADDRESS(ROW(),COLUMN(comb_rank_norm)),"") | W13: =IF(is_cat,comb_rank_norm+COUNTIF(INDIRECT(comb_rank_norm_run_range),comb_rank_norm)-1,"") | X13: =IF(is_cat,header_row_id+comb_rank_unique,row_id) -> 9 | Y13: =IF(is_empty,"",INDEX($J:$J,MATCH(row_id,$X:$X,0))) -> Income | Z13: =IF(is_empty,"",IF(is_header,"Tracked",INDEX($K:$K,MATCH(row_id,$X:$X,0)))) -> Tracked | AA13: =IF(is_empty,"",IF(is_header,"Budget",INDEX($L:$L,MATCH(row_id,$X:$X,0)))) -> Budget | AB13: =IF(is_empty,"",IF(is_header,"% Compl.",IFERROR(out_tracked/out_budget,"-"))) -> % Compl. | AC13: =IF(is_empty,"",IF(is_header,"Remaining",IF(out_budget-out_tracked>0,out_budget-out_tracked,0))) -> Remaining | AD13: =IF(is_empty,"",IF(is_header,"Excess",IF(out_budget-out_tracked<0,out_tracked-out_budget,0))) -> Excess
C14: {=IF(C13=-1,-1, IF(C13<income_max_row,C13+1,IF(C13=income_max_row,income_total_row,IF(C13=income_total_row,"/1", IF(C13="/1",expenses_header_row,IF(C13<expenses_max_row,C13+1,IF(C13=expenses_max_row,expenses_total_row,IF(C13=expenses_total_row,"/2",IF(C13="/2",savings_header_row,IF(C13<savings_max_row,C13+1,IF(C13=savings_max_row,savings_total_row,-1)))))))))))} -> 10 | D14: =IF(is_header,row_id,IF(NOT(is_empty),D13,-1)) -> 9 | E14: {=1*OR(row_id=Income_header_row, row_id=expenses_header_row, row_id=savings_header_row)} -> 0 | F14: =1*NOT(OR(is_header, is_total, is_empty)) -> 1 | G14: {=1*OR(row_id=income_total_row, row_id=expenses_total_row, row_id=savings_total_row)} -> 0 | H14: =1*OR(row_id="/1", row_id="/2", row_id=-1) -> 0 | I14: {=IFERROR(INDEX('Budget Planning'!$C:$C,header_row_id),"")} -> Income | J14: {=IFERROR(INDEX('Budget Planning'!$C:$C,row_id),"")} -> Salary (Net) | K14: {=IF(OR(is_header,is_empty),"",IF(is_total,IF(selected_period="Total Year",SUMPRODUCT(Tracking[Amount],--(TRIM(Tracking[Type])=TRIM(type)),--(Tracking[Date]>=DATE(selected_year,1,1)),--(Tracking[Date]<DATE(selected_year+1,1,1))),SUMPRODUCT(Tracking[Amount],--(TRIM(Tracking[Type])=TRIM(type)),--(Tracking[Date]>=DATE(selected_year,1,1)),--(Tracking[Date]<DATE(selected_year+1,1,1)),--(MONTH(Tracking[Date])=selected_period))),IF(selected_period="Total Year",SUMPRODUCT(Tracking[Amount],--(TRIM(Tracking[Type])=TRIM(type)),--(TRIM(Tracking[Categories])=TRIM(item)),--(Tracking[Date]>=DATE(selected_year,1,1)),--(Tracking[Date]<DATE(selected_year+1,1,1))),SUMPRODUCT(Tracking[Amount],--(TRIM(Tracking[Type])=TRIM(type)),--(TRIM(Tracking[Categories])=TRIM(item)),--(Tracking[Date]>=DATE(selected_year,1,1)),--(Tracking[Date]<DATE(selected_year+1,1,1)),--(MONTH(Tracking[Date])=selected_period)))))} -> 143954 | L14: {=IF(OR(is_header,is_empty),"",INDEX('Budget Planning'!$E:$FA,row_id,MATCH(IF(selected_period="Total Year",selected_year,DATE(selected_year,selected_period,1)),'Budget Planning'!$E$9:$FA$9,0)))} -> 911182 | M14: {=IF(is_cat,IF(header_row_id=Income_header_row, MATCH(income_min_row,$C:$C,0),IF(header_row_id=expenses_header_row, MATCH(expenses_min_row,$C:$C,0),IF(header_row_id=savings_header_row, MATCH(savings_min_row,$C:$C,0),""))),"")} -> 14 | N14: {=IF(is_cat,IF(header_row_id=Income_header_row, MATCH(income_max_row,$C:$C,0),IF(header_row_id=expenses_header_row, MATCH(expenses_max_row,$C:$C,0),IF(header_row_id=savings_header_row, MATCH(savings_max_row,$C:$C,0),""))),"")} -> 17 | O14: =IF(is_cat,ADDRESS(sort_min_row,COLUMN(tracked))&":"&ADDRESS(sort_max_row,COLUMN(tracked)),"") -> $K$14:$K$17 | P14: =IF(is_cat,RANK(tracked,INDIRECT(tracked_range),0),"") -> 1 | Q14: =IF(is_cat,ADDRESS(sort_min_row,COLUMN(budget))&":"&ADDRESS(sort_max_row,COLUMN(budget)),"") -> $L$14:$L$17 | R14: =IF(is_cat,RANK(budget,INDIRECT(budget_range),0),"") -> 1 | S14: =IF(is_cat,_xlfn.NUMBERVALUE(tracked_rank & budget_rank),"") -> 11 | T14: =IF(is_cat,ADDRESS(sort_min_row,COLUMN(comb_rank))&":"&ADDRESS(sort_max_row,COLUMN(comb_rank)),"") -> $S$14:$S$17 | U14: =IF(is_cat, RANK(comb_rank, INDIRECT(comb_rank_range),1),"") -> 1 | V14: =IF(is_cat,ADDRESS(sort_min_row,COLUMN(comb_rank_norm))&":"&ADDRESS(ROW(),COLUMN(comb_rank_norm)),"") -> $U$14:$U$14 | W14: =IF(is_cat,comb_rank_norm+COUNTIF(INDIRECT(comb_rank_norm_run_range),comb_rank_norm)-1,"") -> 1 | X14: =IF(is_cat,header_row_id+comb_rank_unique,row_id) -> 10 | Y14: =IF(is_empty,"",INDEX($J:$J,MATCH(row_id,$X:$X,0))) -> Salary (Net) | Z14: =IF(is_empty,"",IF(is_header,"Tracked",INDEX($K:$K,MATCH(row_id,$X:$X,0)))) -> 143954 | AA14: =IF(is_empty,"",IF(is_header,"Budget",INDEX($L:$L,MATCH(row_id,$X:$X,0)))) -> 911182 | AB14: =IF(is_empty,"",IF(is_header,"% Compl.",IFERROR(out_tracked/out_budget,"-"))) -> 0.157986 | AC14: =IF(is_empty,"",IF(is_header,"Remaining",IF(out_budget-out_tracked>0,out_budget-out_tracked,0))) -> 767228 | AD14: =IF(is_empty,"",IF(is_header,"Excess",IF(out_budget-out_tracked<0,out_tracked-out_budget,0))) -> 0
C15: {=IF(C14=-1,-1, IF(C14<income_max_row,C14+1,IF(C14=income_max_row,income_total_row,IF(C14=income_total_row,"/1", IF(C14="/1",expenses_header_row,IF(C14<expenses_max_row,C14+1,IF(C14=expenses_max_row,expenses_total_row,IF(C14=expenses_total_row,"/2",IF(C14="/2",savings_header_row,IF(C14<savings_max_row,C14+1,IF(C14=savings_max_row,savings_total_row,-1)))))))))))} -> 11 | D15: =IF(is_header,row_id,IF(NOT(is_empty),D14,-1)) -> 9 | E15: {=1*OR(row_id=Income_header_row, row_id=expenses_header_row, row_id=savings_header_row)} -> 0 | F15: =1*NOT(OR(is_header, is_total, is_empty)) -> 1 | G15: {=1*OR(row_id=income_total_row, row_id=expenses_total_row, row_id=savings_total_row)} -> 0 | H15: =1*OR(row_id="/1", row_id="/2", row_id=-1) -> 0 | I15: {=IFERROR(INDEX('Budget Planning'!$C:$C,header_row_id),"")} -> Income | J15: {=IFERROR(INDEX('Budget Planning'!$C:$C,row_id),"")} -> Side Hustle (Net) | K15: {=IF(OR(is_header,is_empty),"",IF(is_total,IF(selected_period="Total Year",SUMPRODUCT(Tracking[Amount],--(TRIM(Tracking[Type])=TRIM(type)),--(Tracking[Date]>=DATE(selected_year,1,1)),--(Tracking[Date]<DATE(selected_year+1,1,1))),SUMPRODUCT(Tracking[Amount],--(TRIM(Tracking[Type])=TRIM(type)),--(Tracking[Date]>=DATE(selected_year,1,1)),--(Tracking[Date]<DATE(selected_year+1,1,1)),--(MONTH(Tracking[Date])=selected_period))),IF(selected_period="Total Year",SUMPRODUCT(Tracking[Amount],--(TRIM(Tracking[Type])=TRIM(type)),--(TRIM(Tracking[Categories])=TRIM(item)),--(Tracking[Date]>=DATE(selected_year,1,1)),--(Tracking[Date]<DATE(selected_year+1,1,1))),SUMPRODUCT(Tracking[Amount],--(TRIM(Tracking[Type])=TRIM(type)),--(TRIM(Tracking[Categories])=TRIM(item)),--(Tracking[Date]>=DATE(selected_year,1,1)),--(Tracking[Date]<DATE(selected_year+1,1,1)),--(MONTH(Tracking[Date])=selected_period)))))} -> 103163 | L15: {=IF(OR(is_header,is_empty),"",INDEX('Budget Planning'!$E:$FA,row_id,MATCH(IF(selected_period="Total Year",selected_year,DATE(selected_year,selected_period,1)),'Budget Planning'!$E$9:$FA$9,0)))} -> 299323 | M15: {=IF(is_cat,IF(header_row_id=Income_header_row, MATCH(income_min_row,$C:$C,0),IF(header_row_id=expenses_header_row, MATCH(expenses_min_row,$C:$C,0),IF(header_row_id=savings_header_row, MATCH(savings_min_row,$C:$C,0),""))),"")} -> 14 | N15: {=IF(is_cat,IF(header_row_id=Income_header_row, MATCH(income_max_row,$C:$C,0),IF(header_row_id=expenses_header_row, MATCH(expenses_max_row,$C:$C,0),IF(header_row_id=savings_header_row, MATCH(savings_max_row,$C:$C,0),""))),"")} -> 17 | O15: =IF(is_cat,ADDRESS(sort_min_row,COLUMN(tracked))&":"&ADDRESS(sort_max_row,COLUMN(tracked)),"") -> $K$14:$K$17 | P15: =IF(is_cat,RANK(tracked,INDIRECT(tracked_range),0),"") -> 2 | Q15: =IF(is_cat,ADDRESS(sort_min_row,COLUMN(budget))&":"&ADDRESS(sort_max_row,COLUMN(budget)),"") -> $L$14:$L$17 | R15: =IF(is_cat,RANK(budget,INDIRECT(budget_range),0),"") -> 2 | S15: =IF(is_cat,_xlfn.NUMBERVALUE(tracked_rank & budget_rank),"") -> 22 | T15: =IF(is_cat,ADDRESS(sort_min_row,COLUMN(comb_rank))&":"&ADDRESS(sort_max_row,COLUMN(comb_rank)),"") -> $S$14:$S$17 | U15: =IF(is_cat, RANK(comb_rank, INDIRECT(comb_rank_range),1),"") -> 2 | V15: =IF(is_cat,ADDRESS(sort_min_row,COLUMN(comb_rank_norm))&":"&ADDRESS(ROW(),COLUMN(comb_rank_norm)),"") -> $U$14:$U$15 | W15: =IF(is_cat,comb_rank_norm+COUNTIF(INDIRECT(comb_rank_norm_run_range),comb_rank_norm)-1,"") -> 2 | X15: =IF(is_cat,header_row_id+comb_rank_unique,row_id) -> 11 | Y15: =IF(is_empty,"",INDEX($J:$J,MATCH(row_id,$X:$X,0))) -> Side Hustle (Net) | Z15: =IF(is_empty,"",IF(is_header,"Tracked",INDEX($K:$K,MATCH(row_id,$X:$X,0)))) -> 103163 | AA15: =IF(is_empty,"",IF(is_header,"Budget",INDEX($L:$L,MATCH(row_id,$X:$X,0)))) -> 299323 | AB15: =IF(is_empty,"",IF(is_header,"% Compl.",IFERROR(out_tracked/out_budget,"-"))) -> 0.34465444 | AC15: =IF(is_empty,"",IF(is_header,"Remaining",IF(out_budget-out_tracked>0,out_budget-out_tracked,0))) -> 196160 | AD15: =IF(is_empty,"",IF(is_header,"Excess",IF(out_budget-out_tracked<0,out_tracked-out_budget,0))) -> 0
C16: {=IF(C15=-1,-1, IF(C15<income_max_row,C15+1,IF(C15=income_max_row,income_total_row,IF(C15=income_total_row,"/1", IF(C15="/1",expenses_header_row,IF(C15<expenses_max_row,C15+1,IF(C15=expenses_max_row,expenses_total_row,IF(C15=expenses_total_row,"/2",IF(C15="/2",savings_header_row,IF(C15<savings_max_row,C15+1,IF(C15=savings_max_row,savings_total_row,-1)))))))))))} -> 12 | D16: =IF(is_header,row_id,IF(NOT(is_empty),D15,-1)) -> 9 | E16: {=1*OR(row_id=Income_header_row, row_id=expenses_header_row, row_id=savings_header_row)} -> 0 | F16: =1*NOT(OR(is_header, is_total, is_empty)) -> 1 | G16: {=1*OR(row_id=income_total_row, row_id=expenses_total_row, row_id=savings_total_row)} -> 0 | H16: =1*OR(row_id="/1", row_id="/2", row_id=-1) -> 0 | I16: {=IFERROR(INDEX('Budget Planning'!$C:$C,header_row_id),"")} -> Income | J16: {=IFERROR(INDEX('Budget Planning'!$C:$C,row_id),"")} -> Dividends (Net) | K16: {=IF(OR(is_header,is_empty),"",IF(is_total,IF(selected_period="Total Year",SUMPRODUCT(Tracking[Amount],--(TRIM(Tracking[Type])=TRIM(type)),--(Tracking[Date]>=DATE(selected_year,1,1)),--(Tracking[Date]<DATE(selected_year+1,1,1))),SUMPRODUCT(Tracking[Amount],--(TRIM(Tracking[Type])=TRIM(type)),--(Tracking[Date]>=DATE(selected_year,1,1)),--(Tracking[Date]<DATE(selected_year+1,1,1)),--(MONTH(Tracking[Date])=selected_period))),IF(selected_period="Total Year",SUMPRODUCT(Tracking[Amount],--(TRIM(Tracking[Type])=TRIM(type)),--(TRIM(Tracking[Categories])=TRIM(item)),--(Tracking[Date]>=DATE(selected_year,1,1)),--(Tracking[Date]<DATE(selected_year+1,1,1))),SUMPRODUCT(Tracking[Amount],--(TRIM(Tracking[Type])=TRIM(type)),--(TRIM(Tracking[Categories])=TRIM(item)),--(Tracking[Date]>=DATE(selected_year,1,1)),--(Tracking[Date]<DATE(selected_year+1,1,1)),--(MONTH(Tracking[Date])=selected_period)))))} -> 19950 | L16: {=IF(OR(is_header,is_empty),"",INDEX('Budget Planning'!$E:$FA,row_id,MATCH(IF(selected_period="Total Year",selected_year,DATE(selected_year,selected_period,1)),'Budget Planning'!$E$9:$FA$9,0)))} -> 1930 | M16: {=IF(is_cat,IF(header_row_id=Income_header_row, MATCH(income_min_row,$C:$C,0),IF(header_row_id=expenses_header_row, MATCH(expenses_min_row,$C:$C,0),IF(header_row_id=savings_header_row, MATCH(savings_min_row,$C:$C,0),""))),"")} -> 14 | N16: {=IF(is_cat,IF(header_row_id=Income_header_row, MATCH(income_max_row,$C:$C,0),IF(header_row_id=expenses_header_row, MATCH(expenses_max_row,$C:$C,0),IF(header_row_id=savings_header_row, MATCH(savings_max_row,$C:$C,0),""))),"")} -> 17 | O16: =IF(is_cat,ADDRESS(sort_min_row,COLUMN(tracked))&":"&ADDRESS(sort_max_row,COLUMN(tracked)),"") -> $K$14:$K$17 | P16: =IF(is_cat,RANK(tracked,INDIRECT(tracked_range),0),"") -> 4 | Q16: =IF(is_cat,ADDRESS(sort_min_row,COLUMN(budget))&":"&ADDRESS(sort_max_row,COLUMN(budget)),"") -> $L$14:$L$17 | R16: =IF(is_cat,RANK(budget,INDIRECT(budget_range),0),"") -> 4 | S16: =IF(is_cat,_xlfn.NUMBERVALUE(tracked_rank & budget_rank),"") -> 44 | T16: =IF(is_cat,ADDRESS(sort_min_row,COLUMN(comb_rank))&":"&ADDRESS(sort_max_row,COLUMN(comb_rank)),"") -> $S$14:$S$17 | U16: =IF(is_cat, RANK(comb_rank, INDIRECT(comb_rank_range),1),"") -> 4 | V16: =IF(is_cat,ADDRESS(sort_min_row,COLUMN(comb_rank_norm))&":"&ADDRESS(ROW(),COLUMN(comb_rank_norm)),"") -> $U$14:$U$16 | W16: =IF(is_cat,comb_rank_norm+COUNTIF(INDIRECT(comb_rank_norm_run_range),comb_rank_norm)-1,"") -> 4 | X16: =IF(is_cat,header_row_id+comb_rank_unique,row_id) -> 13 | Y16: =IF(is_empty,"",INDEX($J:$J,MATCH(row_id,$X:$X,0))) -> Freelance (Net) | Z16: =IF(is_empty,"",IF(is_header,"Tracked",INDEX($K:$K,MATCH(row_id,$X:$X,0)))) -> 50897 | AA16: =IF(is_empty,"",IF(is_header,"Budget",INDEX($L:$L,MATCH(row_id,$X:$X,0)))) -> 113448 | AB16: =IF(is_empty,"",IF(is_header,"% Compl.",IFERROR(out_tracked/out_budget,"-"))) -> 0.44863726 | AC16: =IF(is_empty,"",IF(is_header,"Remaining",IF(out_budget-out_tracked>0,out_budget-out_tracked,0))) -> 62551 | AD16: =IF(is_empty,"",IF(is_header,"Excess",IF(out_budget-out_tracked<0,out_tracked-out_budget,0))) -> 0
C17: {=IF(C16=-1,-1, IF(C16<income_max_row,C16+1,IF(C16=income_max_row,income_total_row,IF(C16=income_total_row,"/1", IF(C16="/1",expenses_header_row,IF(C16<expenses_max_row,C16+1,IF(C16=expenses_max_row,expenses_total_row,IF(C16=expenses_total_row,"/2",IF(C16="/2",savings_header_row,IF(C16<savings_max_row,C16+1,IF(C16=savings_max_row,savings_total_row,-1)))))))))))} -> 13 | D17: =IF(is_header,row_id,IF(NOT(is_empty),D16,-1)) -> 9 | E17: {=1*OR(row_id=Income_header_row, row_id=expenses_header_row, row_id=savings_header_row)} -> 0 | F17: =1*NOT(OR(is_header, is_total, is_empty)) -> 1 | G17: {=1*OR(row_id=income_total_row, row_id=expenses_total_row, row_id=savings_total_row)} -> 0 | H17: =1*OR(row_id="/1", row_id="/2", row_id=-1) -> 0 | I17: {=IFERROR(INDEX('Budget Planning'!$C:$C,header_row_id),"")} -> Income | J17: {=IFERROR(INDEX('Budget Planning'!$C:$C,row_id),"")} -> Freelance (Net) | K17: {=IF(OR(is_header,is_empty),"",IF(is_total,IF(selected_period="Total Year",SUMPRODUCT(Tracking[Amount],--(TRIM(Tracking[Type])=TRIM(type)),--(Tracking[Date]>=DATE(selected_year,1,1)),--(Tracking[Date]<DATE(selected_year+1,1,1))),SUMPRODUCT(Tracking[Amount],--(TRIM(Tracking[Type])=TRIM(type)),--(Tracking[Date]>=DATE(selected_year,1,1)),--(Tracking[Date]<DATE(selected_year+1,1,1)),--(MONTH(Tracking[Date])=selected_period))),IF(selected_period="Total Year",SUMPRODUCT(Tracking[Amount],--(TRIM(Tracking[Type])=TRIM(type)),--(TRIM(Tracking[Categories])=TRIM(item)),--(Tracking[Date]>=DATE(selected_year,1,1)),--(Tracking[Date]<DATE(selected_year+1,1,1))),SUMPRODUCT(Tracking[Amount],--(TRIM(Tracking[Type])=TRIM(type)),--(TRIM(Tracking[Categories])=TRIM(item)),--(Tracking[Date]>=DATE(selected_year,1,1)),--(Tracking[Date]<DATE(selected_year+1,1,1)),--(MONTH(Tracking[Date])=selected_period)))))} -> 50897 | L17: {=IF(OR(is_header,is_empty),"",INDEX('Budget Planning'!$E:$FA,row_id,MATCH(IF(selected_period="Total Year",selected_year,DATE(selected_year,selected_period,1)),'Budget Planning'!$E$9:$FA$9,0)))} -> 113448 | M17: {=IF(is_cat,IF(header_row_id=Income_header_row, MATCH(income_min_row,$C:$C,0),IF(header_row_id=expenses_header_row, MATCH(expenses_min_row,$C:$C,0),IF(header_row_id=savings_header_row, MATCH(savings_min_row,$C:$C,0),""))),"")} -> 14 | N17: {=IF(is_cat,IF(header_row_id=Income_header_row, MATCH(income_max_row,$C:$C,0),IF(header_row_id=expenses_header_row, MATCH(expenses_max_row,$C:$C,0),IF(header_row_id=savings_header_row, MATCH(savings_max_row,$C:$C,0),""))),"")} -> 17 | O17: =IF(is_cat,ADDRESS(sort_min_row,COLUMN(tracked))&":"&ADDRESS(sort_max_row,COLUMN(tracked)),"") -> $K$14:$K$17 | P17: =IF(is_cat,RANK(tracked,INDIRECT(tracked_range),0),"") -> 3 | Q17: =IF(is_cat,ADDRESS(sort_min_row,COLUMN(budget))&":"&ADDRESS(sort_max_row,COLUMN(budget)),"") -> $L$14:$L$17 | R17: =IF(is_cat,RANK(budget,INDIRECT(budget_range),0),"") -> 3 | S17: =IF(is_cat,_xlfn.NUMBERVALUE(tracked_rank & budget_rank),"") -> 33 | T17: =IF(is_cat,ADDRESS(sort_min_row,COLUMN(comb_rank))&":"&ADDRESS(sort_max_row,COLUMN(comb_rank)),"") -> $S$14:$S$17 | U17: =IF(is_cat, RANK(comb_rank, INDIRECT(comb_rank_range),1),"") -> 3 | V17: =IF(is_cat,ADDRESS(sort_min_row,COLUMN(comb_rank_norm))&":"&ADDRESS(ROW(),COLUMN(comb_rank_norm)),"") -> $U$14:$U$17 | W17: =IF(is_cat,comb_rank_norm+COUNTIF(INDIRECT(comb_rank_norm_run_range),comb_rank_norm)-1,"") -> 3 | X17: =IF(is_cat,header_row_id+comb_rank_unique,row_id) -> 12 | Y17: =IF(is_empty,"",INDEX($J:$J,MATCH(row_id,$X:$X,0))) -> Dividends (Net) | Z17: =IF(is_empty,"",IF(is_header,"Tracked",INDEX($K:$K,MATCH(row_id,$X:$X,0)))) -> 19950 | AA17: =IF(is_empty,"",IF(is_header,"Budget",INDEX($L:$L,MATCH(row_id,$X:$X,0)))) -> 1930 | AB17: =IF(is_empty,"",IF(is_header,"% Compl.",IFERROR(out_tracked/out_budget,"-"))) -> 10.336788 | AC17: =IF(is_empty,"",IF(is_header,"Remaining",IF(out_budget-out_tracked>0,out_budget-out_tracked,0))) -> 0 | AD17: =IF(is_empty,"",IF(is_header,"Excess",IF(out_budget-out_tracked<0,out_tracked-out_budget,0))) -> 18020 | AI17: =Calculations!E35 -> Salary (Net) | AJ17: =Calculations!F35 -> 143954
C18: {=IF(C17=-1,-1, IF(C17<income_max_row,C17+1,IF(C17=income_max_row,income_total_row,IF(C17=income_total_row,"/1", IF(C17="/1",expenses_header_row,IF(C17<expenses_max_row,C17+1,IF(C17=expenses_max_row,expenses_total_row,IF(C17=expenses_total_row,"/2",IF(C17="/2",savings_header_row,IF(C17<savings_max_row,C17+1,IF(C17=savings_max_row,savings_total_row,-1)))))))))))} -> 24 | D18: =IF(is_header,row_id,IF(NOT(is_empty),D17,-1)) -> 9 | E18: {=1*OR(row_id=Income_header_row, row_id=expenses_header_row, row_id=savings_header_row)} -> 0 | F18: =1*NOT(OR(is_header, is_total, is_empty)) -> 0 | G18: {=1*OR(row_id=income_total_row, row_id=expenses_total_row, row_id=savings_total_row)} -> 1 | H18: =1*OR(row_id="/1", row_id="/2", row_id=-1) -> 0 | I18: {=IFERROR(INDEX('Budget Planning'!$C:$C,header_row_id),"")} -> Income | J18: {=IFERROR(INDEX('Budget Planning'!$C:$C,row_id),"")} -> Total | K18: {=IF(OR(is_header,is_empty),"",IF(is_total,IF(selected_period="Total Year",SUMPRODUCT(Tracking[Amount],--(TRIM(Tracking[Type])=TRIM(type)),--(Tracking[Date]>=DATE(selected_year,1,1)),--(Tracking[Date]<DATE(selected_year+1,1,1))),SUMPRODUCT(Tracking[Amount],--(TRIM(Tracking[Type])=TRIM(type)),--(Tracking[Date]>=DATE(selected_year,1,1)),--(Tracking[Date]<DATE(selected_year+1,1,1)),--(MONTH(Tracking[Date])=selected_period))),IF(selected_period="Total Year",SUMPRODUCT(Tracking[Amount],--(TRIM(Tracking[Type])=TRIM(type)),--(TRIM(Tracking[Categories])=TRIM(item)),--(Tracking[Date]>=DATE(selected_year,1,1)),--(Tracking[Date]<DATE(selected_year+1,1,1))),SUMPRODUCT(Tracking[Amount],--(TRIM(Tracking[Type])=TRIM(type)),--(TRIM(Tracking[Categories])=TRIM(item)),--(Tracking[Date]>=DATE(selected_year,1,1)),--(Tracking[Date]<DATE(selected_year+1,1,1)),--(MONTH(Tracking[Date])=selected_period)))))} -> 317964 | L18: {=IF(OR(is_header,is_empty),"",INDEX('Budget Planning'!$E:$FA,row_id,MATCH(IF(selected_period="Total Year",selected_year,DATE(selected_year,selected_period,1)),'Budget Planning'!$E$9:$FA$9,0)))} -> 1325883 | M18: {=IF(is_cat,IF(header_row_id=Income_header_row, MATCH(income_min_row,$C:$C,0),IF(header_row_id=expenses_header_row, MATCH(expenses_min_row,$C:$C,0),IF(header_row_id=savings_header_row, MATCH(savings_min_row,$C:$C,0),""))),"")} | N18: {=IF(is_cat,IF(header_row_id=Income_header_row, MATCH(income_max_row,$C:$C,0),IF(header_row_id=expenses_header_row, MATCH(expenses_max_row,$C:$C,0),IF(header_row_id=savings_header_row, MATCH(savings_max_row,$C:$C,0),""))),"")} | O18: =IF(is_cat,ADDRESS(sort_min_row,COLUMN(tracked))&":"&ADDRESS(sort_max_row,COLUMN(tracked)),"") | P18: =IF(is_cat,RANK(tracked,INDIRECT(tracked_range),0),"") | Q18: =IF(is_cat,ADDRESS(sort_min_row,COLUMN(budget))&":"&ADDRESS(sort_max_row,COLUMN(budget)),"") | R18: =IF(is_cat,RANK(budget,INDIRECT(budget_range),0),"") | S18: =IF(is_cat,_xlfn.NUMBERVALUE(tracked_rank & budget_rank),"") | T18: =IF(is_cat,ADDRESS(sort_min_row,COLUMN(comb_rank))&":"&ADDRESS(sort_max_row,COLUMN(comb_rank)),"") | U18: =IF(is_cat, RANK(comb_rank, INDIRECT(comb_rank_range),1),"") | V18: =IF(is_cat,ADDRESS(sort_min_row,COLUMN(comb_rank_norm))&":"&ADDRESS(ROW(),COLUMN(comb_rank_norm)),"") | W18: =IF(is_cat,comb_rank_norm+COUNTIF(INDIRECT(comb_rank_norm_run_range),comb_rank_norm)-1,"") | X18: =IF(is_cat,header_row_id+comb_rank_unique,row_id) -> 24 | Y18: =IF(is_empty,"",INDEX($J:$J,MATCH(row_id,$X:$X,0))) -> Total | Z18: =IF(is_empty,"",IF(is_header,"Tracked",INDEX($K:$K,MATCH(row_id,$X:$X,0)))) -> 317964 | AA18: =IF(is_empty,"",IF(is_header,"Budget",INDEX($L:$L,MATCH(row_id,$X:$X,0)))) -> 1325883 | AB18: =IF(is_empty,"",IF(is_header,"% Compl.",IFERROR(out_tracked/out_budget,"-"))) -> 0.23981302 | AC18: =IF(is_empty,"",IF(is_header,"Remaining",IF(out_budget-out_tracked>0,out_budget-out_tracked,0))) -> 1007919 | AD18: =IF(is_empty,"",IF(is_header,"Excess",IF(out_budget-out_tracked<0,out_tracked-out_budget,0))) -> 0 | AI18: =Calculations!E36 -> Side Hustle (Net) | AJ18: =Calculations!F36 -> 103163
C19: {=IF(C18=-1,-1, IF(C18<income_max_row,C18+1,IF(C18=income_max_row,income_total_row,IF(C18=income_total_row,"/1", IF(C18="/1",expenses_header_row,IF(C18<expenses_max_row,C18+1,IF(C18=expenses_max_row,expenses_total_row,IF(C18=expenses_total_row,"/2",IF(C18="/2",savings_header_row,IF(C18<savings_max_row,C18+1,IF(C18=savings_max_row,savings_total_row,-1)))))))))))} -> /1 | D19: =IF(is_header,row_id,IF(NOT(is_empty),D18,-1)) -> -1 | E19: {=1*OR(row_id=Income_header_row, row_id=expenses_header_row, row_id=savings_header_row)} -> 0 | F19: =1*NOT(OR(is_header, is_total, is_empty)) -> 0 | G19: {=1*OR(row_id=income_total_row, row_id=expenses_total_row, row_id=savings_total_row)} -> 0 | H19: =1*OR(row_id="/1", row_id="/2", row_id=-1) -> 1 | I19: {=IFERROR(INDEX('Budget Planning'!$C:$C,header_row_id),"")} | J19: {=IFERROR(INDEX('Budget Planning'!$C:$C,row_id),"")} | K19: {=IF(OR(is_header,is_empty),"",IF(is_total,IF(selected_period="Total Year",SUMPRODUCT(Tracking[Amount],--(TRIM(Tracking[Type])=TRIM(type)),--(Tracking[Date]>=DATE(selected_year,1,1)),--(Tracking[Date]<DATE(selected_year+1,1,1))),SUMPRODUCT(Tracking[Amount],--(TRIM(Tracking[Type])=TRIM(type)),--(Tracking[Date]>=DATE(selected_year,1,1)),--(Tracking[Date]<DATE(selected_year+1,1,1)),--(MONTH(Tracking[Date])=selected_period))),IF(selected_period="Total Year",SUMPRODUCT(Tracking[Amount],--(TRIM(Tracking[Type])=TRIM(type)),--(TRIM(Tracking[Categories])=TRIM(item)),--(Tracking[Date]>=DATE(selected_year,1,1)),--(Tracking[Date]<DATE(selected_year+1,1,1))),SUMPRODUCT(Tracking[Amount],--(TRIM(Tracking[Type])=TRIM(type)),--(TRIM(Tracking[Categories])=TRIM(item)),--(Tracking[Date]>=DATE(selected_year,1,1)),--(Tracking[Date]<DATE(selected_year+1,1,1)),--(MONTH(Tracking[Date])=selected_period)))))} | L19: {=IF(OR(is_header,is_empty),"",INDEX('Budget Planning'!$E:$FA,row_id,MATCH(IF(selected_period="Total Year",selected_year,DATE(selected_year,selected_period,1)),'Budget Planning'!$E$9:$FA$9,0)))} | M19: {=IF(is_cat,IF(header_row_id=Income_header_row, MATCH(income_min_row,$C:$C,0),IF(header_row_id=expenses_header_row, MATCH(expenses_min_row,$C:$C,0),IF(header_row_id=savings_header_row, MATCH(savings_min_row,$C:$C,0),""))),"")} | N19: {=IF(is_cat,IF(header_row_id=Income_header_row, MATCH(income_max_row,$C:$C,0),IF(header_row_id=expenses_header_row, MATCH(expenses_max_row,$C:$C,0),IF(header_row_id=savings_header_row, MATCH(savings_max_row,$C:$C,0),""))),"")} | O19: =IF(is_cat,ADDRESS(sort_min_row,COLUMN(tracked))&":"&ADDRESS(sort_max_row,COLUMN(tracked)),"") | P19: =IF(is_cat,RANK(tracked,INDIRECT(tracked_range),0),"") | Q19: =IF(is_cat,ADDRESS(sort_min_row,COLUMN(budget))&":"&ADDRESS(sort_max_row,COLUMN(budget)),"") | R19: =IF(is_cat,RANK(budget,INDIRECT(budget_range),0),"") | S19: =IF(is_cat,_xlfn.NUMBERVALUE(tracked_rank & budget_rank),"") | T19: =IF(is_cat,ADDRESS(sort_min_row,COLUMN(comb_rank))&":"&ADDRESS(sort_max_row,COLUMN(comb_rank)),"") | U19: =IF(is_cat, RANK(comb_rank, INDIRECT(comb_rank_range),1),"") | V19: =IF(is_cat,ADDRESS(sort_min_row,COLUMN(comb_rank_norm))&":"&ADDRESS(ROW(),COLUMN(comb_rank_norm)),"") | W19: =IF(is_cat,comb_rank_norm+COUNTIF(INDIRECT(comb_rank_norm_run_range),comb_rank_norm)-1,"") | X19: =IF(is_cat,header_row_id+comb_rank_unique,row_id) -> /1 | Y19: =IF(is_empty,"",INDEX($J:$J,MATCH(row_id,$X:$X,0))) | Z19: =IF(is_empty,"",IF(is_header,"Tracked",INDEX($K:$K,MATCH(row_id,$X:$X,0)))) | AA19: =IF(is_empty,"",IF(is_header,"Budget",INDEX($L:$L,MATCH(row_id,$X:$X,0)))) | AB19: =IF(is_empty,"",IF(is_header,"% Compl.",IFERROR(out_tracked/out_budget,"-"))) | AC19: =IF(is_empty,"",IF(is_header,"Remaining",IF(out_budget-out_tracked>0,out_budget-out_tracked,0))) | AD19: =IF(is_empty,"",IF(is_header,"Excess",IF(out_budget-out_tracked<0,out_tracked-out_budget,0))) | AI19: =Calculations!E37 -> Freelance (Net) | AJ19: =Calculations!F37 -> 50897
C20: {=IF(C19=-1,-1, IF(C19<income_max_row,C19+1,IF(C19=income_max_row,income_total_row,IF(C19=income_total_row,"/1", IF(C19="/1",expenses_header_row,IF(C19<expenses_max_row,C19+1,IF(C19=expenses_max_row,expenses_total_row,IF(C19=expenses_total_row,"/2",IF(C19="/2",savings_header_row,IF(C19<savings_max_row,C19+1,IF(C19=savings_max_row,savings_total_row,-1)))))))))))} -> 26 | D20: =IF(is_header,row_id,IF(NOT(is_empty),D19,-1)) -> 26 | E20: {=1*OR(row_id=Income_header_row, row_id=expenses_header_row, row_id=savings_header_row)} -> 1 | F20: =1*NOT(OR(is_header, is_total, is_empty)) -> 0 | G20: {=1*OR(row_id=income_total_row, row_id=expenses_total_row, row_id=savings_total_row)} -> 0 | H20: =1*OR(row_id="/1", row_id="/2", row_id=-1) -> 0 | I20: {=IFERROR(INDEX('Budget Planning'!$C:$C,header_row_id),"")} -> Expenses | J20: {=IFERROR(INDEX('Budget Planning'!$C:$C,row_id),"")} -> Expenses | K20: {=IF(OR(is_header,is_empty),"",IF(is_total,IF(selected_period="Total Year",SUMPRODUCT(Tracking[Amount],--(TRIM(Tracking[Type])=TRIM(type)),--(Tracking[Date]>=DATE(selected_year,1,1)),--(Tracking[Date]<DATE(selected_year+1,1,1))),SUMPRODUCT(Tracking[Amount],--(TRIM(Tracking[Type])=TRIM(type)),--(Tracking[Date]>=DATE(selected_year,1,1)),--(Tracking[Date]<DATE(selected_year+1,1,1)),--(MONTH(Tracking[Date])=selected_period))),IF(selected_period="Total Year",SUMPRODUCT(Tracking[Amount],--(TRIM(Tracking[Type])=TRIM(type)),--(TRIM(Tracking[Categories])=TRIM(item)),--(Tracking[Date]>=DATE(selected_year,1,1)),--(Tracking[Date]<DATE(selected_year+1,1,1))),SUMPRODUCT(Tracking[Amount],--(TRIM(Tracking[Type])=TRIM(type)),--(TRIM(Tracking[Categories])=TRIM(item)),--(Tracking[Date]>=DATE(selected_year,1,1)),--(Tracking[Date]<DATE(selected_year+1,1,1)),--(MONTH(Tracking[Date])=selected_period)))))} | L20: {=IF(OR(is_header,is_empty),"",INDEX('Budget Planning'!$E:$FA,row_id,MATCH(IF(selected_period="Total Year",selected_year,DATE(selected_year,selected_period,1)),'Budget Planning'!$E$9:$FA$9,0)))} | M20: {=IF(is_cat,IF(header_row_id=Income_header_row, MATCH(income_min_row,$C:$C,0),IF(header_row_id=expenses_header_row, MATCH(expenses_min_row,$C:$C,0),IF(header_row_id=savings_header_row, MATCH(savings_min_row,$C:$C,0),""))),"")} | N20: {=IF(is_cat,IF(header_row_id=Income_header_row, MATCH(income_max_row,$C:$C,0),IF(header_row_id=expenses_header_row, MATCH(expenses_max_row,$C:$C,0),IF(header_row_id=savings_header_row, MATCH(savings_max_row,$C:$C,0),""))),"")} | O20: =IF(is_cat,ADDRESS(sort_min_row,COLUMN(tracked))&":"&ADDRESS(sort_max_row,COLUMN(tracked)),"") | P20: =IF(is_cat,RANK(tracked,INDIRECT(tracked_range),0),"") | Q20: =IF(is_cat,ADDRESS(sort_min_row,COLUMN(budget))&":"&ADDRESS(sort_max_row,COLUMN(budget)),"") | R20: =IF(is_cat,RANK(budget,INDIRECT(budget_range),0),"") | S20: =IF(is_cat,_xlfn.NUMBERVALUE(tracked_rank & budget_rank),"") | T20: =IF(is_cat,ADDRESS(sort_min_row,COLUMN(comb_rank))&":"&ADDRESS(sort_max_row,COLUMN(comb_rank)),"") | U20: =IF(is_cat, RANK(comb_rank, INDIRECT(comb_rank_range),1),"") | V20: =IF(is_cat,ADDRESS(sort_min_row,COLUMN(comb_rank_norm))&":"&ADDRESS(ROW(),COLUMN(comb_rank_norm)),"") | W20: =IF(is_cat,comb_rank_norm+COUNTIF(INDIRECT(comb_rank_norm_run_range),comb_rank_norm)-1,"") | X20: =IF(is_cat,header_row_id+comb_rank_unique,row_id) -> 26 | Y20: =IF(is_empty,"",INDEX($J:$J,MATCH(row_id,$X:$X,0))) -> Expenses | Z20: =IF(is_empty,"",IF(is_header,"Tracked",INDEX($K:$K,MATCH(row_id,$X:$X,0)))) -> Tracked | AA20: =IF(is_empty,"",IF(is_header,"Budget",INDEX($L:$L,MATCH(row_id,$X:$X,0)))) -> Budget | AB20: =IF(is_empty,"",IF(is_header,"% Compl.",IFERROR(out_tracked/out_budget,"-"))) -> % Compl. | AC20: =IF(is_empty,"",IF(is_header,"Remaining",IF(out_budget-out_tracked>0,out_budget-out_tracked,0))) -> Remaining | AD20: =IF(is_empty,"",IF(is_header,"Excess",IF(out_budget-out_tracked<0,out_tracked-out_budget,0))) -> Excess | AI20: =Calculations!E38 -> Dividends (Net) | AJ20: =Calculations!F38 -> 19950
C21: {=IF(C20=-1,-1, IF(C20<income_max_row,C20+1,IF(C20=income_max_row,income_total_row,IF(C20=income_total_row,"/1", IF(C20="/1",expenses_header_row,IF(C20<expenses_max_row,C20+1,IF(C20=expenses_max_row,expenses_total_row,IF(C20=expenses_total_row,"/2",IF(C20="/2",savings_header_row,IF(C20<savings_max_row,C20+1,IF(C20=savings_max_row,savings_total_row,-1)))))))))))} -> 27 | D21: =IF(is_header,row_id,IF(NOT(is_empty),D20,-1)) -> 26 | E21: {=1*OR(row_id=Income_header_row, row_id=expenses_header_row, row_id=savings_header_row)} -> 0 | F21: =1*NOT(OR(is_header, is_total, is_empty)) -> 1 | G21: {=1*OR(row_id=income_total_row, row_id=expenses_total_row, row_id=savings_total_row)} -> 0 | H21: =1*OR(row_id="/1", row_id="/2", row_id=-1) -> 0 | I21: {=IFERROR(INDEX('Budget Planning'!$C:$C,header_row_id),"")} -> Expenses | J21: {=IFERROR(INDEX('Budget Planning'!$C:$C,row_id),"")} -> Rent | K21: {=IF(OR(is_header,is_empty),"",IF(is_total,IF(selected_period="Total Year",SUMPRODUCT(Tracking[Amount],--(TRIM(Tracking[Type])=TRIM(type)),--(Tracking[Date]>=DATE(selected_year,1,1)),--(Tracking[Date]<DATE(selected_year+1,1,1))),SUMPRODUCT(Tracking[Amount],--(TRIM(Tracking[Type])=TRIM(type)),--(Tracking[Date]>=DATE(selected_year,1,1)),--(Tracking[Date]<DATE(selected_year+1,1,1)),--(MONTH(Tracking[Date])=selected_period))),IF(selected_period="Total Year",SUMPRODUCT(Tracking[Amount],--(TRIM(Tracking[Type])=TRIM(type)),--(TRIM(Tracking[Categories])=TRIM(item)),--(Tracking[Date]>=DATE(selected_year,1,1)),--(Tracking[Date]<DATE(selected_year+1,1,1))),SUMPRODUCT(Tracking[Amount],--(TRIM(Tracking[Type])=TRIM(type)),--(TRIM(Tracking[Categories])=TRIM(item)),--(Tracking[Date]>=DATE(selected_year,1,1)),--(Tracking[Date]<DATE(selected_year+1,1,1)),--(MONTH(Tracking[Date])=selected_period)))))} -> 25000 | L21: {=IF(OR(is_header,is_empty),"",INDEX('Budget Planning'!$E:$FA,row_id,MATCH(IF(selected_period="Total Year",selected_year,DATE(selected_year,selected_period,1)),'Budget Planning'!$E$9:$FA$9,0)))} -> 223500 | M21: {=IF(is_cat,IF(header_row_id=Income_header_row, MATCH(income_min_row,$C:$C,0),IF(header_row_id=expenses_header_row, MATCH(expenses_min_row,$C:$C,0),IF(header_row_id=savings_header_row, MATCH(savings_min_row,$C:$C,0),""))),"")} -> 21 | N21: {=IF(is_cat,IF(header_row_id=Income_header_row, MATCH(income_max_row,$C:$C,0),IF(header_row_id=expenses_header_row, MATCH(expenses_max_row,$C:$C,0),IF(header_row_id=savings_header_row, MATCH(savings_max_row,$C:$C,0),""))),"")} -> 29 | O21: =IF(is_cat,ADDRESS(sort_min_row,COLUMN(tracked))&":"&ADDRESS(sort_max_row,COLUMN(tracked)),"") -> $K$21:$K$29 | P21: =IF(is_cat,RANK(tracked,INDIRECT(tracked_range),0),"") -> 2 | Q21: =IF(is_cat,ADDRESS(sort_min_row,COLUMN(budget))&":"&ADDRESS(sort_max_row,COLUMN(budget)),"") -> $L$21:$L$29 | R21: =IF(is_cat,RANK(budget,INDIRECT(budget_range),0),"") -> 1 | S21: =IF(is_cat,_xlfn.NUMBERVALUE(tracked_rank & budget_rank),"") -> 21 | T21: =IF(is_cat,ADDRESS(sort_min_row,COLUMN(comb_rank))&":"&ADDRESS(sort_max_row,COLUMN(comb_rank)),"") -> $S$21:$S$29 | U21: =IF(is_cat, RANK(comb_rank, INDIRECT(comb_rank_range),1),"") -> 2 | V21: =IF(is_cat,ADDRESS(sort_min_row,COLUMN(comb_rank_norm))&":"&ADDRESS(ROW(),COLUMN(comb_rank_norm)),"") -> $U$21:$U$21 | W21: =IF(is_cat,comb_rank_norm+COUNTIF(INDIRECT(comb_rank_norm_run_range),comb_rank_norm)-1,"") -> 2 | X21: =IF(is_cat,header_row_id+comb_rank_unique,row_id) -> 28 | Y21: =IF(is_empty,"",INDEX($J:$J,MATCH(row_id,$X:$X,0))) -> Groceries | Z21: =IF(is_empty,"",IF(is_header,"Tracked",INDEX($K:$K,MATCH(row_id,$X:$X,0)))) -> 45830 | AA21: =IF(is_empty,"",IF(is_header,"Budget",INDEX($L:$L,MATCH(row_id,$X:$X,0)))) -> 186816 | AB21: =IF(is_empty,"",IF(is_header,"% Compl.",IFERROR(out_tracked/out_budget,"-"))) -> 0.2453216 | AC21: =IF(is_empty,"",IF(is_header,"Remaining",IF(out_budget-out_tracked>0,out_budget-out_tracked,0))) -> 140986 | AD21: =IF(is_empty,"",IF(is_header,"Excess",IF(out_budget-out_tracked<0,out_tracked-out_budget,0))) -> 0 | AI21: =Calculations!E39 | AJ21: =Calculations!F39
C22: {=IF(C21=-1,-1, IF(C21<income_max_row,C21+1,IF(C21=income_max_row,income_total_row,IF(C21=income_total_row,"/1", IF(C21="/1",expenses_header_row,IF(C21<expenses_max_row,C21+1,IF(C21=expenses_max_row,expenses_total_row,IF(C21=expenses_total_row,"/2",IF(C21="/2",savings_header_row,IF(C21<savings_max_row,C21+1,IF(C21=savings_max_row,savings_total_row,-1)))))))))))} -> 28 | D22: =IF(is_header,row_id,IF(NOT(is_empty),D21,-1)) -> 26 | E22: {=1*OR(row_id=Income_header_row, row_id=expenses_header_row, row_id=savings_header_row)} -> 0 | F22: =1*NOT(OR(is_header, is_total, is_empty)) -> 1 | G22: {=1*OR(row_id=income_total_row, row_id=expenses_total_row, row_id=savings_total_row)} -> 0 | H22: =1*OR(row_id="/1", row_id="/2", row_id=-1) -> 0 | I22: {=IFERROR(INDEX('Budget Planning'!$C:$C,header_row_id),"")} -> Expenses | J22: {=IFERROR(INDEX('Budget Planning'!$C:$C,row_id),"")} -> Fuel | K22: {=IF(OR(is_header,is_empty),"",IF(is_total,IF(selected_period="Total Year",SUMPRODUCT(Tracking[Amount],--(TRIM(Tracking[Type])=TRIM(type)),--(Tracking[Date]>=DATE(selected_year,1,1)),--(Tracking[Date]<DATE(selected_year+1,1,1))),SUMPRODUCT(Tracking[Amount],--(TRIM(Tracking[Type])=TRIM(type)),--(Tracking[Date]>=DATE(selected_year,1,1)),--(Tracking[Date]<DATE(selected_year+1,1,1)),--(MONTH(Tracking[Date])=selected_period))),IF(selected_period="Total Year",SUMPRODUCT(Tracking[Amount],--(TRIM(Tracking[Type])=TRIM(type)),--(TRIM(Tracking[Categories])=TRIM(item)),--(Tracking[Date]>=DATE(selected_year,1,1)),--(Tracking[Date]<DATE(selected_year+1,1,1))),SUMPRODUCT(Tracking[Amount],--(TRIM(Tracking[Type])=TRIM(type)),--(TRIM(Tracking[Categories])=TRIM(item)),--(Tracking[Date]>=DATE(selected_year,1,1)),--(Tracking[Date]<DATE(selected_year+1,1,1)),--(MONTH(Tracking[Date])=selected_period)))))} -> 7500 | L22: {=IF(OR(is_header,is_empty),"",INDEX('Budget Planning'!$E:$FA,row_id,MATCH(IF(selected_period="Total Year",selected_year,DATE(selected_year,selected_period,1)),'Budget Planning'!$E$9:$FA$9,0)))} -> 36000 | M22: {=IF(is_cat,IF(header_row_id=Income_header_row, MATCH(income_min_row,$C:$C,0),IF(header_row_id=expenses_header_row, MATCH(expenses_min_row,$C:$C,0),IF(header_row_id=savings_header_row, MATCH(savings_min_row,$C:$C,0),""))),"")} -> 21 | N22: {=IF(is_cat,IF(header_row_id=Income_header_row, MATCH(income_max_row,$C:$C,0),IF(header_row_id=expenses_header_row, MATCH(expenses_max_row,$C:$C,0),IF(header_row_id=savings_header_row, MATCH(savings_max_row,$C:$C,0),""))),"")} -> 29 | O22: =IF(is_cat,ADDRESS(sort_min_row,COLUMN(tracked))&":"&ADDRESS(sort_max_row,COLUMN(tracked)),"") -> $K$21:$K$29 | P22: =IF(is_cat,RANK(tracked,INDIRECT(tracked_range),0),"") -> 3 | Q22: =IF(is_cat,ADDRESS(sort_min_row,COLUMN(budget))&":"&ADDRESS(sort_max_row,COLUMN(budget)),"") -> $L$21:$L$29 | R22: =IF(is_cat,RANK(budget,INDIRECT(budget_range),0),"") -> 3 | S22: =IF(is_cat,_xlfn.NUMBERVALUE(tracked_rank & budget_rank),"") -> 33 | T22: =IF(is_cat,ADDRESS(sort_min_row,COLUMN(comb_rank))&":"&ADDRESS(sort_max_row,COLUMN(comb_rank)),"") -> $S$21:$S$29 | U22: =IF(is_cat, RANK(comb_rank, INDIRECT(comb_rank_range),1),"") -> 3 | V22: =IF(is_cat,ADDRESS(sort_min_row,COLUMN(comb_rank_norm))&":"&ADDRESS(ROW(),COLUMN(comb_rank_norm)),"") -> $U$21:$U$22 | W22: =IF(is_cat,comb_rank_norm+COUNTIF(INDIRECT(comb_rank_norm_run_range),comb_rank_norm)-1,"") -> 3 | X22: =IF(is_cat,header_row_id+comb_rank_unique,row_id) -> 29 | Y22: =IF(is_empty,"",INDEX($J:$J,MATCH(row_id,$X:$X,0))) -> Rent | Z22: =IF(is_empty,"",IF(is_header,"Tracked",INDEX($K:$K,MATCH(row_id,$X:$X,0)))) -> 25000 | AA22: =IF(is_empty,"",IF(is_header,"Budget",INDEX($L:$L,MATCH(row_id,$X:$X,0)))) -> 223500 | AB22: =IF(is_empty,"",IF(is_header,"% Compl.",IFERROR(out_tracked/out_budget,"-"))) -> 0.11185682 | AC22: =IF(is_empty,"",IF(is_header,"Remaining",IF(out_budget-out_tracked>0,out_budget-out_tracked,0))) -> 198500 | AD22: =IF(is_empty,"",IF(is_header,"Excess",IF(out_budget-out_tracked<0,out_tracked-out_budget,0))) -> 0 | AI22: =Calculations!E40 | AJ22: =Calculations!F40
C23: {=IF(C22=-1,-1, IF(C22<income_max_row,C22+1,IF(C22=income_max_row,income_total_row,IF(C22=income_total_row,"/1", IF(C22="/1",expenses_header_row,IF(C22<expenses_max_row,C22+1,IF(C22=expenses_max_row,expenses_total_row,IF(C22=expenses_total_row,"/2",IF(C22="/2",savings_header_row,IF(C22<savings_max_row,C22+1,IF(C22=savings_max_row,savings_total_row,-1)))))))))))} -> 29 | D23: =IF(is_header,row_id,IF(NOT(is_empty),D22,-1)) -> 26 | E23: {=1*OR(row_id=Income_header_row, row_id=expenses_header_row, row_id=savings_header_row)} -> 0 | F23: =1*NOT(OR(is_header, is_total, is_empty)) -> 1 | G23: {=1*OR(row_id=income_total_row, row_id=expenses_total_row, row_id=savings_total_row)} -> 0 | H23: =1*OR(row_id="/1", row_id="/2", row_id=-1) -> 0 | I23: {=IFERROR(INDEX('Budget Planning'!$C:$C,header_row_id),"")} -> Expenses | J23: {=IFERROR(INDEX('Budget Planning'!$C:$C,row_id),"")} -> Groceries | K23: {=IF(OR(is_header,is_empty),"",IF(is_total,IF(selected_period="Total Year",SUMPRODUCT(Tracking[Amount],--(TRIM(Tracking[Type])=TRIM(type)),--(Tracking[Date]>=DATE(selected_year,1,1)),--(Tracking[Date]<DATE(selected_year+1,1,1))),SUMPRODUCT(Tracking[Amount],--(TRIM(Tracking[Type])=TRIM(type)),--(Tracking[Date]>=DATE(selected_year,1,1)),--(Tracking[Date]<DATE(selected_year+1,1,1)),--(MONTH(Tracking[Date])=selected_period))),IF(selected_period="Total Year",SUMPRODUCT(Tracking[Amount],--(TRIM(Tracking[Type])=TRIM(type)),--(TRIM(Tracking[Categories])=TRIM(item)),--(Tracking[Date]>=DATE(selected_year,1,1)),--(Tracking[Date]<DATE(selected_year+1,1,1))),SUMPRODUCT(Tracking[Amount],--(TRIM(Tracking[Type])=TRIM(type)),--(TRIM(Tracking[Categories])=TRIM(item)),--(Tracking[Date]>=DATE(selected_year,1,1)),--(Tracking[Date]<DATE(selected_year+1,1,1)),--(MONTH(Tracking[Date])=selected_period)))))} -> 45830 | L23: {=IF(OR(is_header,is_empty),"",INDEX('Budget Planning'!$E:$FA,row_id,MATCH(IF(selected_period="Total Year",selected_year,DATE(selected_year,selected_period,1)),'Budget Planning'!$E$9:$FA$9,0)))} -> 186816 | M23: {=IF(is_cat,IF(header_row_id=Income_header_row, MATCH(income_min_row,$C:$C,0),IF(header_row_id=expenses_header_row, MATCH(expenses_min_row,$C:$C,0),IF(header_row_id=savings_header_row, MATCH(savings_min_row,$C:$C,0),""))),"")} -> 21 | N23: {=IF(is_cat,IF(header_row_id=Income_header_row, MATCH(income_max_row,$C:$C,0),IF(header_row_id=expenses_header_row, MATCH(expenses_max_row,$C:$C,0),IF(header_row_id=savings_header_row, MATCH(savings_max_row,$C:$C,0),""))),"")} -> 29 | O23: =IF(is_cat,ADDRESS(sort_min_row,COLUMN(tracked))&":"&ADDRESS(sort_max_row,COLUMN(tracked)),"") -> $K$21:$K$29 | P23: =IF(is_cat,RANK(tracked,INDIRECT(tracked_range),0),"") -> 1 | Q23: =IF(is_cat,ADDRESS(sort_min_row,COLUMN(budget))&":"&ADDRESS(sort_max_row,COLUMN(budget)),"") -> $L$21:$L$29 | R23: =IF(is_cat,RANK(budget,INDIRECT(budget_range),0),"") -> 2 | S23: =IF(is_cat,_xlfn.NUMBERVALUE(tracked_rank & budget_rank),"") -> 12 | T23: =IF(is_cat,ADDRESS(sort_min_row,COLUMN(comb_rank))&":"&ADDRESS(sort_max_row,COLUMN(comb_rank)),"") -> $S$21:$S$29 | U23: =IF(is_cat, RANK(comb_rank, INDIRECT(comb_rank_range),1),"") -> 1 | V23: =IF(is_cat,ADDRESS(sort_min_row,COLUMN(comb_rank_norm))&":"&ADDRESS(ROW(),COLUMN(comb_rank_norm)),"") -> $U$21:$U$23 | W23: =IF(is_cat,comb_rank_norm+COUNTIF(INDIRECT(comb_rank_norm_run_range),comb_rank_norm)-1,"") -> 1 | X23: =IF(is_cat,header_row_id+comb_rank_unique,row_id) -> 27 | Y23: =IF(is_empty,"",INDEX($J:$J,MATCH(row_id,$X:$X,0))) -> Fuel | Z23: =IF(is_empty,"",IF(is_header,"Tracked",INDEX($K:$K,MATCH(row_id,$X:$X,0)))) -> 7500 | AA23: =IF(is_empty,"",IF(is_header,"Budget",INDEX($L:$L,MATCH(row_id,$X:$X,0)))) -> 36000 | AB23: =IF(is_empty,"",IF(is_header,"% Compl.",IFERROR(out_tracked/out_budget,"-"))) -> 0.20833333 | AC23: =IF(is_empty,"",IF(is_header,"Remaining",IF(out_budget-out_tracked>0,out_budget-out_tracked,0))) -> 28500 | AD23: =IF(is_empty,"",IF(is_header,"Excess",IF(out_budget-out_tracked<0,out_tracked-out_budget,0))) -> 0 | AI23: =Calculations!E41 -> Total | AJ23: =Calculations!F41 -> 317964
C24: {=IF(C23=-1,-1, IF(C23<income_max_row,C23+1,IF(C23=income_max_row,income_total_row,IF(C23=income_total_row,"/1", IF(C23="/1",expenses_header_row,IF(C23<expenses_max_row,C23+1,IF(C23=expenses_max_row,expenses_total_row,IF(C23=expenses_total_row,"/2",IF(C23="/2",savings_header_row,IF(C23<savings_max_row,C23+1,IF(C23=savings_max_row,savings_total_row,-1)))))))))))} -> 30 | D24: =IF(is_header,row_id,IF(NOT(is_empty),D23,-1)) -> 26 | E24: {=1*OR(row_id=Income_header_row, row_id=expenses_header_row, row_id=savings_header_row)} -> 0 | F24: =1*NOT(OR(is_header, is_total, is_empty)) -> 1 | G24: {=1*OR(row_id=income_total_row, row_id=expenses_total_row, row_id=savings_total_row)} -> 0 | H24: =1*OR(row_id="/1", row_id="/2", row_id=-1) -> 0 | I24: {=IFERROR(INDEX('Budget Planning'!$C:$C,header_row_id),"")} -> Expenses | J24: {=IFERROR(INDEX('Budget Planning'!$C:$C,row_id),"")} -> MISC | K24: {=IF(OR(is_header,is_empty),"",IF(is_total,IF(selected_period="Total Year",SUMPRODUCT(Tracking[Amount],--(TRIM(Tracking[Type])=TRIM(type)),--(Tracking[Date]>=DATE(selected_year,1,1)),--(Tracking[Date]<DATE(selected_year+1,1,1))),SUMPRODUCT(Tracking[Amount],--(TRIM(Tracking[Type])=TRIM(type)),--(Tracking[Date]>=DATE(selected_year,1,1)),--(Tracking[Date]<DATE(selected_year+1,1,1)),--(MONTH(Tracking[Date])=selected_period))),IF(selected_period="Total Year",SUMPRODUCT(Tracking[Amount],--(TRIM(Tracking[Type])=TRIM(type)),--(TRIM(Tracking[Categories])=TRIM(item)),--(Tracking[Date]>=DATE(selected_year,1,1)),--(Tracking[Date]<DATE(selected_year+1,1,1))),SUMPRODUCT(Tracking[Amount],--(TRIM(Tracking[Type])=TRIM(type)),--(TRIM(Tracking[Categories])=TRIM(item)),--(Tracking[Date]>=DATE(selected_year,1,1)),--(Tracking[Date]<DATE(selected_year+1,1,1)),--(MONTH(Tracking[Date])=selected_period)))))} -> 3222 | L24: {=IF(OR(is_header,is_empty),"",INDEX('Budget Planning'!$E:$FA,row_id,MATCH(IF(selected_period="Total Year",selected_year,DATE(selected_year,selected_period,1)),'Budget Planning'!$E$9:$FA$9,0)))} -> 12000 | M24: {=IF(is_cat,IF(header_row_id=Income_header_row, MATCH(income_min_row,$C:$C,0),IF(header_row_id=expenses_header_row, MATCH(expenses_min_row,$C:$C,0),IF(header_row_id=savings_header_row, MATCH(savings_min_row,$C:$C,0),""))),"")} -> 21 | N24: {=IF(is_cat,IF(header_row_id=Income_header_row, MATCH(income_max_row,$C:$C,0),IF(header_row_id=expenses_header_row, MATCH(expenses_max_row,$C:$C,0),IF(header_row_id=savings_header_row, MATCH(savings_max_row,$C:$C,0),""))),"")} -> 29 | O24: =IF(is_cat,ADDRESS(sort_min_row,COLUMN(tracked))&":"&ADDRESS(sort_max_row,COLUMN(tracked)),"") -> $K$21:$K$29 | P24: =IF(is_cat,RANK(tracked,INDIRECT(tracked_range),0),"") -> 5 | Q24: =IF(is_cat,ADDRESS(sort_min_row,COLUMN(budget))&":"&ADDRESS(sort_max_row,COLUMN(budget)),"") -> $L$21:$L$29 | R24: =IF(is_cat,RANK(budget,INDIRECT(budget_range),0),"") -> 7 | S24: =IF(is_cat,_xlfn.NUMBERVALUE(tracked_rank & budget_rank),"") -> 57 | T24: =IF(is_cat,ADDRESS(sort_min_row,COLUMN(comb_rank))&":"&ADDRESS(sort_max_row,COLUMN(comb_rank)),"") -> $S$21:$S$29 | U24: =IF(is_cat, RANK(comb_rank, INDIRECT(comb_rank_range),1),"") -> 5 | V24: =IF(is_cat,ADDRESS(sort_min_row,COLUMN(comb_rank_norm))&":"&ADDRESS(ROW(),COLUMN(comb_rank_norm)),"") -> $U$21:$U$24 | W24: =IF(is_cat,comb_rank_norm+COUNTIF(INDIRECT(comb_rank_norm_run_range),comb_rank_norm)-1,"") -> 5 | X24: =IF(is_cat,header_row_id+comb_rank_unique,row_id) -> 31 | Y24: =IF(is_empty,"",INDEX($J:$J,MATCH(row_id,$X:$X,0))) -> Fun & Vacation | Z24: =IF(is_empty,"",IF(is_header,"Tracked",INDEX($K:$K,MATCH(row_id,$X:$X,0)))) -> 6430 | AA24: =IF(is_empty,"",IF(is_header,"Budget",INDEX($L:$L,MATCH(row_id,$X:$X,0)))) -> 34300 | AB24: =IF(is_empty,"",IF(is_header,"% Compl.",IFERROR(out_tracked/out_budget,"-"))) -> 0.18746356 | AC24: =IF(is_empty,"",IF(is_header,"Remaining",IF(out_budget-out_tracked>0,out_budget-out_tracked,0))) -> 27870 | AD24: =IF(is_empty,"",IF(is_header,"Excess",IF(out_budget-out_tracked<0,out_tracked-out_budget,0))) -> 0
C25: {=IF(C24=-1,-1, IF(C24<income_max_row,C24+1,IF(C24=income_max_row,income_total_row,IF(C24=income_total_row,"/1", IF(C24="/1",expenses_header_row,IF(C24<expenses_max_row,C24+1,IF(C24=expenses_max_row,expenses_total_row,IF(C24=expenses_total_row,"/2",IF(C24="/2",savings_header_row,IF(C24<savings_max_row,C24+1,IF(C24=savings_max_row,savings_total_row,-1)))))))))))} -> 31 | D25: =IF(is_header,row_id,IF(NOT(is_empty),D24,-1)) -> 26 | E25: {=1*OR(row_id=Income_header_row, row_id=expenses_header_row, row_id=savings_header_row)} -> 0 | F25: =1*NOT(OR(is_header, is_total, is_empty)) -> 1 | G25: {=1*OR(row_id=income_total_row, row_id=expenses_total_row, row_id=savings_total_row)} -> 0 | H25: =1*OR(row_id="/1", row_id="/2", row_id=-1) -> 0 | I25: {=IFERROR(INDEX('Budget Planning'!$C:$C,header_row_id),"")} -> Expenses | J25: {=IFERROR(INDEX('Budget Planning'!$C:$C,row_id),"")} -> Insurances | K25: {=IF(OR(is_header,is_empty),"",IF(is_total,IF(selected_period="Total Year",SUMPRODUCT(Tracking[Amount],--(TRIM(Tracking[Type])=TRIM(type)),--(Tracking[Date]>=DATE(selected_year,1,1)),--(Tracking[Date]<DATE(selected_year+1,1,1))),SUMPRODUCT(Tracking[Amount],--(TRIM(Tracking[Type])=TRIM(type)),--(Tracking[Date]>=DATE(selected_year,1,1)),--(Tracking[Date]<DATE(selected_year+1,1,1)),--(MONTH(Tracking[Date])=selected_period))),IF(selected_period="Total Year",SUMPRODUCT(Tracking[Amount],--(TRIM(Tracking[Type])=TRIM(type)),--(TRIM(Tracking[Categories])=TRIM(item)),--(Tracking[Date]>=DATE(selected_year,1,1)),--(Tracking[Date]<DATE(selected_year+1,1,1))),SUMPRODUCT(Tracking[Amount],--(TRIM(Tracking[Type])=TRIM(type)),--(TRIM(Tracking[Categories])=TRIM(item)),--(Tracking[Date]>=DATE(selected_year,1,1)),--(Tracking[Date]<DATE(selected_year+1,1,1)),--(MONTH(Tracking[Date])=selected_period)))))} -> 2550 | L25: {=IF(OR(is_header,is_empty),"",INDEX('Budget Planning'!$E:$FA,row_id,MATCH(IF(selected_period="Total Year",selected_year,DATE(selected_year,selected_period,1)),'Budget Planning'!$E$9:$FA$9,0)))} -> 12600 | M25: {=IF(is_cat,IF(header_row_id=Income_header_row, MATCH(income_min_row,$C:$C,0),IF(header_row_id=expenses_header_row, MATCH(expenses_min_row,$C:$C,0),IF(header_row_id=savings_header_row, MATCH(savings_min_row,$C:$C,0),""))),"")} -> 21 | N25: {=IF(is_cat,IF(header_row_id=Income_header_row, MATCH(income_max_row,$C:$C,0),IF(header_row_id=expenses_header_row, MATCH(expenses_max_row,$C:$C,0),IF(header_row_id=savings_header_row, MATCH(savings_max_row,$C:$C,0),""))),"")} -> 29 | O25: =IF(is_cat,ADDRESS(sort_min_row,COLUMN(tracked))&":"&ADDRESS(sort_max_row,COLUMN(tracked)),"") -> $K$21:$K$29 | P25: =IF(is_cat,RANK(tracked,INDIRECT(tracked_range),0),"") -> 6 | Q25: =IF(is_cat,ADDRESS(sort_min_row,COLUMN(budget))&":"&ADDRESS(sort_max_row,COLUMN(budget)),"") -> $L$21:$L$29 | R25: =IF(is_cat,RANK(budget,INDIRECT(budget_range),0),"") -> 6 | S25: =IF(is_cat,_xlfn.NUMBERVALUE(tracked_rank & budget_rank),"") -> 66 | T25: =IF(is_cat,ADDRESS(sort_min_row,COLUMN(comb_rank))&":"&ADDRESS(sort_max_row,COLUMN(comb_rank)),"") -> $S$21:$S$29 | U25: =IF(is_cat, RANK(comb_rank, INDIRECT(comb_rank_range),1),"") -> 6 | V25: =IF(is_cat,ADDRESS(sort_min_row,COLUMN(comb_rank_norm))&":"&ADDRESS(ROW(),COLUMN(comb_rank_norm)),"") -> $U$21:$U$25 | W25: =IF(is_cat,comb_rank_norm+COUNTIF(INDIRECT(comb_rank_norm_run_range),comb_rank_norm)-1,"") -> 6 | X25: =IF(is_cat,header_row_id+comb_rank_unique,row_id) -> 32 | Y25: =IF(is_empty,"",INDEX($J:$J,MATCH(row_id,$X:$X,0))) -> MISC | Z25: =IF(is_empty,"",IF(is_header,"Tracked",INDEX($K:$K,MATCH(row_id,$X:$X,0)))) -> 3222 | AA25: =IF(is_empty,"",IF(is_header,"Budget",INDEX($L:$L,MATCH(row_id,$X:$X,0)))) -> 12000 | AB25: =IF(is_empty,"",IF(is_header,"% Compl.",IFERROR(out_tracked/out_budget,"-"))) -> 0.2685 | AC25: =IF(is_empty,"",IF(is_header,"Remaining",IF(out_budget-out_tracked>0,out_budget-out_tracked,0))) -> 8778 | AD25: =IF(is_empty,"",IF(is_header,"Excess",IF(out_budget-out_tracked<0,out_tracked-out_budget,0))) -> 0
C26: {=IF(C25=-1,-1, IF(C25<income_max_row,C25+1,IF(C25=income_max_row,income_total_row,IF(C25=income_total_row,"/1", IF(C25="/1",expenses_header_row,IF(C25<expenses_max_row,C25+1,IF(C25=expenses_max_row,expenses_total_row,IF(C25=expenses_total_row,"/2",IF(C25="/2",savings_header_row,IF(C25<savings_max_row,C25+1,IF(C25=savings_max_row,savings_total_row,-1)))))))))))} -> 32 | D26: =IF(is_header,row_id,IF(NOT(is_empty),D25,-1)) -> 26 | E26: {=1*OR(row_id=Income_header_row, row_id=expenses_header_row, row_id=savings_header_row)} -> 0 | F26: =1*NOT(OR(is_header, is_total, is_empty)) -> 1 | G26: {=1*OR(row_id=income_total_row, row_id=expenses_total_row, row_id=savings_total_row)} -> 0 | H26: =1*OR(row_id="/1", row_id="/2", row_id=-1) -> 0 | I26: {=IFERROR(INDEX('Budget Planning'!$C:$C,header_row_id),"")} -> Expenses | J26: {=IFERROR(INDEX('Budget Planning'!$C:$C,row_id),"")} -> Clothing | K26: {=IF(OR(is_header,is_empty),"",IF(is_total,IF(selected_period="Total Year",SUMPRODUCT(Tracking[Amount],--(TRIM(Tracking[Type])=TRIM(type)),--(Tracking[Date]>=DATE(selected_year,1,1)),--(Tracking[Date]<DATE(selected_year+1,1,1))),SUMPRODUCT(Tracking[Amount],--(TRIM(Tracking[Type])=TRIM(type)),--(Tracking[Date]>=DATE(selected_year,1,1)),--(Tracking[Date]<DATE(selected_year+1,1,1)),--(MONTH(Tracking[Date])=selected_period))),IF(selected_period="Total Year",SUMPRODUCT(Tracking[Amount],--(TRIM(Tracking[Type])=TRIM(type)),--(TRIM(Tracking[Categories])=TRIM(item)),--(Tracking[Date]>=DATE(selected_year,1,1)),--(Tracking[Date]<DATE(selected_year+1,1,1))),SUMPRODUCT(Tracking[Amount],--(TRIM(Tracking[Type])=TRIM(type)),--(TRIM(Tracking[Categories])=TRIM(item)),--(Tracking[Date]>=DATE(selected_year,1,1)),--(Tracking[Date]<DATE(selected_year+1,1,1)),--(MONTH(Tracking[Date])=selected_period)))))} -> 1023 | L26: {=IF(OR(is_header,is_empty),"",INDEX('Budget Planning'!$E:$FA,row_id,MATCH(IF(selected_period="Total Year",selected_year,DATE(selected_year,selected_period,1)),'Budget Planning'!$E$9:$FA$9,0)))} -> 16000 | M26: {=IF(is_cat,IF(header_row_id=Income_header_row, MATCH(income_min_row,$C:$C,0),IF(header_row_id=expenses_header_row, MATCH(expenses_min_row,$C:$C,0),IF(header_row_id=savings_header_row, MATCH(savings_min_row,$C:$C,0),""))),"")} -> 21 | N26: {=IF(is_cat,IF(header_row_id=Income_header_row, MATCH(income_max_row,$C:$C,0),IF(header_row_id=expenses_header_row, MATCH(expenses_max_row,$C:$C,0),IF(header_row_id=savings_header_row, MATCH(savings_max_row,$C:$C,0),""))),"")} -> 29 | O26: =IF(is_cat,ADDRESS(sort_min_row,COLUMN(tracked))&":"&ADDRESS(sort_max_row,COLUMN(tracked)),"") -> $K$21:$K$29 | P26: =IF(is_cat,RANK(tracked,INDIRECT(tracked_range),0),"") -> 7 | Q26: =IF(is_cat,ADDRESS(sort_min_row,COLUMN(budget))&":"&ADDRESS(sort_max_row,COLUMN(budget)),"") -> $L$21:$L$29 | R26: =IF(is_cat,RANK(budget,INDIRECT(budget_range),0),"") -> 5 | S26: =IF(is_cat,_xlfn.NUMBERVALUE(tracked_rank & budget_rank),"") -> 75 | T26: =IF(is_cat,ADDRESS(sort_min_row,COLUMN(comb_rank))&":"&ADDRESS(sort_max_row,COLUMN(comb_rank)),"") -> $S$21:$S$29 | U26: =IF(is_cat, RANK(comb_rank, INDIRECT(comb_rank_range),1),"") -> 7 | V26: =IF(is_cat,ADDRESS(sort_min_row,COLUMN(comb_rank_norm))&":"&ADDRESS(ROW(),COLUMN(comb_rank_norm)),"") -> $U$21:$U$26 | W26: =IF(is_cat,comb_rank_norm+COUNTIF(INDIRECT(comb_rank_norm_run_range),comb_rank_norm)-1,"") -> 7 | X26: =IF(is_cat,header_row_id+comb_rank_unique,row_id) -> 33 | Y26: =IF(is_empty,"",INDEX($J:$J,MATCH(row_id,$X:$X,0))) -> Insurances | Z26: =IF(is_empty,"",IF(is_header,"Tracked",INDEX($K:$K,MATCH(row_id,$X:$X,0)))) -> 2550 | AA26: =IF(is_empty,"",IF(is_header,"Budget",INDEX($L:$L,MATCH(row_id,$X:$X,0)))) -> 12600 | AB26: =IF(is_empty,"",IF(is_header,"% Compl.",IFERROR(out_tracked/out_budget,"-"))) -> 0.20238095 | AC26: =IF(is_empty,"",IF(is_header,"Remaining",IF(out_budget-out_tracked>0,out_budget-out_tracked,0))) -> 10050 | AD26: =IF(is_empty,"",IF(is_header,"Excess",IF(out_budget-out_tracked<0,out_tracked-out_budget,0))) -> 0
C27: {=IF(C26=-1,-1, IF(C26<income_max_row,C26+1,IF(C26=income_max_row,income_total_row,IF(C26=income_total_row,"/1", IF(C26="/1",expenses_header_row,IF(C26<expenses_max_row,C26+1,IF(C26=expenses_max_row,expenses_total_row,IF(C26=expenses_total_row,"/2",IF(C26="/2",savings_header_row,IF(C26<savings_max_row,C26+1,IF(C26=savings_max_row,savings_total_row,-1)))))))))))} -> 33 | D27: =IF(is_header,row_id,IF(NOT(is_empty),D26,-1)) -> 26 | E27: {=1*OR(row_id=Income_header_row, row_id=expenses_header_row, row_id=savings_header_row)} -> 0 | F27: =1*NOT(OR(is_header, is_total, is_empty)) -> 1 | G27: {=1*OR(row_id=income_total_row, row_id=expenses_total_row, row_id=savings_total_row)} -> 0 | H27: =1*OR(row_id="/1", row_id="/2", row_id=-1) -> 0 | I27: {=IFERROR(INDEX('Budget Planning'!$C:$C,header_row_id),"")} -> Expenses | J27: {=IFERROR(INDEX('Budget Planning'!$C:$C,row_id),"")} -> Wellness&Medicine | K27: {=IF(OR(is_header,is_empty),"",IF(is_total,IF(selected_period="Total Year",SUMPRODUCT(Tracking[Amount],--(TRIM(Tracking[Type])=TRIM(type)),--(Tracking[Date]>=DATE(selected_year,1,1)),--(Tracking[Date]<DATE(selected_year+1,1,1))),SUMPRODUCT(Tracking[Amount],--(TRIM(Tracking[Type])=TRIM(type)),--(Tracking[Date]>=DATE(selected_year,1,1)),--(Tracking[Date]<DATE(selected_year+1,1,1)),--(MONTH(Tracking[Date])=selected_period))),IF(selected_period="Total Year",SUMPRODUCT(Tracking[Amount],--(TRIM(Tracking[Type])=TRIM(type)),--(TRIM(Tracking[Categories])=TRIM(item)),--(Tracking[Date]>=DATE(selected_year,1,1)),--(Tracking[Date]<DATE(selected_year+1,1,1))),SUMPRODUCT(Tracking[Amount],--(TRIM(Tracking[Type])=TRIM(type)),--(TRIM(Tracking[Categories])=TRIM(item)),--(Tracking[Date]>=DATE(selected_year,1,1)),--(Tracking[Date]<DATE(selected_year+1,1,1)),--(MONTH(Tracking[Date])=selected_period)))))} -> 0 | L27: {=IF(OR(is_header,is_empty),"",INDEX('Budget Planning'!$E:$FA,row_id,MATCH(IF(selected_period="Total Year",selected_year,DATE(selected_year,selected_period,1)),'Budget Planning'!$E$9:$FA$9,0)))} -> 6000 | M27: {=IF(is_cat,IF(header_row_id=Income_header_row, MATCH(income_min_row,$C:$C,0),IF(header_row_id=expenses_header_row, MATCH(expenses_min_row,$C:$C,0),IF(header_row_id=savings_header_row, MATCH(savings_min_row,$C:$C,0),""))),"")} -> 21 | N27: {=IF(is_cat,IF(header_row_id=Income_header_row, MATCH(income_max_row,$C:$C,0),IF(header_row_id=expenses_header_row, MATCH(expenses_max_row,$C:$C,0),IF(header_row_id=savings_header_row, MATCH(savings_max_row,$C:$C,0),""))),"")} -> 29 | O27: =IF(is_cat,ADDRESS(sort_min_row,COLUMN(tracked))&":"&ADDRESS(sort_max_row,COLUMN(tracked)),"") -> $K$21:$K$29 | P27: =IF(is_cat,RANK(tracked,INDIRECT(tracked_range),0),"") -> 8 | Q27: =IF(is_cat,ADDRESS(sort_min_row,COLUMN(budget))&":"&ADDRESS(sort_max_row,COLUMN(budget)),"") -> $L$21:$L$29 | R27: =IF(is_cat,RANK(budget,INDIRECT(budget_range),0),"") -> 8 | S27: =IF(is_cat,_xlfn.NUMBERVALUE(tracked_rank & budget_rank),"") -> 88 | T27: =IF(is_cat,ADDRESS(sort_min_row,COLUMN(comb_rank))&":"&ADDRESS(sort_max_row,COLUMN(comb_rank)),"") -> $S$21:$S$29 | U27: =IF(is_cat, RANK(comb_rank, INDIRECT(comb_rank_range),1),"") -> 8 | V27: =IF(is_cat,ADDRESS(sort_min_row,COLUMN(comb_rank_norm))&":"&ADDRESS(ROW(),COLUMN(comb_rank_norm)),"") -> $U$21:$U$27 | W27: =IF(is_cat,comb_rank_norm+COUNTIF(INDIRECT(comb_rank_norm_run_range),comb_rank_norm)-1,"") -> 8 | X27: =IF(is_cat,header_row_id+comb_rank_unique,row_id) -> 34 | Y27: =IF(is_empty,"",INDEX($J:$J,MATCH(row_id,$X:$X,0))) -> Clothing | Z27: =IF(is_empty,"",IF(is_header,"Tracked",INDEX($K:$K,MATCH(row_id,$X:$X,0)))) -> 1023 | AA27: =IF(is_empty,"",IF(is_header,"Budget",INDEX($L:$L,MATCH(row_id,$X:$X,0)))) -> 16000 | AB27: =IF(is_empty,"",IF(is_header,"% Compl.",IFERROR(out_tracked/out_budget,"-"))) -> 0.0639375 | AC27: =IF(is_empty,"",IF(is_header,"Remaining",IF(out_budget-out_tracked>0,out_budget-out_tracked,0))) -> 14977 | AD27: =IF(is_empty,"",IF(is_header,"Excess",IF(out_budget-out_tracked<0,out_tracked-out_budget,0))) -> 0
C28: {=IF(C27=-1,-1, IF(C27<income_max_row,C27+1,IF(C27=income_max_row,income_total_row,IF(C27=income_total_row,"/1", IF(C27="/1",expenses_header_row,IF(C27<expenses_max_row,C27+1,IF(C27=expenses_max_row,expenses_total_row,IF(C27=expenses_total_row,"/2",IF(C27="/2",savings_header_row,IF(C27<savings_max_row,C27+1,IF(C27=savings_max_row,savings_total_row,-1)))))))))))} -> 34 | D28: =IF(is_header,row_id,IF(NOT(is_empty),D27,-1)) -> 26 | E28: {=1*OR(row_id=Income_header_row, row_id=expenses_header_row, row_id=savings_header_row)} -> 0 | F28: =1*NOT(OR(is_header, is_total, is_empty)) -> 1 | G28: {=1*OR(row_id=income_total_row, row_id=expenses_total_row, row_id=savings_total_row)} -> 0 | H28: =1*OR(row_id="/1", row_id="/2", row_id=-1) -> 0 | I28: {=IFERROR(INDEX('Budget Planning'!$C:$C,header_row_id),"")} -> Expenses | J28: {=IFERROR(INDEX('Budget Planning'!$C:$C,row_id),"")} -> Media | K28: {=IF(OR(is_header,is_empty),"",IF(is_total,IF(selected_period="Total Year",SUMPRODUCT(Tracking[Amount],--(TRIM(Tracking[Type])=TRIM(type)),--(Tracking[Date]>=DATE(selected_year,1,1)),--(Tracking[Date]<DATE(selected_year+1,1,1))),SUMPRODUCT(Tracking[Amount],--(TRIM(Tracking[Type])=TRIM(type)),--(Tracking[Date]>=DATE(selected_year,1,1)),--(Tracking[Date]<DATE(selected_year+1,1,1)),--(MONTH(Tracking[Date])=selected_period))),IF(selected_period="Total Year",SUMPRODUCT(Tracking[Amount],--(TRIM(Tracking[Type])=TRIM(type)),--(TRIM(Tracking[Categories])=TRIM(item)),--(Tracking[Date]>=DATE(selected_year,1,1)),--(Tracking[Date]<DATE(selected_year+1,1,1))),SUMPRODUCT(Tracking[Amount],--(TRIM(Tracking[Type])=TRIM(type)),--(TRIM(Tracking[Categories])=TRIM(item)),--(Tracking[Date]>=DATE(selected_year,1,1)),--(Tracking[Date]<DATE(selected_year+1,1,1)),--(MONTH(Tracking[Date])=selected_period)))))} -> 0 | L28: {=IF(OR(is_header,is_empty),"",INDEX('Budget Planning'!$E:$FA,row_id,MATCH(IF(selected_period="Total Year",selected_year,DATE(selected_year,selected_period,1)),'Budget Planning'!$E$9:$FA$9,0)))} -> 3600 | M28: {=IF(is_cat,IF(header_row_id=Income_header_row, MATCH(income_min_row,$C:$C,0),IF(header_row_id=expenses_header_row, MATCH(expenses_min_row,$C:$C,0),IF(header_row_id=savings_header_row, MATCH(savings_min_row,$C:$C,0),""))),"")} -> 21 | N28: {=IF(is_cat,IF(header_row_id=Income_header_row, MATCH(income_max_row,$C:$C,0),IF(header_row_id=expenses_header_row, MATCH(expenses_max_row,$C:$C,0),IF(header_row_id=savings_header_row, MATCH(savings_max_row,$C:$C,0),""))),"")} -> 29 | O28: =IF(is_cat,ADDRESS(sort_min_row,COLUMN(tracked))&":"&ADDRESS(sort_max_row,COLUMN(tracked)),"") -> $K$21:$K$29 | P28: =IF(is_cat,RANK(tracked,INDIRECT(tracked_range),0),"") -> 8 | Q28: =IF(is_cat,ADDRESS(sort_min_row,COLUMN(budget))&":"&ADDRESS(sort_max_row,COLUMN(budget)),"") -> $L$21:$L$29 | R28: =IF(is_cat,RANK(budget,INDIRECT(budget_range),0),"") -> 9 | S28: =IF(is_cat,_xlfn.NUMBERVALUE(tracked_rank & budget_rank),"") -> 89 | T28: =IF(is_cat,ADDRESS(sort_min_row,COLUMN(comb_rank))&":"&ADDRESS(sort_max_row,COLUMN(comb_rank)),"") -> $S$21:$S$29 | U28: =IF(is_cat, RANK(comb_rank, INDIRECT(comb_rank_range),1),"") -> 9 | V28: =IF(is_cat,ADDRESS(sort_min_row,COLUMN(comb_rank_norm))&":"&ADDRESS(ROW(),COLUMN(comb_rank_norm)),"") -> $U$21:$U$28 | W28: =IF(is_cat,comb_rank_norm+COUNTIF(INDIRECT(comb_rank_norm_run_range),comb_rank_norm)-1,"") -> 9 | X28: =IF(is_cat,header_row_id+comb_rank_unique,row_id) -> 35 | Y28: =IF(is_empty,"",INDEX($J:$J,MATCH(row_id,$X:$X,0))) -> Wellness&Medicine | Z28: =IF(is_empty,"",IF(is_header,"Tracked",INDEX($K:$K,MATCH(row_id,$X:$X,0)))) -> 0 | AA28: =IF(is_empty,"",IF(is_header,"Budget",INDEX($L:$L,MATCH(row_id,$X:$X,0)))) -> 6000 | AB28: =IF(is_empty,"",IF(is_header,"% Compl.",IFERROR(out_tracked/out_budget,"-"))) -> 0 | AC28: =IF(is_empty,"",IF(is_header,"Remaining",IF(out_budget-out_tracked>0,out_budget-out_tracked,0))) -> 6000 | AD28: =IF(is_empty,"",IF(is_header,"Excess",IF(out_budget-out_tracked<0,out_tracked-out_budget,0))) -> 0
C29: {=IF(C28=-1,-1, IF(C28<income_max_row,C28+1,IF(C28=income_max_row,income_total_row,IF(C28=income_total_row,"/1", IF(C28="/1",expenses_header_row,IF(C28<expenses_max_row,C28+1,IF(C28=expenses_max_row,expenses_total_row,IF(C28=expenses_total_row,"/2",IF(C28="/2",savings_header_row,IF(C28<savings_max_row,C28+1,IF(C28=savings_max_row,savings_total_row,-1)))))))))))} -> 35 | D29: =IF(is_header,row_id,IF(NOT(is_empty),D28,-1)) -> 26 | E29: {=1*OR(row_id=Income_header_row, row_id=expenses_header_row, row_id=savings_header_row)} -> 0 | F29: =1*NOT(OR(is_header, is_total, is_empty)) -> 1 | G29: {=1*OR(row_id=income_total_row, row_id=expenses_total_row, row_id=savings_total_row)} -> 0 | H29: =1*OR(row_id="/1", row_id="/2", row_id=-1) -> 0 | I29: {=IFERROR(INDEX('Budget Planning'!$C:$C,header_row_id),"")} -> Expenses | J29: {=IFERROR(INDEX('Budget Planning'!$C:$C,row_id),"")} -> Fun & Vacation | K29: {=IF(OR(is_header,is_empty),"",IF(is_total,IF(selected_period="Total Year",SUMPRODUCT(Tracking[Amount],--(TRIM(Tracking[Type])=TRIM(type)),--(Tracking[Date]>=DATE(selected_year,1,1)),--(Tracking[Date]<DATE(selected_year+1,1,1))),SUMPRODUCT(Tracking[Amount],--(TRIM(Tracking[Type])=TRIM(type)),--(Tracking[Date]>=DATE(selected_year,1,1)),--(Tracking[Date]<DATE(selected_year+1,1,1)),--(MONTH(Tracking[Date])=selected_period))),IF(selected_period="Total Year",SUMPRODUCT(Tracking[Amount],--(TRIM(Tracking[Type])=TRIM(type)),--(TRIM(Tracking[Categories])=TRIM(item)),--(Tracking[Date]>=DATE(selected_year,1,1)),--(Tracking[Date]<DATE(selected_year+1,1,1))),SUMPRODUCT(Tracking[Amount],--(TRIM(Tracking[Type])=TRIM(type)),--(TRIM(Tracking[Categories])=TRIM(item)),--(Tracking[Date]>=DATE(selected_year,1,1)),--(Tracking[Date]<DATE(selected_year+1,1,1)),--(MONTH(Tracking[Date])=selected_period)))))} -> 6430 | L29: {=IF(OR(is_header,is_empty),"",INDEX('Budget Planning'!$E:$FA,row_id,MATCH(IF(selected_period="Total Year",selected_year,DATE(selected_year,selected_period,1)),'Budget Planning'!$E$9:$FA$9,0)))} -> 34300 | M29: {=IF(is_cat,IF(header_row_id=Income_header_row, MATCH(income_min_row,$C:$C,0),IF(header_row_id=expenses_header_row, MATCH(expenses_min_row,$C:$C,0),IF(header_row_id=savings_header_row, MATCH(savings_min_row,$C:$C,0),""))),"")} -> 21 | N29: {=IF(is_cat,IF(header_row_id=Income_header_row, MATCH(income_max_row,$C:$C,0),IF(header_row_id=expenses_header_row, MATCH(expenses_max_row,$C:$C,0),IF(header_row_id=savings_header_row, MATCH(savings_max_row,$C:$C,0),""))),"")} -> 29 | O29: =IF(is_cat,ADDRESS(sort_min_row,COLUMN(tracked))&":"&ADDRESS(sort_max_row,COLUMN(tracked)),"") -> $K$21:$K$29 | P29: =IF(is_cat,RANK(tracked,INDIRECT(tracked_range),0),"") -> 4 | Q29: =IF(is_cat,ADDRESS(sort_min_row,COLUMN(budget))&":"&ADDRESS(sort_max_row,COLUMN(budget)),"") -> $L$21:$L$29 | R29: =IF(is_cat,RANK(budget,INDIRECT(budget_range),0),"") -> 4 | S29: =IF(is_cat,_xlfn.NUMBERVALUE(tracked_rank & budget_rank),"") -> 44 | T29: =IF(is_cat,ADDRESS(sort_min_row,COLUMN(comb_rank))&":"&ADDRESS(sort_max_row,COLUMN(comb_rank)),"") -> $S$21:$S$29 | U29: =IF(is_cat, RANK(comb_rank, INDIRECT(comb_rank_range),1),"") -> 4 | V29: =IF(is_cat,ADDRESS(sort_min_row,COLUMN(comb_rank_norm))&":"&ADDRESS(ROW(),COLUMN(comb_rank_norm)),"") -> $U$21:$U$29 | W29: =IF(is_cat,comb_rank_norm+COUNTIF(INDIRECT(comb_rank_norm_run_range),comb_rank_norm)-1,"") -> 4 | X29: =IF(is_cat,header_row_id+comb_rank_unique,row_id) -> 30 | Y29: =IF(is_empty,"",INDEX($J:$J,MATCH(row_id,$X:$X,0))) -> Media | Z29: =IF(is_empty,"",IF(is_header,"Tracked",INDEX($K:$K,MATCH(row_id,$X:$X,0)))) -> 0 | AA29: =IF(is_empty,"",IF(is_header,"Budget",INDEX($L:$L,MATCH(row_id,$X:$X,0)))) -> 3600 | AB29: =IF(is_empty,"",IF(is_header,"% Compl.",IFERROR(out_tracked/out_budget,"-"))) -> 0 | AC29: =IF(is_empty,"",IF(is_header,"Remaining",IF(out_budget-out_tracked>0,out_budget-out_tracked,0))) -> 3600 | AD29: =IF(is_empty,"",IF(is_header,"Excess",IF(out_budget-out_tracked<0,out_tracked-out_budget,0))) -> 0
C30: {=IF(C29=-1,-1, IF(C29<income_max_row,C29+1,IF(C29=income_max_row,income_total_row,IF(C29=income_total_row,"/1", IF(C29="/1",expenses_header_row,IF(C29<expenses_max_row,C29+1,IF(C29=expenses_max_row,expenses_total_row,IF(C29=expenses_total_row,"/2",IF(C29="/2",savings_header_row,IF(C29<savings_max_row,C29+1,IF(C29=savings_max_row,savings_total_row,-1)))))))))))} -> 41 | D30: =IF(is_header,row_id,IF(NOT(is_empty),D29,-1)) -> 26 | E30: {=1*OR(row_id=Income_header_row, row_id=expenses_header_row, row_id=savings_header_row)} -> 0 | F30: =1*NOT(OR(is_header, is_total, is_empty)) -> 0 | G30: {=1*OR(row_id=income_total_row, row_id=expenses_total_row, row_id=savings_total_row)} -> 1 | H30: =1*OR(row_id="/1", row_id="/2", row_id=-1) -> 0 | I30: {=IFERROR(INDEX('Budget Planning'!$C:$C,header_row_id),"")} -> Expenses | J30: {=IFERROR(INDEX('Budget Planning'!$C:$C,row_id),"")} -> Total | K30: {=IF(OR(is_header,is_empty),"",IF(is_total,IF(selected_period="Total Year",SUMPRODUCT(Tracking[Amount],--(TRIM(Tracking[Type])=TRIM(type)),--(Tracking[Date]>=DATE(selected_year,1,1)),--(Tracking[Date]<DATE(selected_year+1,1,1))),SUMPRODUCT(Tracking[Amount],--(TRIM(Tracking[Type])=TRIM(type)),--(Tracking[Date]>=DATE(selected_year,1,1)),--(Tracking[Date]<DATE(selected_year+1,1,1)),--(MONTH(Tracking[Date])=selected_period))),IF(selected_period="Total Year",SUMPRODUCT(Tracking[Amount],--(TRIM(Tracking[Type])=TRIM(type)),--(TRIM(Tracking[Categories])=TRIM(item)),--(Tracking[Date]>=DATE(selected_year,1,1)),--(Tracking[Date]<DATE(selected_year+1,1,1))),SUMPRODUCT(Tracking[Amount],--(TRIM(Tracking[Type])=TRIM(type)),--(TRIM(Tracking[Categories])=TRIM(item)),--(Tracking[Date]>=DATE(selected_year,1,1)),--(Tracking[Date]<DATE(selected_year+1,1,1)),--(MONTH(Tracking[Date])=selected_period)))))} -> 91555 | L30: {=IF(OR(is_header,is_empty),"",INDEX('Budget Planning'!$E:$FA,row_id,MATCH(IF(selected_period="Total Year",selected_year,DATE(selected_year,selected_period,1)),'Budget Planning'!$E$9:$FA$9,0)))} -> 530816 | M30: {=IF(is_cat,IF(header_row_id=Income_header_row, MATCH(income_min_row,$C:$C,0),IF(header_row_id=expenses_header_row, MATCH(expenses_min_row,$C:$C,0),IF(header_row_id=savings_header_row, MATCH(savings_min_row,$C:$C,0),""))),"")} | N30: {=IF(is_cat,IF(header_row_id=Income_header_row, MATCH(income_max_row,$C:$C,0),IF(header_row_id=expenses_header_row, MATCH(expenses_max_row,$C:$C,0),IF(header_row_id=savings_header_row, MATCH(savings_max_row,$C:$C,0),""))),"")} | O30: =IF(is_cat,ADDRESS(sort_min_row,COLUMN(tracked))&":"&ADDRESS(sort_max_row,COLUMN(tracked)),"") | P30: =IF(is_cat,RANK(tracked,INDIRECT(tracked_range),0),"") | Q30: =IF(is_cat,ADDRESS(sort_min_row,COLUMN(budget))&":"&ADDRESS(sort_max_row,COLUMN(budget)),"") | R30: =IF(is_cat,RANK(budget,INDIRECT(budget_range),0),"") | S30: =IF(is_cat,_xlfn.NUMBERVALUE(tracked_rank & budget_rank),"") | T30: =IF(is_cat,ADDRESS(sort_min_row,COLUMN(comb_rank))&":"&ADDRESS(sort_max_row,COLUMN(comb_rank)),"") | U30: =IF(is_cat, RANK(comb_rank, INDIRECT(comb_rank_range),1),"") | V30: =IF(is_cat,ADDRESS(sort_min_row,COLUMN(comb_rank_norm))&":"&ADDRESS(ROW(),COLUMN(comb_rank_norm)),"") | W30: =IF(is_cat,comb_rank_norm+COUNTIF(INDIRECT(comb_rank_norm_run_range),comb_rank_norm)-1,"") | X30: =IF(is_cat,header_row_id+comb_rank_unique,row_id) -> 41 | Y30: =IF(is_empty,"",INDEX($J:$J,MATCH(row_id,$X:$X,0))) -> Total | Z30: =IF(is_empty,"",IF(is_header,"Tracked",INDEX($K:$K,MATCH(row_id,$X:$X,0)))) -> 91555 | AA30: =IF(is_empty,"",IF(is_header,"Budget",INDEX($L:$L,MATCH(row_id,$X:$X,0)))) -> 530816 | AB30: =IF(is_empty,"",IF(is_header,"% Compl.",IFERROR(out_tracked/out_budget,"-"))) -> 0.17247973 | AC30: =IF(is_empty,"",IF(is_header,"Remaining",IF(out_budget-out_tracked>0,out_budget-out_tracked,0))) -> 439261 | AD30: =IF(is_empty,"",IF(is_header,"Excess",IF(out_budget-out_tracked<0,out_tracked-out_budget,0))) -> 0 | AI30: =Calculations!I35 -> Groceries | AJ30: =Calculations!J35 -> 45830 | AP30: =Calculations!M35 -> Emergency Fund | AQ30: =Calculations!N35 -> 50000
C31: {=IF(C30=-1,-1, IF(C30<income_max_row,C30+1,IF(C30=income_max_row,income_total_row,IF(C30=income_total_row,"/1", IF(C30="/1",expenses_header_row,IF(C30<expenses_max_row,C30+1,IF(C30=expenses_max_row,expenses_total_row,IF(C30=expenses_total_row,"/2",IF(C30="/2",savings_header_row,IF(C30<savings_max_row,C30+1,IF(C30=savings_max_row,savings_total_row,-1)))))))))))} -> /2 | D31: =IF(is_header,row_id,IF(NOT(is_empty),D30,-1)) -> -1 | E31: {=1*OR(row_id=Income_header_row, row_id=expenses_header_row, row_id=savings_header_row)} -> 0 | F31: =1*NOT(OR(is_header, is_total, is_empty)) -> 0 | G31: {=1*OR(row_id=income_total_row, row_id=expenses_total_row, row_id=savings_total_row)} -> 0 | H31: =1*OR(row_id="/1", row_id="/2", row_id=-1) -> 1 | I31: {=IFERROR(INDEX('Budget Planning'!$C:$C,header_row_id),"")} | J31: {=IFERROR(INDEX('Budget Planning'!$C:$C,row_id),"")} | K31: {=IF(OR(is_header,is_empty),"",IF(is_total,IF(selected_period="Total Year",SUMPRODUCT(Tracking[Amount],--(TRIM(Tracking[Type])=TRIM(type)),--(Tracking[Date]>=DATE(selected_year,1,1)),--(Tracking[Date]<DATE(selected_year+1,1,1))),SUMPRODUCT(Tracking[Amount],--(TRIM(Tracking[Type])=TRIM(type)),--(Tracking[Date]>=DATE(selected_year,1,1)),--(Tracking[Date]<DATE(selected_year+1,1,1)),--(MONTH(Tracking[Date])=selected_period))),IF(selected_period="Total Year",SUMPRODUCT(Tracking[Amount],--(TRIM(Tracking[Type])=TRIM(type)),--(TRIM(Tracking[Categories])=TRIM(item)),--(Tracking[Date]>=DATE(selected_year,1,1)),--(Tracking[Date]<DATE(selected_year+1,1,1))),SUMPRODUCT(Tracking[Amount],--(TRIM(Tracking[Type])=TRIM(type)),--(TRIM(Tracking[Categories])=TRIM(item)),--(Tracking[Date]>=DATE(selected_year,1,1)),--(Tracking[Date]<DATE(selected_year+1,1,1)),--(MONTH(Tracking[Date])=selected_period)))))} | L31: {=IF(OR(is_header,is_empty),"",INDEX('Budget Planning'!$E:$FA,row_id,MATCH(IF(selected_period="Total Year",selected_year,DATE(selected_year,selected_period,1)),'Budget Planning'!$E$9:$FA$9,0)))} | M31: {=IF(is_cat,IF(header_row_id=Income_header_row, MATCH(income_min_row,$C:$C,0),IF(header_row_id=expenses_header_row, MATCH(expenses_min_row,$C:$C,0),IF(header_row_id=savings_header_row, MATCH(savings_min_row,$C:$C,0),""))),"")} | N31: {=IF(is_cat,IF(header_row_id=Income_header_row, MATCH(income_max_row,$C:$C,0),IF(header_row_id=expenses_header_row, MATCH(expenses_max_row,$C:$C,0),IF(header_row_id=savings_header_row, MATCH(savings_max_row,$C:$C,0),""))),"")} | O31: =IF(is_cat,ADDRESS(sort_min_row,COLUMN(tracked))&":"&ADDRESS(sort_max_row,COLUMN(tracked)),"") | P31: =IF(is_cat,RANK(tracked,INDIRECT(tracked_range),0),"") | Q31: =IF(is_cat,ADDRESS(sort_min_row,COLUMN(budget))&":"&ADDRESS(sort_max_row,COLUMN(budget)),"") | R31: =IF(is_cat,RANK(budget,INDIRECT(budget_range),0),"") | S31: =IF(is_cat,_xlfn.NUMBERVALUE(tracked_rank & budget_rank),"") | T31: =IF(is_cat,ADDRESS(sort_min_row,COLUMN(comb_rank))&":"&ADDRESS(sort_max_row,COLUMN(comb_rank)),"") | U31: =IF(is_cat, RANK(comb_rank, INDIRECT(comb_rank_range),1),"") | V31: =IF(is_cat,ADDRESS(sort_min_row,COLUMN(comb_rank_norm))&":"&ADDRESS(ROW(),COLUMN(comb_rank_norm)),"") | W31: =IF(is_cat,comb_rank_norm+COUNTIF(INDIRECT(comb_rank_norm_run_range),comb_rank_norm)-1,"") | X31: =IF(is_cat,header_row_id+comb_rank_unique,row_id) -> /2 | Y31: =IF(is_empty,"",INDEX($J:$J,MATCH(row_id,$X:$X,0))) | Z31: =IF(is_empty,"",IF(is_header,"Tracked",INDEX($K:$K,MATCH(row_id,$X:$X,0)))) | AA31: =IF(is_empty,"",IF(is_header,"Budget",INDEX($L:$L,MATCH(row_id,$X:$X,0)))) | AB31: =IF(is_empty,"",IF(is_header,"% Compl.",IFERROR(out_tracked/out_budget,"-"))) | AC31: =IF(is_empty,"",IF(is_header,"Remaining",IF(out_budget-out_tracked>0,out_budget-out_tracked,0))) | AD31: =IF(is_empty,"",IF(is_header,"Excess",IF(out_budget-out_tracked<0,out_tracked-out_budget,0))) | AI31: =Calculations!I36 -> Rent | AJ31: =Calculations!J36 -> 25000 | AP31: =Calculations!M36 -> Mcleodganj Trip Fund | AQ31: =Calculations!N36 -> 35000
C32: {=IF(C31=-1,-1, IF(C31<income_max_row,C31+1,IF(C31=income_max_row,income_total_row,IF(C31=income_total_row,"/1", IF(C31="/1",expenses_header_row,IF(C31<expenses_max_row,C31+1,IF(C31=expenses_max_row,expenses_total_row,IF(C31=expenses_total_row,"/2",IF(C31="/2",savings_header_row,IF(C31<savings_max_row,C31+1,IF(C31=savings_max_row,savings_total_row,-1)))))))))))} -> 43 | D32: =IF(is_header,row_id,IF(NOT(is_empty),D31,-1)) -> 43 | E32: {=1*OR(row_id=Income_header_row, row_id=expenses_header_row, row_id=savings_header_row)} -> 1 | F32: =1*NOT(OR(is_header, is_total, is_empty)) -> 0 | G32: {=1*OR(row_id=income_total_row, row_id=expenses_total_row, row_id=savings_total_row)} -> 0 | H32: =1*OR(row_id="/1", row_id="/2", row_id=-1) -> 0 | I32: {=IFERROR(INDEX('Budget Planning'!$C:$C,header_row_id),"")} -> Savings | J32: {=IFERROR(INDEX('Budget Planning'!$C:$C,row_id),"")} -> Savings | K32: {=IF(OR(is_header,is_empty),"",IF(is_total,IF(selected_period="Total Year",SUMPRODUCT(Tracking[Amount],--(TRIM(Tracking[Type])=TRIM(type)),--(Tracking[Date]>=DATE(selected_year,1,1)),--(Tracking[Date]<DATE(selected_year+1,1,1))),SUMPRODUCT(Tracking[Amount],--(TRIM(Tracking[Type])=TRIM(type)),--(Tracking[Date]>=DATE(selected_year,1,1)),--(Tracking[Date]<DATE(selected_year+1,1,1)),--(MONTH(Tracking[Date])=selected_period))),IF(selected_period="Total Year",SUMPRODUCT(Tracking[Amount],--(TRIM(Tracking[Type])=TRIM(type)),--(TRIM(Tracking[Categories])=TRIM(item)),--(Tracking[Date]>=DATE(selected_year,1,1)),--(Tracking[Date]<DATE(selected_year+1,1,1))),SUMPRODUCT(Tracking[Amount],--(TRIM(Tracking[Type])=TRIM(type)),--(TRIM(Tracking[Categories])=TRIM(item)),--(Tracking[Date]>=DATE(selected_year,1,1)),--(Tracking[Date]<DATE(selected_year+1,1,1)),--(MONTH(Tracking[Date])=selected_period)))))} | L32: {=IF(OR(is_header,is_empty),"",INDEX('Budget Planning'!$E:$FA,row_id,MATCH(IF(selected_period="Total Year",selected_year,DATE(selected_year,selected_period,1)),'Budget Planning'!$E$9:$FA$9,0)))} | M32: {=IF(is_cat,IF(header_row_id=Income_header_row, MATCH(income_min_row,$C:$C,0),IF(header_row_id=expenses_header_row, MATCH(expenses_min_row,$C:$C,0),IF(header_row_id=savings_header_row, MATCH(savings_min_row,$C:$C,0),""))),"")} | N32: {=IF(is_cat,IF(header_row_id=Income_header_row, MATCH(income_max_row,$C:$C,0),IF(header_row_id=expenses_header_row, MATCH(expenses_max_row,$C:$C,0),IF(header_row_id=savings_header_row, MATCH(savings_max_row,$C:$C,0),""))),"")} | O32: =IF(is_cat,ADDRESS(sort_min_row,COLUMN(tracked))&":"&ADDRESS(sort_max_row,COLUMN(tracked)),"") | P32: =IF(is_cat,RANK(tracked,INDIRECT(tracked_range),0),"") | Q32: =IF(is_cat,ADDRESS(sort_min_row,COLUMN(budget))&":"&ADDRESS(sort_max_row,COLUMN(budget)),"") | R32: =IF(is_cat,RANK(budget,INDIRECT(budget_range),0),"") | S32: =IF(is_cat,_xlfn.NUMBERVALUE(tracked_rank & budget_rank),"") | T32: =IF(is_cat,ADDRESS(sort_min_row,COLUMN(comb_rank))&":"&ADDRESS(sort_max_row,COLUMN(comb_rank)),"") | U32: =IF(is_cat, RANK(comb_rank, INDIRECT(comb_rank_range),1),"") | V32: =IF(is_cat,ADDRESS(sort_min_row,COLUMN(comb_rank_norm))&":"&ADDRESS(ROW(),COLUMN(comb_rank_norm)),"") | W32: =IF(is_cat,comb_rank_norm+COUNTIF(INDIRECT(comb_rank_norm_run_range),comb_rank_norm)-1,"") | X32: =IF(is_cat,header_row_id+comb_rank_unique,row_id) -> 43 | Y32: =IF(is_empty,"",INDEX($J:$J,MATCH(row_id,$X:$X,0))) -> Savings | Z32: =IF(is_empty,"",IF(is_header,"Tracked",INDEX($K:$K,MATCH(row_id,$X:$X,0)))) -> Tracked | AA32: =IF(is_empty,"",IF(is_header,"Budget",INDEX($L:$L,MATCH(row_id,$X:$X,0)))) -> Budget | AB32: =IF(is_empty,"",IF(is_header,"% Compl.",IFERROR(out_tracked/out_budget,"-"))) -> % Compl. | AC32: =IF(is_empty,"",IF(is_header,"Remaining",IF(out_budget-out_tracked>0,out_budget-out_tracked,0))) -> Remaining | AD32: =IF(is_empty,"",IF(is_header,"Excess",IF(out_budget-out_tracked<0,out_tracked-out_budget,0))) -> Excess | AI32: =Calculations!I37 -> Fuel | AJ32: =Calculations!J37 -> 7500 | AP32: =Calculations!M37 -> Coorg Trip Fund | AQ32: =Calculations!N37 -> 15000
C33: {=IF(C32=-1,-1, IF(C32<income_max_row,C32+1,IF(C32=income_max_row,income_total_row,IF(C32=income_total_row,"/1", IF(C32="/1",expenses_header_row,IF(C32<expenses_max_row,C32+1,IF(C32=expenses_max_row,expenses_total_row,IF(C32=expenses_total_row,"/2",IF(C32="/2",savings_header_row,IF(C32<savings_max_row,C32+1,IF(C32=savings_max_row,savings_total_row,-1)))))))))))} -> 44 | D33: =IF(is_header,row_id,IF(NOT(is_empty),D32,-1)) -> 43 | E33: {=1*OR(row_id=Income_header_row, row_id=expenses_header_row, row_id=savings_header_row)} -> 0 | F33: =1*NOT(OR(is_header, is_total, is_empty)) -> 1 | G33: {=1*OR(row_id=income_total_row, row_id=expenses_total_row, row_id=savings_total_row)} -> 0 | H33: =1*OR(row_id="/1", row_id="/2", row_id=-1) -> 0 | I33: {=IFERROR(INDEX('Budget Planning'!$C:$C,header_row_id),"")} -> Savings | J33: {=IFERROR(INDEX('Budget Planning'!$C:$C,row_id),"")} -> Emergency Fund | K33: {=IF(OR(is_header,is_empty),"",IF(is_total,IF(selected_period="Total Year",SUMPRODUCT(Tracking[Amount],--(TRIM(Tracking[Type])=TRIM(type)),--(Tracking[Date]>=DATE(selected_year,1,1)),--(Tracking[Date]<DATE(selected_year+1,1,1))),SUMPRODUCT(Tracking[Amount],--(TRIM(Tracking[Type])=TRIM(type)),--(Tracking[Date]>=DATE(selected_year,1,1)),--(Tracking[Date]<DATE(selected_year+1,1,1)),--(MONTH(Tracking[Date])=selected_period))),IF(selected_period="Total Year",SUMPRODUCT(Tracking[Amount],--(TRIM(Tracking[Type])=TRIM(type)),--(TRIM(Tracking[Categories])=TRIM(item)),--(Tracking[Date]>=DATE(selected_year,1,1)),--(Tracking[Date]<DATE(selected_year+1,1,1))),SUMPRODUCT(Tracking[Amount],--(TRIM(Tracking[Type])=TRIM(type)),--(TRIM(Tracking[Categories])=TRIM(item)),--(Tracking[Date]>=DATE(selected_year,1,1)),--(Tracking[Date]<DATE(selected_year+1,1,1)),--(MONTH(Tracking[Date])=selected_period)))))} -> 50000 | L33: {=IF(OR(is_header,is_empty),"",INDEX('Budget Planning'!$E:$FA,row_id,MATCH(IF(selected_period="Total Year",selected_year,DATE(selected_year,selected_period,1)),'Budget Planning'!$E$9:$FA$9,0)))} -> 275000 | M33: {=IF(is_cat,IF(header_row_id=Income_header_row, MATCH(income_min_row,$C:$C,0),IF(header_row_id=expenses_header_row, MATCH(expenses_min_row,$C:$C,0),IF(header_row_id=savings_header_row, MATCH(savings_min_row,$C:$C,0),""))),"")} -> 33 | N33: {=IF(is_cat,IF(header_row_id=Income_header_row, MATCH(income_max_row,$C:$C,0),IF(header_row_id=expenses_header_row, MATCH(expenses_max_row,$C:$C,0),IF(header_row_id=savings_header_row, MATCH(savings_max_row,$C:$C,0),""))),"")} -> 41 | O33: =IF(is_cat,ADDRESS(sort_min_row,COLUMN(tracked))&":"&ADDRESS(sort_max_row,COLUMN(tracked)),"") -> $K$33:$K$41 | P33: =IF(is_cat,RANK(tracked,INDIRECT(tracked_range),0),"") -> 1 | Q33: =IF(is_cat,ADDRESS(sort_min_row,COLUMN(budget))&":"&ADDRESS(sort_max_row,COLUMN(budget)),"") -> $L$33:$L$41 | R33: =IF(is_cat,RANK(budget,INDIRECT(budget_range),0),"") -> 1 | S33: =IF(is_cat,_xlfn.NUMBERVALUE(tracked_rank & budget_rank),"") -> 11 | T33: =IF(is_cat,ADDRESS(sort_min_row,COLUMN(comb_rank))&":"&ADDRESS(sort_max_row,COLUMN(comb_rank)),"") -> $S$33:$S$41 | U33: =IF(is_cat, RANK(comb_rank, INDIRECT(comb_rank_range),1),"") -> 1 | V33: =IF(is_cat,ADDRESS(sort_min_row,COLUMN(comb_rank_norm))&":"&ADDRESS(ROW(),COLUMN(comb_rank_norm)),"") -> $U$33:$U$33 | W33: =IF(is_cat,comb_rank_norm+COUNTIF(INDIRECT(comb_rank_norm_run_range),comb_rank_norm)-1,"") -> 1 | X33: =IF(is_cat,header_row_id+comb_rank_unique,row_id) -> 44 | Y33: =IF(is_empty,"",INDEX($J:$J,MATCH(row_id,$X:$X,0))) -> Emergency Fund | Z33: =IF(is_empty,"",IF(is_header,"Tracked",INDEX($K:$K,MATCH(row_id,$X:$X,0)))) -> 50000 | AA33: =IF(is_empty,"",IF(is_header,"Budget",INDEX($L:$L,MATCH(row_id,$X:$X,0)))) -> 275000 | AB33: =IF(is_empty,"",IF(is_header,"% Compl.",IFERROR(out_tracked/out_budget,"-"))) -> 0.18181818 | AC33: =IF(is_empty,"",IF(is_header,"Remaining",IF(out_budget-out_tracked>0,out_budget-out_tracked,0))) -> 225000 | AD33: =IF(is_empty,"",IF(is_header,"Excess",IF(out_budget-out_tracked<0,out_tracked-out_budget,0))) -> 0 | AI33: =Calculations!I38 -> Fun & Vacation | AJ33: =Calculations!J38 -> 6430 | AP33: =Calculations!M38 -> SIP | AQ33: =Calculations!N38 -> 6000
C34: {=IF(C33=-1,-1, IF(C33<income_max_row,C33+1,IF(C33=income_max_row,income_total_row,IF(C33=income_total_row,"/1", IF(C33="/1",expenses_header_row,IF(C33<expenses_max_row,C33+1,IF(C33=expenses_max_row,expenses_total_row,IF(C33=expenses_total_row,"/2",IF(C33="/2",savings_header_row,IF(C33<savings_max_row,C33+1,IF(C33=savings_max_row,savings_total_row,-1)))))))))))} -> 45 | D34: =IF(is_header,row_id,IF(NOT(is_empty),D33,-1)) -> 43 | E34: {=1*OR(row_id=Income_header_row, row_id=expenses_header_row, row_id=savings_header_row)} -> 0 | F34: =1*NOT(OR(is_header, is_total, is_empty)) -> 1 | G34: {=1*OR(row_id=income_total_row, row_id=expenses_total_row, row_id=savings_total_row)} -> 0 | H34: =1*OR(row_id="/1", row_id="/2", row_id=-1) -> 0 | I34: {=IFERROR(INDEX('Budget Planning'!$C:$C,header_row_id),"")} -> Savings | J34: {=IFERROR(INDEX('Budget Planning'!$C:$C,row_id),"")} -> SIP | K34: {=IF(OR(is_header,is_empty),"",IF(is_total,IF(selected_period="Total Year",SUMPRODUCT(Tracking[Amount],--(TRIM(Tracking[Type])=TRIM(type)),--(Tracking[Date]>=DATE(selected_year,1,1)),--(Tracking[Date]<DATE(selected_year+1,1,1))),SUMPRODUCT(Tracking[Amount],--(TRIM(Tracking[Type])=TRIM(type)),--(Tracking[Date]>=DATE(selected_year,1,1)),--(Tracking[Date]<DATE(selected_year+1,1,1)),--(MONTH(Tracking[Date])=selected_period))),IF(selected_period="Total Year",SUMPRODUCT(Tracking[Amount],--(TRIM(Tracking[Type])=TRIM(type)),--(TRIM(Tracking[Categories])=TRIM(item)),--(Tracking[Date]>=DATE(selected_year,1,1)),--(Tracking[Date]<DATE(selected_year+1,1,1))),SUMPRODUCT(Tracking[Amount],--(TRIM(Tracking[Type])=TRIM(type)),--(TRIM(Tracking[Categories])=TRIM(item)),--(Tracking[Date]>=DATE(selected_year,1,1)),--(Tracking[Date]<DATE(selected_year+1,1,1)),--(MONTH(Tracking[Date])=selected_period)))))} -> 6000 | L34: {=IF(OR(is_header,is_empty),"",INDEX('Budget Planning'!$E:$FA,row_id,MATCH(IF(selected_period="Total Year",selected_year,DATE(selected_year,selected_period,1)),'Budget Planning'!$E$9:$FA$9,0)))} -> 113000 | M34: {=IF(is_cat,IF(header_row_id=Income_header_row, MATCH(income_min_row,$C:$C,0),IF(header_row_id=expenses_header_row, MATCH(expenses_min_row,$C:$C,0),IF(header_row_id=savings_header_row, MATCH(savings_min_row,$C:$C,0),""))),"")} -> 33 | N34: {=IF(is_cat,IF(header_row_id=Income_header_row, MATCH(income_max_row,$C:$C,0),IF(header_row_id=expenses_header_row, MATCH(expenses_max_row,$C:$C,0),IF(header_row_id=savings_header_row, MATCH(savings_max_row,$C:$C,0),""))),"")} -> 41 | O34: =IF(is_cat,ADDRESS(sort_min_row,COLUMN(tracked))&":"&ADDRESS(sort_max_row,COLUMN(tracked)),"") -> $K$33:$K$41 | P34: =IF(is_cat,RANK(tracked,INDIRECT(tracked_range),0),"") -> 4 | Q34: =IF(is_cat,ADDRESS(sort_min_row,COLUMN(budget))&":"&ADDRESS(sort_max_row,COLUMN(budget)),"") -> $L$33:$L$41 | R34: =IF(is_cat,RANK(budget,INDIRECT(budget_range),0),"") -> 3 | S34: =IF(is_cat,_xlfn.NUMBERVALUE(tracked_rank & budget_rank),"") -> 43 | T34: =IF(is_cat,ADDRESS(sort_min_row,COLUMN(comb_rank))&":"&ADDRESS(sort_max_row,COLUMN(comb_rank)),"") -> $S$33:$S$41 | U34: =IF(is_cat, RANK(comb_rank, INDIRECT(comb_rank_range),1),"") -> 4 | V34: =IF(is_cat,ADDRESS(sort_min_row,COLUMN(comb_rank_norm))&":"&ADDRESS(ROW(),COLUMN(comb_rank_norm)),"") -> $U$33:$U$34 | W34: =IF(is_cat,comb_rank_norm+COUNTIF(INDIRECT(comb_rank_norm_run_range),comb_rank_norm)-1,"") -> 4 | X34: =IF(is_cat,header_row_id+comb_rank_unique,row_id) -> 47 | Y34: =IF(is_empty,"",INDEX($J:$J,MATCH(row_id,$X:$X,0))) -> Mcleodganj Trip Fund | Z34: =IF(is_empty,"",IF(is_header,"Tracked",INDEX($K:$K,MATCH(row_id,$X:$X,0)))) -> 35000 | AA34: =IF(is_empty,"",IF(is_header,"Budget",INDEX($L:$L,MATCH(row_id,$X:$X,0)))) -> 50000 | AB34: =IF(is_empty,"",IF(is_header,"% Compl.",IFERROR(out_tracked/out_budget,"-"))) -> 0.7 | AC34: =IF(is_empty,"",IF(is_header,"Remaining",IF(out_budget-out_tracked>0,out_budget-out_tracked,0))) -> 15000 | AD34: =IF(is_empty,"",IF(is_header,"Excess",IF(out_budget-out_tracked<0,out_tracked-out_budget,0))) -> 0 | AI34: =Calculations!I39 -> MISC | AJ34: =Calculations!J39 -> 3222 | AP34: =Calculations!M39 -> Skill Development | AQ34: =Calculations!N39 -> 5686
C35: {=IF(C34=-1,-1, IF(C34<income_max_row,C34+1,IF(C34=income_max_row,income_total_row,IF(C34=income_total_row,"/1", IF(C34="/1",expenses_header_row,IF(C34<expenses_max_row,C34+1,IF(C34=expenses_max_row,expenses_total_row,IF(C34=expenses_total_row,"/2",IF(C34="/2",savings_header_row,IF(C34<savings_max_row,C34+1,IF(C34=savings_max_row,savings_total_row,-1)))))))))))} -> 46 | D35: =IF(is_header,row_id,IF(NOT(is_empty),D34,-1)) -> 43 | E35: {=1*OR(row_id=Income_header_row, row_id=expenses_header_row, row_id=savings_header_row)} -> 0 | F35: =1*NOT(OR(is_header, is_total, is_empty)) -> 1 | G35: {=1*OR(row_id=income_total_row, row_id=expenses_total_row, row_id=savings_total_row)} -> 0 | H35: =1*OR(row_id="/1", row_id="/2", row_id=-1) -> 0 | I35: {=IFERROR(INDEX('Budget Planning'!$C:$C,header_row_id),"")} -> Savings | J35: {=IFERROR(INDEX('Budget Planning'!$C:$C,row_id),"")} -> Stock Portfolio | K35: {=IF(OR(is_header,is_empty),"",IF(is_total,IF(selected_period="Total Year",SUMPRODUCT(Tracking[Amount],--(TRIM(Tracking[Type])=TRIM(type)),--(Tracking[Date]>=DATE(selected_year,1,1)),--(Tracking[Date]<DATE(selected_year+1,1,1))),SUMPRODUCT(Tracking[Amount],--(TRIM(Tracking[Type])=TRIM(type)),--(Tracking[Date]>=DATE(selected_year,1,1)),--(Tracking[Date]<DATE(selected_year+1,1,1)),--(MONTH(Tracking[Date])=selected_period))),IF(selected_period="Total Year",SUMPRODUCT(Tracking[Amount],--(TRIM(Tracking[Type])=TRIM(type)),--(TRIM(Tracking[Categories])=TRIM(item)),--(Tracking[Date]>=DATE(selected_year,1,1)),--(Tracking[Date]<DATE(selected_year+1,1,1))),SUMPRODUCT(Tracking[Amount],--(TRIM(Tracking[Type])=TRIM(type)),--(TRIM(Tracking[Categories])=TRIM(item)),--(Tracking[Date]>=DATE(selected_year,1,1)),--(Tracking[Date]<DATE(selected_year+1,1,1)),--(MONTH(Tracking[Date])=selected_period)))))} -> 0 | L35: {=IF(OR(is_header,is_empty),"",INDEX('Budget Planning'!$E:$FA,row_id,MATCH(IF(selected_period="Total Year",selected_year,DATE(selected_year,selected_period,1)),'Budget Planning'!$E$9:$FA$9,0)))} -> 120186 | M35: {=IF(is_cat,IF(header_row_id=Income_header_row, MATCH(income_min_row,$C:$C,0),IF(header_row_id=expenses_header_row, MATCH(expenses_min_row,$C:$C,0),IF(header_row_id=savings_header_row, MATCH(savings_min_row,$C:$C,0),""))),"")} -> 33 | N35: {=IF(is_cat,IF(header_row_id=Income_header_row, MATCH(income_max_row,$C:$C,0),IF(header_row_id=expenses_header_row, MATCH(expenses_max_row,$C:$C,0),IF(header_row_id=savings_header_row, MATCH(savings_max_row,$C:$C,0),""))),"")} -> 41 | O35: =IF(is_cat,ADDRESS(sort_min_row,COLUMN(tracked))&":"&ADDRESS(sort_max_row,COLUMN(tracked)),"") -> $K$33:$K$41 | P35: =IF(is_cat,RANK(tracked,INDIRECT(tracked_range),0),"") -> 6 | Q35: =IF(is_cat,ADDRESS(sort_min_row,COLUMN(budget))&":"&ADDRESS(sort_max_row,COLUMN(budget)),"") -> $L$33:$L$41 | R35: =IF(is_cat,RANK(budget,INDIRECT(budget_range),0),"") -> 2 | S35: =IF(is_cat,_xlfn.NUMBERVALUE(tracked_rank & budget_rank),"") -> 62 | T35: =IF(is_cat,ADDRESS(sort_min_row,COLUMN(comb_rank))&":"&ADDRESS(sort_max_row,COLUMN(comb_rank)),"") -> $S$33:$S$41 | U35: =IF(is_cat, RANK(comb_rank, INDIRECT(comb_rank_range),1),"") -> 6 | V35: =IF(is_cat,ADDRESS(sort_min_row,COLUMN(comb_rank_norm))&":"&ADDRESS(ROW(),COLUMN(comb_rank_norm)),"") -> $U$33:$U$35 | W35: =IF(is_cat,comb_rank_norm+COUNTIF(INDIRECT(comb_rank_norm_run_range),comb_rank_norm)-1,"") -> 6 | X35: =IF(is_cat,header_row_id+comb_rank_unique,row_id) -> 49 | Y35: =IF(is_empty,"",INDEX($J:$J,MATCH(row_id,$X:$X,0))) -> Coorg Trip Fund | Z35: =IF(is_empty,"",IF(is_header,"Tracked",INDEX($K:$K,MATCH(row_id,$X:$X,0)))) -> 15000 | AA35: =IF(is_empty,"",IF(is_header,"Budget",INDEX($L:$L,MATCH(row_id,$X:$X,0)))) -> 12500 | AB35: =IF(is_empty,"",IF(is_header,"% Compl.",IFERROR(out_tracked/out_budget,"-"))) -> 1.2 | AC35: =IF(is_empty,"",IF(is_header,"Remaining",IF(out_budget-out_tracked>0,out_budget-out_tracked,0))) -> 0 | AD35: =IF(is_empty,"",IF(is_header,"Excess",IF(out_budget-out_tracked<0,out_tracked-out_budget,0))) -> 2500 | AI35: =Calculations!I40 -> Other | AJ35: =Calculations!J40 -> 3573 | AP35: =Calculations!M40 | AQ35: =Calculations!N40
C36: {=IF(C35=-1,-1, IF(C35<income_max_row,C35+1,IF(C35=income_max_row,income_total_row,IF(C35=income_total_row,"/1", IF(C35="/1",expenses_header_row,IF(C35<expenses_max_row,C35+1,IF(C35=expenses_max_row,expenses_total_row,IF(C35=expenses_total_row,"/2",IF(C35="/2",savings_header_row,IF(C35<savings_max_row,C35+1,IF(C35=savings_max_row,savings_total_row,-1)))))))))))} -> 47 | D36: =IF(is_header,row_id,IF(NOT(is_empty),D35,-1)) -> 43 | E36: {=1*OR(row_id=Income_header_row, row_id=expenses_header_row, row_id=savings_header_row)} -> 0 | F36: =1*NOT(OR(is_header, is_total, is_empty)) -> 1 | G36: {=1*OR(row_id=income_total_row, row_id=expenses_total_row, row_id=savings_total_row)} -> 0 | H36: =1*OR(row_id="/1", row_id="/2", row_id=-1) -> 0 | I36: {=IFERROR(INDEX('Budget Planning'!$C:$C,header_row_id),"")} -> Savings | J36: {=IFERROR(INDEX('Budget Planning'!$C:$C,row_id),"")} -> Crpto | K36: {=IF(OR(is_header,is_empty),"",IF(is_total,IF(selected_period="Total Year",SUMPRODUCT(Tracking[Amount],--(TRIM(Tracking[Type])=TRIM(type)),--(Tracking[Date]>=DATE(selected_year,1,1)),--(Tracking[Date]<DATE(selected_year+1,1,1))),SUMPRODUCT(Tracking[Amount],--(TRIM(Tracking[Type])=TRIM(type)),--(Tracking[Date]>=DATE(selected_year,1,1)),--(Tracking[Date]<DATE(selected_year+1,1,1)),--(MONTH(Tracking[Date])=selected_period))),IF(selected_period="Total Year",SUMPRODUCT(Tracking[Amount],--(TRIM(Tracking[Type])=TRIM(type)),--(TRIM(Tracking[Categories])=TRIM(item)),--(Tracking[Date]>=DATE(selected_year,1,1)),--(Tracking[Date]<DATE(selected_year+1,1,1))),SUMPRODUCT(Tracking[Amount],--(TRIM(Tracking[Type])=TRIM(type)),--(TRIM(Tracking[Categories])=TRIM(item)),--(Tracking[Date]>=DATE(selected_year,1,1)),--(Tracking[Date]<DATE(selected_year+1,1,1)),--(MONTH(Tracking[Date])=selected_period)))))} -> 0 | L36: {=IF(OR(is_header,is_empty),"",INDEX('Budget Planning'!$E:$FA,row_id,MATCH(IF(selected_period="Total Year",selected_year,DATE(selected_year,selected_period,1)),'Budget Planning'!$E$9:$FA$9,0)))} -> 41359 | M36: {=IF(is_cat,IF(header_row_id=Income_header_row, MATCH(income_min_row,$C:$C,0),IF(header_row_id=expenses_header_row, MATCH(expenses_min_row,$C:$C,0),IF(header_row_id=savings_header_row, MATCH(savings_min_row,$C:$C,0),""))),"")} -> 33 | N36: {=IF(is_cat,IF(header_row_id=Income_header_row, MATCH(income_max_row,$C:$C,0),IF(header_row_id=expenses_header_row, MATCH(expenses_max_row,$C:$C,0),IF(header_row_id=savings_header_row, MATCH(savings_max_row,$C:$C,0),""))),"")} -> 41 | O36: =IF(is_cat,ADDRESS(sort_min_row,COLUMN(tracked))&":"&ADDRESS(sort_max_row,COLUMN(tracked)),"") -> $K$33:$K$41 | P36: =IF(is_cat,RANK(tracked,INDIRECT(tracked_range),0),"") -> 6 | Q36: =IF(is_cat,ADDRESS(sort_min_row,COLUMN(budget))&":"&ADDRESS(sort_max_row,COLUMN(budget)),"") -> $L$33:$L$41 | R36: =IF(is_cat,RANK(budget,INDIRECT(budget_range),0),"") -> 7 | S36: =IF(is_cat,_xlfn.NUMBERVALUE(tracked_rank & budget_rank),"") -> 67 | T36: =IF(is_cat,ADDRESS(sort_min_row,COLUMN(comb_rank))&":"&ADDRESS(sort_max_row,COLUMN(comb_rank)),"") -> $S$33:$S$41 | U36: =IF(is_cat, RANK(comb_rank, INDIRECT(comb_rank_range),1),"") -> 9 | V36: =IF(is_cat,ADDRESS(sort_min_row,COLUMN(comb_rank_norm))&":"&ADDRESS(ROW(),COLUMN(comb_rank_norm)),"") -> $U$33:$U$36 | W36: =IF(is_cat,comb_rank_norm+COUNTIF(INDIRECT(comb_rank_norm_run_range),comb_rank_norm)-1,"") -> 9 | X36: =IF(is_cat,header_row_id+comb_rank_unique,row_id) -> 52 | Y36: =IF(is_empty,"",INDEX($J:$J,MATCH(row_id,$X:$X,0))) -> SIP | Z36: =IF(is_empty,"",IF(is_header,"Tracked",INDEX($K:$K,MATCH(row_id,$X:$X,0)))) -> 6000 | AA36: =IF(is_empty,"",IF(is_header,"Budget",INDEX($L:$L,MATCH(row_id,$X:$X,0)))) -> 113000 | AB36: =IF(is_empty,"",IF(is_header,"% Compl.",IFERROR(out_tracked/out_budget,"-"))) -> 0.053097345 | AC36: =IF(is_empty,"",IF(is_header,"Remaining",IF(out_budget-out_tracked>0,out_budget-out_tracked,0))) -> 107000 | AD36: =IF(is_empty,"",IF(is_header,"Excess",IF(out_budget-out_tracked<0,out_tracked-out_budget,0))) -> 0 | AI36: =Calculations!I41 -> Total | AJ36: =Calculations!J41 -> 91555 | AP36: =Calculations!M41 -> Total | AQ36: =Calculations!N41 -> 111686
C37: {=IF(C36=-1,-1, IF(C36<income_max_row,C36+1,IF(C36=income_max_row,income_total_row,IF(C36=income_total_row,"/1", IF(C36="/1",expenses_header_row,IF(C36<expenses_max_row,C36+1,IF(C36=expenses_max_row,expenses_total_row,IF(C36=expenses_total_row,"/2",IF(C36="/2",savings_header_row,IF(C36<savings_max_row,C36+1,IF(C36=savings_max_row,savings_total_row,-1)))))))))))} -> 48 | D37: =IF(is_header,row_id,IF(NOT(is_empty),D36,-1)) -> 43 | E37: {=1*OR(row_id=Income_header_row, row_id=expenses_header_row, row_id=savings_header_row)} -> 0 | F37: =1*NOT(OR(is_header, is_total, is_empty)) -> 1 | G37: {=1*OR(row_id=income_total_row, row_id=expenses_total_row, row_id=savings_total_row)} -> 0 | H37: =1*OR(row_id="/1", row_id="/2", row_id=-1) -> 0 | I37: {=IFERROR(INDEX('Budget Planning'!$C:$C,header_row_id),"")} -> Savings | J37: {=IFERROR(INDEX('Budget Planning'!$C:$C,row_id),"")} -> Skill Development | K37: {=IF(OR(is_header,is_empty),"",IF(is_total,IF(selected_period="Total Year",SUMPRODUCT(Tracking[Amount],--(TRIM(Tracking[Type])=TRIM(type)),--(Tracking[Date]>=DATE(selected_year,1,1)),--(Tracking[Date]<DATE(selected_year+1,1,1))),SUMPRODUCT(Tracking[Amount],--(TRIM(Tracking[Type])=TRIM(type)),--(Tracking[Date]>=DATE(selected_year,1,1)),--(Tracking[Date]<DATE(selected_year+1,1,1)),--(MONTH(Tracking[Date])=selected_period))),IF(selected_period="Total Year",SUMPRODUCT(Tracking[Amount],--(TRIM(Tracking[Type])=TRIM(type)),--(TRIM(Tracking[Categories])=TRIM(item)),--(Tracking[Date]>=DATE(selected_year,1,1)),--(Tracking[Date]<DATE(selected_year+1,1,1))),SUMPRODUCT(Tracking[Amount],--(TRIM(Tracking[Type])=TRIM(type)),--(TRIM(Tracking[Categories])=TRIM(item)),--(Tracking[Date]>=DATE(selected_year,1,1)),--(Tracking[Date]<DATE(selected_year+1,1,1)),--(MONTH(Tracking[Date])=selected_period)))))} -> 5686 | L37: {=IF(OR(is_header,is_empty),"",INDEX('Budget Planning'!$E:$FA,row_id,MATCH(IF(selected_period="Total Year",selected_year,DATE(selected_year,selected_period,1)),'Budget Planning'!$E$9:$FA$9,0)))} -> 33000 | M37: {=IF(is_cat,IF(header_row_id=Income_header_row, MATCH(income_min_row,$C:$C,0),IF(header_row_id=expenses_header_row, MATCH(expenses_min_row,$C:$C,0),IF(header_row_id=savings_header_row, MATCH(savings_min_row,$C:$C,0),""))),"")} -> 33 | N37: {=IF(is_cat,IF(header_row_id=Income_header_row, MATCH(income_max_row,$C:$C,0),IF(header_row_id=expenses_header_row, MATCH(expenses_max_row,$C:$C,0),IF(header_row_id=savings_header_row, MATCH(savings_max_row,$C:$C,0),""))),"")} -> 41 | O37: =IF(is_cat,ADDRESS(sort_min_row,COLUMN(tracked))&":"&ADDRESS(sort_max_row,COLUMN(tracked)),"") -> $K$33:$K$41 | P37: =IF(is_cat,RANK(tracked,INDIRECT(tracked_range),0),"") -> 5 | Q37: =IF(is_cat,ADDRESS(sort_min_row,COLUMN(budget))&":"&ADDRESS(sort_max_row,COLUMN(budget)),"") -> $L$33:$L$41 | R37: =IF(is_cat,RANK(budget,INDIRECT(budget_range),0),"") -> 8 | S37: =IF(is_cat,_xlfn.NUMBERVALUE(tracked_rank & budget_rank),"") -> 58 | T37: =IF(is_cat,ADDRESS(sort_min_row,COLUMN(comb_rank))&":"&ADDRESS(sort_max_row,COLUMN(comb_rank)),"") -> $S$33:$S$41 | U37: =IF(is_cat, RANK(comb_rank, INDIRECT(comb_rank_range),1),"") -> 5 | V37: =IF(is_cat,ADDRESS(sort_min_row,COLUMN(comb_rank_norm))&":"&ADDRESS(ROW(),COLUMN(comb_rank_norm)),"") -> $U$33:$U$37 | W37: =IF(is_cat,comb_rank_norm+COUNTIF(INDIRECT(comb_rank_norm_run_range),comb_rank_norm)-1,"") -> 5 | X37: =IF(is_cat,header_row_id+comb_rank_unique,row_id) -> 48 | Y37: =IF(is_empty,"",INDEX($J:$J,MATCH(row_id,$X:$X,0))) -> Skill Development | Z37: =IF(is_empty,"",IF(is_header,"Tracked",INDEX($K:$K,MATCH(row_id,$X:$X,0)))) -> 5686 | AA37: =IF(is_empty,"",IF(is_header,"Budget",INDEX($L:$L,MATCH(row_id,$X:$X,0)))) -> 33000 | AB37: =IF(is_empty,"",IF(is_header,"% Compl.",IFERROR(out_tracked/out_budget,"-"))) -> 0.17230303 | AC37: =IF(is_empty,"",IF(is_header,"Remaining",IF(out_budget-out_tracked>0,out_budget-out_tracked,0))) -> 27314 | AD37: =IF(is_empty,"",IF(is_header,"Excess",IF(out_budget-out_tracked<0,out_tracked-out_budget,0))) -> 0
C38: {=IF(C37=-1,-1, IF(C37<income_max_row,C37+1,IF(C37=income_max_row,income_total_row,IF(C37=income_total_row,"/1", IF(C37="/1",expenses_header_row,IF(C37<expenses_max_row,C37+1,IF(C37=expenses_max_row,expenses_total_row,IF(C37=expenses_total_row,"/2",IF(C37="/2",savings_header_row,IF(C37<savings_max_row,C37+1,IF(C37=savings_max_row,savings_total_row,-1)))))))))))} -> 49 | D38: =IF(is_header,row_id,IF(NOT(is_empty),D37,-1)) -> 43 | E38: {=1*OR(row_id=Income_header_row, row_id=expenses_header_row, row_id=savings_header_row)} -> 0 | F38: =1*NOT(OR(is_header, is_total, is_empty)) -> 1 | G38: {=1*OR(row_id=income_total_row, row_id=expenses_total_row, row_id=savings_total_row)} -> 0 | H38: =1*OR(row_id="/1", row_id="/2", row_id=-1) -> 0 | I38: {=IFERROR(INDEX('Budget Planning'!$C:$C,header_row_id),"")} -> Savings | J38: {=IFERROR(INDEX('Budget Planning'!$C:$C,row_id),"")} -> Coorg Trip Fund | K38: {=IF(OR(is_header,is_empty),"",IF(is_total,IF(selected_period="Total Year",SUMPRODUCT(Tracking[Amount],--(TRIM(Tracking[Type])=TRIM(type)),--(Tracking[Date]>=DATE(selected_year,1,1)),--(Tracking[Date]<DATE(selected_year+1,1,1))),SUMPRODUCT(Tracking[Amount],--(TRIM(Tracking[Type])=TRIM(type)),--(Tracking[Date]>=DATE(selected_year,1,1)),--(Tracking[Date]<DATE(selected_year+1,1,1)),--(MONTH(Tracking[Date])=selected_period))),IF(selected_period="Total Year",SUMPRODUCT(Tracking[Amount],--(TRIM(Tracking[Type])=TRIM(type)),--(TRIM(Tracking[Categories])=TRIM(item)),--(Tracking[Date]>=DATE(selected_year,1,1)),--(Tracking[Date]<DATE(selected_year+1,1,1))),SUMPRODUCT(Tracking[Amount],--(TRIM(Tracking[Type])=TRIM(type)),--(TRIM(Tracking[Categories])=TRIM(item)),--(Tracking[Date]>=DATE(selected_year,1,1)),--(Tracking[Date]<DATE(selected_year+1,1,1)),--(MONTH(Tracking[Date])=selected_period)))))} -> 15000 | L38: {=IF(OR(is_header,is_empty),"",INDEX('Budget Planning'!$E:$FA,row_id,MATCH(IF(selected_period="Total Year",selected_year,DATE(selected_year,selected_period,1)),'Budget Planning'!$E$9:$FA$9,0)))} -> 12500 | M38: {=IF(is_cat,IF(header_row_id=Income_header_row, MATCH(income_min_row,$C:$C,0),IF(header_row_id=expenses_header_row, MATCH(expenses_min_row,$C:$C,0),IF(header_row_id=savings_header_row, MATCH(savings_min_row,$C:$C,0),""))),"")} -> 33 | N38: {=IF(is_cat,IF(header_row_id=Income_header_row, MATCH(income_max_row,$C:$C,0),IF(header_row_id=expenses_header_row, MATCH(expenses_max_row,$C:$C,0),IF(header_row_id=savings_header_row, MATCH(savings_max_row,$C:$C,0),""))),"")} -> 41 | O38: =IF(is_cat,ADDRESS(sort_min_row,COLUMN(tracked))&":"&ADDRESS(sort_max_row,COLUMN(tracked)),"") -> $K$33:$K$41 | P38: =IF(is_cat,RANK(tracked,INDIRECT(tracked_range),0),"") -> 3 | Q38: =IF(is_cat,ADDRESS(sort_min_row,COLUMN(budget))&":"&ADDRESS(sort_max_row,COLUMN(budget)),"") -> $L$33:$L$41 | R38: =IF(is_cat,RANK(budget,INDIRECT(budget_range),0),"") -> 9 | S38: =IF(is_cat,_xlfn.NUMBERVALUE(tracked_rank & budget_rank),"") -> 39 | T38: =IF(is_cat,ADDRESS(sort_min_row,COLUMN(comb_rank))&":"&ADDRESS(sort_max_row,COLUMN(comb_rank)),"") -> $S$33:$S$41 | U38: =IF(is_cat, RANK(comb_rank, INDIRECT(comb_rank_range),1),"") -> 3 | V38: =IF(is_cat,ADDRESS(sort_min_row,COLUMN(comb_rank_norm))&":"&ADDRESS(ROW(),COLUMN(comb_rank_norm)),"") -> $U$33:$U$38 | W38: =IF(is_cat,comb_rank_norm+COUNTIF(INDIRECT(comb_rank_norm_run_range),comb_rank_norm)-1,"") -> 3 | X38: =IF(is_cat,header_row_id+comb_rank_unique,row_id) -> 46 | Y38: =IF(is_empty,"",INDEX($J:$J,MATCH(row_id,$X:$X,0))) -> Stock Portfolio | Z38: =IF(is_empty,"",IF(is_header,"Tracked",INDEX($K:$K,MATCH(row_id,$X:$X,0)))) -> 0 | AA38: =IF(is_empty,"",IF(is_header,"Budget",INDEX($L:$L,MATCH(row_id,$X:$X,0)))) -> 120186 | AB38: =IF(is_empty,"",IF(is_header,"% Compl.",IFERROR(out_tracked/out_budget,"-"))) -> 0 | AC38: =IF(is_empty,"",IF(is_header,"Remaining",IF(out_budget-out_tracked>0,out_budget-out_tracked,0))) -> 120186 | AD38: =IF(is_empty,"",IF(is_header,"Excess",IF(out_budget-out_tracked<0,out_tracked-out_budget,0))) -> 0
C39: {=IF(C38=-1,-1, IF(C38<income_max_row,C38+1,IF(C38=income_max_row,income_total_row,IF(C38=income_total_row,"/1", IF(C38="/1",expenses_header_row,IF(C38<expenses_max_row,C38+1,IF(C38=expenses_max_row,expenses_total_row,IF(C38=expenses_total_row,"/2",IF(C38="/2",savings_header_row,IF(C38<savings_max_row,C38+1,IF(C38=savings_max_row,savings_total_row,-1)))))))))))} -> 50 | D39: =IF(is_header,row_id,IF(NOT(is_empty),D38,-1)) -> 43 | E39: {=1*OR(row_id=Income_header_row, row_id=expenses_header_row, row_id=savings_header_row)} -> 0 | F39: =1*NOT(OR(is_header, is_total, is_empty)) -> 1 | G39: {=1*OR(row_id=income_total_row, row_id=expenses_total_row, row_id=savings_total_row)} -> 0 | H39: =1*OR(row_id="/1", row_id="/2", row_id=-1) -> 0 | I39: {=IFERROR(INDEX('Budget Planning'!$C:$C,header_row_id),"")} -> Savings | J39: {=IFERROR(INDEX('Budget Planning'!$C:$C,row_id),"")} -> Mcleodganj Trip Fund | K39: {=IF(OR(is_header,is_empty),"",IF(is_total,IF(selected_period="Total Year",SUMPRODUCT(Tracking[Amount],--(TRIM(Tracking[Type])=TRIM(type)),--(Tracking[Date]>=DATE(selected_year,1,1)),--(Tracking[Date]<DATE(selected_year+1,1,1))),SUMPRODUCT(Tracking[Amount],--(TRIM(Tracking[Type])=TRIM(type)),--(Tracking[Date]>=DATE(selected_year,1,1)),--(Tracking[Date]<DATE(selected_year+1,1,1)),--(MONTH(Tracking[Date])=selected_period))),IF(selected_period="Total Year",SUMPRODUCT(Tracking[Amount],--(TRIM(Tracking[Type])=TRIM(type)),--(TRIM(Tracking[Categories])=TRIM(item)),--(Tracking[Date]>=DATE(selected_year,1,1)),--(Tracking[Date]<DATE(selected_year+1,1,1))),SUMPRODUCT(Tracking[Amount],--(TRIM(Tracking[Type])=TRIM(type)),--(TRIM(Tracking[Categories])=TRIM(item)),--(Tracking[Date]>=DATE(selected_year,1,1)),--(Tracking[Date]<DATE(selected_year+1,1,1)),--(MONTH(Tracking[Date])=selected_period)))))} -> 35000 | L39: {=IF(OR(is_header,is_empty),"",INDEX('Budget Planning'!$E:$FA,row_id,MATCH(IF(selected_period="Total Year",selected_year,DATE(selected_year,selected_period,1)),'Budget Planning'!$E$9:$FA$9,0)))} -> 50000 | M39: {=IF(is_cat,IF(header_row_id=Income_header_row, MATCH(income_min_row,$C:$C,0),IF(header_row_id=expenses_header_row, MATCH(expenses_min_row,$C:$C,0),IF(header_row_id=savings_header_row, MATCH(savings_min_row,$C:$C,0),""))),"")} -> 33 | N39: {=IF(is_cat,IF(header_row_id=Income_header_row, MATCH(income_max_row,$C:$C,0),IF(header_row_id=expenses_header_row, MATCH(expenses_max_row,$C:$C,0),IF(header_row_id=savings_header_row, MATCH(savings_max_row,$C:$C,0),""))),"")} -> 41 | O39: =IF(is_cat,ADDRESS(sort_min_row,COLUMN(tracked))&":"&ADDRESS(sort_max_row,COLUMN(tracked)),"") -> $K$33:$K$41 | P39: =IF(is_cat,RANK(tracked,INDIRECT(tracked_range),0),"") -> 2 | Q39: =IF(is_cat,ADDRESS(sort_min_row,COLUMN(budget))&":"&ADDRESS(sort_max_row,COLUMN(budget)),"") -> $L$33:$L$41 | R39: =IF(is_cat,RANK(budget,INDIRECT(budget_range),0),"") -> 6 | S39: =IF(is_cat,_xlfn.NUMBERVALUE(tracked_rank & budget_rank),"") -> 26 | T39: =IF(is_cat,ADDRESS(sort_min_row,COLUMN(comb_rank))&":"&ADDRESS(sort_max_row,COLUMN(comb_rank)),"") -> $S$33:$S$41 | U39: =IF(is_cat, RANK(comb_rank, INDIRECT(comb_rank_range),1),"") -> 2 | V39: =IF(is_cat,ADDRESS(sort_min_row,COLUMN(comb_rank_norm))&":"&ADDRESS(ROW(),COLUMN(comb_rank_norm)),"") -> $U$33:$U$39 | W39: =IF(is_cat,comb_rank_norm+COUNTIF(INDIRECT(comb_rank_norm_run_range),comb_rank_norm)-1,"") -> 2 | X39: =IF(is_cat,header_row_id+comb_rank_unique,row_id) -> 45 | Y39: =IF(is_empty,"",INDEX($J:$J,MATCH(row_id,$X:$X,0))) -> Vietnam Trip Fund | Z39: =IF(is_empty,"",IF(is_header,"Tracked",INDEX($K:$K,MATCH(row_id,$X:$X,0)))) -> 0 | AA39: =IF(is_empty,"",IF(is_header,"Budget",INDEX($L:$L,MATCH(row_id,$X:$X,0)))) -> 90000 | AB39: =IF(is_empty,"",IF(is_header,"% Compl.",IFERROR(out_tracked/out_budget,"-"))) -> 0 | AC39: =IF(is_empty,"",IF(is_header,"Remaining",IF(out_budget-out_tracked>0,out_budget-out_tracked,0))) -> 90000 | AD39: =IF(is_empty,"",IF(is_header,"Excess",IF(out_budget-out_tracked<0,out_tracked-out_budget,0))) -> 0
C40: {=IF(C39=-1,-1, IF(C39<income_max_row,C39+1,IF(C39=income_max_row,income_total_row,IF(C39=income_total_row,"/1", IF(C39="/1",expenses_header_row,IF(C39<expenses_max_row,C39+1,IF(C39=expenses_max_row,expenses_total_row,IF(C39=expenses_total_row,"/2",IF(C39="/2",savings_header_row,IF(C39<savings_max_row,C39+1,IF(C39=savings_max_row,savings_total_row,-1)))))))))))} -> 51 | D40: =IF(is_header,row_id,IF(NOT(is_empty),D39,-1)) -> 43 | E40: {=1*OR(row_id=Income_header_row, row_id=expenses_header_row, row_id=savings_header_row)} -> 0 | F40: =1*NOT(OR(is_header, is_total, is_empty)) -> 1 | G40: {=1*OR(row_id=income_total_row, row_id=expenses_total_row, row_id=savings_total_row)} -> 0 | H40: =1*OR(row_id="/1", row_id="/2", row_id=-1) -> 0 | I40: {=IFERROR(INDEX('Budget Planning'!$C:$C,header_row_id),"")} -> Savings | J40: {=IFERROR(INDEX('Budget Planning'!$C:$C,row_id),"")} -> Sri Lanka Trip Fund | K40: {=IF(OR(is_header,is_empty),"",IF(is_total,IF(selected_period="Total Year",SUMPRODUCT(Tracking[Amount],--(TRIM(Tracking[Type])=TRIM(type)),--(Tracking[Date]>=DATE(selected_year,1,1)),--(Tracking[Date]<DATE(selected_year+1,1,1))),SUMPRODUCT(Tracking[Amount],--(TRIM(Tracking[Type])=TRIM(type)),--(Tracking[Date]>=DATE(selected_year,1,1)),--(Tracking[Date]<DATE(selected_year+1,1,1)),--(MONTH(Tracking[Date])=selected_period))),IF(selected_period="Total Year",SUMPRODUCT(Tracking[Amount],--(TRIM(Tracking[Type])=TRIM(type)),--(TRIM(Tracking[Categories])=TRIM(item)),--(Tracking[Date]>=DATE(selected_year,1,1)),--(Tracking[Date]<DATE(selected_year+1,1,1))),SUMPRODUCT(Tracking[Amount],--(TRIM(Tracking[Type])=TRIM(type)),--(TRIM(Tracking[Categories])=TRIM(item)),--(Tracking[Date]>=DATE(selected_year,1,1)),--(Tracking[Date]<DATE(selected_year+1,1,1)),--(MONTH(Tracking[Date])=selected_period)))))} -> 0 | L40: {=IF(OR(is_header,is_empty),"",INDEX('Budget Planning'!$E:$FA,row_id,MATCH(IF(selected_period="Total Year",selected_year,DATE(selected_year,selected_period,1)),'Budget Planning'!$E$9:$FA$9,0)))} -> 65000 | M40: {=IF(is_cat,IF(header_row_id=Income_header_row, MATCH(income_min_row,$C:$C,0),IF(header_row_id=expenses_header_row, MATCH(expenses_min_row,$C:$C,0),IF(header_row_id=savings_header_row, MATCH(savings_min_row,$C:$C,0),""))),"")} -> 33 | N40: {=IF(is_cat,IF(header_row_id=Income_header_row, MATCH(income_max_row,$C:$C,0),IF(header_row_id=expenses_header_row, MATCH(expenses_max_row,$C:$C,0),IF(header_row_id=savings_header_row, MATCH(savings_max_row,$C:$C,0),""))),"")} -> 41 | O40: =IF(is_cat,ADDRESS(sort_min_row,COLUMN(tracked))&":"&ADDRESS(sort_max_row,COLUMN(tracked)),"") -> $K$33:$K$41 | P40: =IF(is_cat,RANK(tracked,INDIRECT(tracked_range),0),"") -> 6 | Q40: =IF(is_cat,ADDRESS(sort_min_row,COLUMN(budget))&":"&ADDRESS(sort_max_row,COLUMN(budget)),"") -> $L$33:$L$41 | R40: =IF(is_cat,RANK(budget,INDIRECT(budget_range),0),"") -> 5 | S40: =IF(is_cat,_xlfn.NUMBERVALUE(tracked_rank & budget_rank),"") -> 65 | T40: =IF(is_cat,ADDRESS(sort_min_row,COLUMN(comb_rank))&":"&ADDRESS(sort_max_row,COLUMN(comb_rank)),"") -> $S$33:$S$41 | U40: =IF(is_cat, RANK(comb_rank, INDIRECT(comb_rank_range),1),"") -> 8 | V40: =IF(is_cat,ADDRESS(sort_min_row,COLUMN(comb_rank_norm))&":"&ADDRESS(ROW(),COLUMN(comb_rank_norm)),"") -> $U$33:$U$40 | W40: =IF(is_cat,comb_rank_norm+COUNTIF(INDIRECT(comb_rank_norm_run_range),comb_rank_norm)-1,"") -> 8 | X40: =IF(is_cat,header_row_id+comb_rank_unique,row_id) -> 51 | Y40: =IF(is_empty,"",INDEX($J:$J,MATCH(row_id,$X:$X,0))) -> Sri Lanka Trip Fund | Z40: =IF(is_empty,"",IF(is_header,"Tracked",INDEX($K:$K,MATCH(row_id,$X:$X,0)))) -> 0 | AA40: =IF(is_empty,"",IF(is_header,"Budget",INDEX($L:$L,MATCH(row_id,$X:$X,0)))) -> 65000 | AB40: =IF(is_empty,"",IF(is_header,"% Compl.",IFERROR(out_tracked/out_budget,"-"))) -> 0 | AC40: =IF(is_empty,"",IF(is_header,"Remaining",IF(out_budget-out_tracked>0,out_budget-out_tracked,0))) -> 65000 | AD40: =IF(is_empty,"",IF(is_header,"Excess",IF(out_budget-out_tracked<0,out_tracked-out_budget,0))) -> 0
C41: {=IF(C40=-1,-1, IF(C40<income_max_row,C40+1,IF(C40=income_max_row,income_total_row,IF(C40=income_total_row,"/1", IF(C40="/1",expenses_header_row,IF(C40<expenses_max_row,C40+1,IF(C40=expenses_max_row,expenses_total_row,IF(C40=expenses_total_row,"/2",IF(C40="/2",savings_header_row,IF(C40<savings_max_row,C40+1,IF(C40=savings_max_row,savings_total_row,-1)))))))))))} -> 52 | D41: =IF(is_header,row_id,IF(NOT(is_empty),D40,-1)) -> 43 | E41: {=1*OR(row_id=Income_header_row, row_id=expenses_header_row, row_id=savings_header_row)} -> 0 | F41: =1*NOT(OR(is_header, is_total, is_empty)) -> 1 | G41: {=1*OR(row_id=income_total_row, row_id=expenses_total_row, row_id=savings_total_row)} -> 0 | H41: =1*OR(row_id="/1", row_id="/2", row_id=-1) -> 0 | I41: {=IFERROR(INDEX('Budget Planning'!$C:$C,header_row_id),"")} -> Savings | J41: {=IFERROR(INDEX('Budget Planning'!$C:$C,row_id),"")} -> Vietnam Trip Fund | K41: {=IF(OR(is_header,is_empty),"",IF(is_total,IF(selected_period="Total Year",SUMPRODUCT(Tracking[Amount],--(TRIM(Tracking[Type])=TRIM(type)),--(Tracking[Date]>=DATE(selected_year,1,1)),--(Tracking[Date]<DATE(selected_year+1,1,1))),SUMPRODUCT(Tracking[Amount],--(TRIM(Tracking[Type])=TRIM(type)),--(Tracking[Date]>=DATE(selected_year,1,1)),--(Tracking[Date]<DATE(selected_year+1,1,1)),--(MONTH(Tracking[Date])=selected_period))),IF(selected_period="Total Year",SUMPRODUCT(Tracking[Amount],--(TRIM(Tracking[Type])=TRIM(type)),--(TRIM(Tracking[Categories])=TRIM(item)),--(Tracking[Date]>=DATE(selected_year,1,1)),--(Tracking[Date]<DATE(selected_year+1,1,1))),SUMPRODUCT(Tracking[Amount],--(TRIM(Tracking[Type])=TRIM(type)),--(TRIM(Tracking[Categories])=TRIM(item)),--(Tracking[Date]>=DATE(selected_year,1,1)),--(Tracking[Date]<DATE(selected_year+1,1,1)),--(MONTH(Tracking[Date])=selected_period)))))} -> 0 | L41: {=IF(OR(is_header,is_empty),"",INDEX('Budget Planning'!$E:$FA,row_id,MATCH(IF(selected_period="Total Year",selected_year,DATE(selected_year,selected_period,1)),'Budget Planning'!$E$9:$FA$9,0)))} -> 90000 | M41: {=IF(is_cat,IF(header_row_id=Income_header_row, MATCH(income_min_row,$C:$C,0),IF(header_row_id=expenses_header_row, MATCH(expenses_min_row,$C:$C,0),IF(header_row_id=savings_header_row, MATCH(savings_min_row,$C:$C,0),""))),"")} -> 33 | N41: {=IF(is_cat,IF(header_row_id=Income_header_row, MATCH(income_max_row,$C:$C,0),IF(header_row_id=expenses_header_row, MATCH(expenses_max_row,$C:$C,0),IF(header_row_id=savings_header_row, MATCH(savings_max_row,$C:$C,0),""))),"")} -> 41 | O41: =IF(is_cat,ADDRESS(sort_min_row,COLUMN(tracked))&":"&ADDRESS(sort_max_row,COLUMN(tracked)),"") -> $K$33:$K$41 | P41: =IF(is_cat,RANK(tracked,INDIRECT(tracked_range),0),"") -> 6 | Q41: =IF(is_cat,ADDRESS(sort_min_row,COLUMN(budget))&":"&ADDRESS(sort_max_row,COLUMN(budget)),"") -> $L$33:$L$41 | R41: =IF(is_cat,RANK(budget,INDIRECT(budget_range),0),"") -> 4 | S41: =IF(is_cat,_xlfn.NUMBERVALUE(tracked_rank & budget_rank),"") -> 64 | T41: =IF(is_cat,ADDRESS(sort_min_row,COLUMN(comb_rank))&":"&ADDRESS(sort_max_row,COLUMN(comb_rank)),"") -> $S$33:$S$41 | U41: =IF(is_cat, RANK(comb_rank, INDIRECT(comb_rank_range),1),"") -> 7 | V41: =IF(is_cat,ADDRESS(sort_min_row,COLUMN(comb_rank_norm))&":"&ADDRESS(ROW(),COLUMN(comb_rank_norm)),"") -> $U$33:$U$41 | W41: =IF(is_cat,comb_rank_norm+COUNTIF(INDIRECT(comb_rank_norm_run_range),comb_rank_norm)-1,"") -> 7 | X41: =IF(is_cat,header_row_id+comb_rank_unique,row_id) -> 50 | Y41: =IF(is_empty,"",INDEX($J:$J,MATCH(row_id,$X:$X,0))) -> Crpto | Z41: =IF(is_empty,"",IF(is_header,"Tracked",INDEX($K:$K,MATCH(row_id,$X:$X,0)))) -> 0 | AA41: =IF(is_empty,"",IF(is_header,"Budget",INDEX($L:$L,MATCH(row_id,$X:$X,0)))) -> 41359 | AB41: =IF(is_empty,"",IF(is_header,"% Compl.",IFERROR(out_tracked/out_budget,"-"))) -> 0 | AC41: =IF(is_empty,"",IF(is_header,"Remaining",IF(out_budget-out_tracked>0,out_budget-out_tracked,0))) -> 41359 | AD41: =IF(is_empty,"",IF(is_header,"Excess",IF(out_budget-out_tracked<0,out_tracked-out_budget,0))) -> 0
C42: {=IF(C41=-1,-1, IF(C41<income_max_row,C41+1,IF(C41=income_max_row,income_total_row,IF(C41=income_total_row,"/1", IF(C41="/1",expenses_header_row,IF(C41<expenses_max_row,C41+1,IF(C41=expenses_max_row,expenses_total_row,IF(C41=expenses_total_row,"/2",IF(C41="/2",savings_header_row,IF(C41<savings_max_row,C41+1,IF(C41=savings_max_row,savings_total_row,-1)))))))))))} -> 58 | D42: =IF(is_header,row_id,IF(NOT(is_empty),D41,-1)) -> 43 | E42: {=1*OR(row_id=Income_header_row, row_id=expenses_header_row, row_id=savings_header_row)} -> 0 | F42: =1*NOT(OR(is_header, is_total, is_empty)) -> 0 | G42: {=1*OR(row_id=income_total_row, row_id=expenses_total_row, row_id=savings_total_row)} -> 1 | H42: =1*OR(row_id="/1", row_id="/2", row_id=-1) -> 0 | I42: {=IFERROR(INDEX('Budget Planning'!$C:$C,header_row_id),"")} -> Savings | J42: {=IFERROR(INDEX('Budget Planning'!$C:$C,row_id),"")} -> Total | K42: {=IF(OR(is_header,is_empty),"",IF(is_total,IF(selected_period="Total Year",SUMPRODUCT(Tracking[Amount],--(TRIM(Tracking[Type])=TRIM(type)),--(Tracking[Date]>=DATE(selected_year,1,1)),--(Tracking[Date]<DATE(selected_year+1,1,1))),SUMPRODUCT(Tracking[Amount],--(TRIM(Tracking[Type])=TRIM(type)),--(Tracking[Date]>=DATE(selected_year,1,1)),--(Tracking[Date]<DATE(selected_year+1,1,1)),--(MONTH(Tracking[Date])=selected_period))),IF(selected_period="Total Year",SUMPRODUCT(Tracking[Amount],--(TRIM(Tracking[Type])=TRIM(type)),--(TRIM(Tracking[Categories])=TRIM(item)),--(Tracking[Date]>=DATE(selected_year,1,1)),--(Tracking[Date]<DATE(selected_year+1,1,1))),SUMPRODUCT(Tracking[Amount],--(TRIM(Tracking[Type])=TRIM(type)),--(TRIM(Tracking[Categories])=TRIM(item)),--(Tracking[Date]>=DATE(selected_year,1,1)),--(Tracking[Date]<DATE(selected_year+1,1,1)),--(MONTH(Tracking[Date])=selected_period)))))} -> 111686 | L42: {=IF(OR(is_header,is_empty),"",INDEX('Budget Planning'!$E:$FA,row_id,MATCH(IF(selected_period="Total Year",selected_year,DATE(selected_year,selected_period,1)),'Budget Planning'!$E$9:$FA$9,0)))} -> 800045 | M42: {=IF(is_cat,IF(header_row_id=Income_header_row, MATCH(income_min_row,$C:$C,0),IF(header_row_id=expenses_header_row, MATCH(expenses_min_row,$C:$C,0),IF(header_row_id=savings_header_row, MATCH(savings_min_row,$C:$C,0),""))),"")} | N42: {=IF(is_cat,IF(header_row_id=Income_header_row, MATCH(income_max_row,$C:$C,0),IF(header_row_id=expenses_header_row, MATCH(expenses_max_row,$C:$C,0),IF(header_row_id=savings_header_row, MATCH(savings_max_row,$C:$C,0),""))),"")} | O42: =IF(is_cat,ADDRESS(sort_min_row,COLUMN(tracked))&":"&ADDRESS(sort_max_row,COLUMN(tracked)),"") | P42: =IF(is_cat,RANK(tracked,INDIRECT(tracked_range),0),"") | Q42: =IF(is_cat,ADDRESS(sort_min_row,COLUMN(budget))&":"&ADDRESS(sort_max_row,COLUMN(budget)),"") | R42: =IF(is_cat,RANK(budget,INDIRECT(budget_range),0),"") | S42: =IF(is_cat,_xlfn.NUMBERVALUE(tracked_rank & budget_rank),"") | T42: =IF(is_cat,ADDRESS(sort_min_row,COLUMN(comb_rank))&":"&ADDRESS(sort_max_row,COLUMN(comb_rank)),"") | U42: =IF(is_cat, RANK(comb_rank, INDIRECT(comb_rank_range),1),"") | V42: =IF(is_cat,ADDRESS(sort_min_row,COLUMN(comb_rank_norm))&":"&ADDRESS(ROW(),COLUMN(comb_rank_norm)),"") | W42: =IF(is_cat,comb_rank_norm+COUNTIF(INDIRECT(comb_rank_norm_run_range),comb_rank_norm)-1,"") | X42: =IF(is_cat,header_row_id+comb_rank_unique,row_id) -> 58 | Y42: =IF(is_empty,"",INDEX($J:$J,MATCH(row_id,$X:$X,0))) -> Total | Z42: =IF(is_empty,"",IF(is_header,"Tracked",INDEX($K:$K,MATCH(row_id,$X:$X,0)))) -> 111686 | AA42: =IF(is_empty,"",IF(is_header,"Budget",INDEX($L:$L,MATCH(row_id,$X:$X,0)))) -> 800045 | AB42: =IF(is_empty,"",IF(is_header,"% Compl.",IFERROR(out_tracked/out_budget,"-"))) -> 0.13959965 | AC42: =IF(is_empty,"",IF(is_header,"Remaining",IF(out_budget-out_tracked>0,out_budget-out_tracked,0))) -> 688359 | AD42: =IF(is_empty,"",IF(is_header,"Excess",IF(out_budget-out_tracked<0,out_tracked-out_budget,0))) -> 0
